Workbook
Name F_borne1: PIVOT!$J$76
Name F_borne2: PIVOT!$K$76
Name M_Borne1: PIVOT!$J$75
Name M_borne2: PIVOT!$K$75
Name R_borne1: PIVOT!$J$74
Name R_borne2: PIVOT!$K$74
Name Segment_Education: #N/A
Name Segment_Segment_RFM: #N/A
Name Segment_Tranche_âge: #N/A

Sheet RAW
A1: ID | B1: Year_Birth | C1: Education | D1: Marital_Status | E1: Income | F1: Kidhome | G1: Teenhome | H1: Dt_Customer | I1: Recency | J1: MntWines | K1: MntFruits | L1: MntMeatProducts | M1: MntFishProducts | N1: MntSweetProducts | O1: MntGoldProds | P1: NumDealsPurchases | Q1: NumWebPurchases | R1: NumCatalogPurchases | S1: NumStorePurchases | T1: NumWebVisitsMonth | U1: AcceptedCmp3 | V1: AcceptedCmp4 | W1: AcceptedCmp5 | X1: AcceptedCmp1 | Y1: AcceptedCmp2 | Z1: Complain | AA1: Z_CostContact | AB1: Z_Revenue | AC1: Response
A2: 5524 | B2: 1957 | C2: Graduation | D2: Single | E2: 58138 | F2: 0 | G2: 0 | H2: 04-09-2012 | I2: 58 | J2: 635 | K2: 88 | L2: 546 | M2: 172 | N2: 88 | O2: 88 | P2: 3 | Q2: 8 | R2: 10 | S2: 4 | T2: 7 | U2: 0 | V2: 0 | W2: 0 | X2: 0 | Y2: 0 | Z2: 0 | AA2: 3 | AB2: 11 | AC2: 1
A3: 2174 | B3: 1954 | C3: Graduation | D3: Single | E3: 46344 | F3: 1 | G3: 1 | H3: 08-03-2014 | I3: 38 | J3: 11 | K3: 1 | L3: 6 | M3: 2 | N3: 1 | O3: 6 | P3: 2 | Q3: 1 | R3: 1 | S3: 2 | T3: 5 | U3: 0 | V3: 0 | W3: 0 | X3: 0 | Y3: 0 | Z3: 0 | AA3: 3 | AB3: 11 | AC3: 0
A4: 4141 | B4: 1965 | C4: Graduation | D4: Together | E4: 71613 | F4: 0 | G4: 0 | H4: 21-08-2013 | I4: 26 | J4: 426 | K4: 49 | L4: 127 | M4: 111 | N4: 21 | O4: 42 | P4: 1 | Q4: 8 | R4: 2 | S4: 10 | T4: 4 | U4: 0 | V4: 0 | W4: 0 | X4: 0 | Y4: 0 | Z4: 0 | AA4: 3 | AB4: 11 | AC4: 0
A5: 6182 | B5: 1984 | C5: Graduation | D5: Together | E5: 26646 | F5: 1 | G5: 0 | H5: 10-02-2014 | I5: 26 | J5: 11 | K5: 4 | L5: 20 | M5: 10 | N5: 3 | O5: 5 | P5: 2 | Q5: 2 | R5: 0 | S5: 4 | T5: 6 | U5: 0 | V5: 0 | W5: 0 | X5: 0 | Y5: 0 | Z5: 0 | AA5: 3 | AB5: 11 | AC5: 0
A6: 5324 | B6: 1981 | C6: PhD | D6: Married | E6: 58293 | F6: 1 | G6: 0 | H6: 19-01-2014 | I6: 94 | J6: 173 | K6: 43 | L6: 118 | M6: 46 | N6: 27 | O6: 15 | P6: 5 | Q6: 5 | R6: 3 | S6: 6 | T6: 5 | U6: 0 | V6: 0 | W6: 0 | X6: 0 | Y6: 0 | Z6: 0 | AA6: 3 | AB6: 11 | AC6: 0
A7: 7446 | B7: 1967 | C7: Master | D7: Together | E7: 62513 | F7: 0 | G7: 1 | H7: 09-09-2013 | I7: 16 | J7: 520 | K7: 42 | L7: 98 | M7: 0 | N7: 42 | O7: 14 | P7: 2 | Q7: 6 | R7: 4 | S7: 10 | T7: 6 | U7: 0 | V7: 0 | W7: 0 | X7: 0 | Y7: 0 | Z7: 0 | AA7: 3 | AB7: 11 | AC7: 0
A8: 965 | B8: 1971 | C8: Graduation | D8: Divorced | E8: 55635 | F8: 0 | G8: 1 | H8: 13-11-2012 | I8: 34 | J8: 235 | K8: 65 | L8: 164 | M8: 50 | N8: 49 | O8: 27 | P8: 4 | Q8: 7 | R8: 3 | S8: 7 | T8: 6 | U8: 0 | V8: 0 | W8: 0 | X8: 0 | Y8: 0 | Z8: 0 | AA8: 3 | AB8: 11 | AC8: 0
A9: 6177 | B9: 1985 | C9: PhD | D9: Married | E9: 33454 | F9: 1 | G9: 0 | H9: 08-05-2013 | I9: 32 | J9: 76 | K9: 10 | L9: 56 | M9: 3 | N9: 1 | O9: 23 | P9: 2 | Q9: 4 | R9: 0 | S9: 4 | T9: 8 | U9: 0 | V9: 0 | W9: 0 | X9: 0 | Y9: 0 | Z9: 0 | AA9: 3 | AB9: 11 | AC9: 0
A10: 4855 | B10: 1974 | C10: PhD | D10: Together | E10: 30351 | F10: 1 | G10: 0 | H10: 06-06-2013 | I10: 19 | J10: 14 | K10: 0 | L10: 24 | M10: 3 | N10: 3 | O10: 2 | P10: 1 | Q10: 3 | R10: 0 | S10: 2 | T10: 9 | U10: 0 | V10: 0 | W10: 0 | X10: 0 | Y10: 0 | Z10: 0 | AA10: 3 | AB10: 11 | AC10: 1
A11: 5899 | B11: 1950 | C11: PhD | D11: Together | E11: 5648 | F11: 1 | G11: 1 | H11: 13-03-2014 | I11: 68 | J11: 28 | K11: 0 | L11: 6 | M11: 1 | N11: 1 | O11: 13 | P11: 1 | Q11: 1 | R11: 0 | S11: 0 | T11: 20 | U11: 1 | V11: 0 | W11: 0 | X11: 0 | Y11: 0 | Z11: 0 | AA11: 3 | AB11: 11 | AC11: 0
A12: 1994 | B12: 1983 | C12: Graduation | D12: Married | F12: 1 | G12: 0 | H12: 15-11-2013 | I12: 11 | J12: 5 | K12: 5 | L12: 6 | M12: 0 | N12: 2 | O12: 1 | P12: 1 | Q12: 1 | R12: 0 | S12: 2 | T12: 7 | U12: 0 | V12: 0 | W12: 0 | X12: 0 | Y12: 0 | Z12: 0 | AA12: 3 | AB12: 11 | AC12: 0
A13: 387 | B13: 1976 | C13: Basic | D13: Married | E13: 7500 | F13: 0 | G13: 0 | H13: 13-11-2012 | I13: 59 | J13: 6 | K13: 16 | L13: 11 | M13: 11 | N13: 1 | O13: 16 | P13: 1 | Q13: 2 | R13: 0 | S13: 3 | T13: 8 | U13: 0 | V13: 0 | W13: 0 | X13: 0 | Y13: 0 | Z13: 0 | AA13: 3 | AB13: 11 | AC13: 0
A14: 2125 | B14: 1959 | C14: Graduation | D14: Divorced | E14: 63033 | F14: 0 | G14: 0 | H14: 15-11-2013 | I14: 82 | J14: 194 | K14: 61 | L14: 480 | M14: 225 | N14: 112 | O14: 30 | P14: 1 | Q14: 3 | R14: 4 | S14: 8 | T14: 2 | U14: 0 | V14: 0 | W14: 0 | X14: 0 | Y14: 0 | Z14: 0 | AA14: 3 | AB14: 11 | AC14: 0
A15: 8180 | B15: 1952 | C15: Master | D15: Divorced | E15: 59354 | F15: 1 | G15: 1 | H15: 15-11-2013 | I15: 53 | J15: 233 | K15: 2 | L15: 53 | M15: 3 | N15: 5 | O15: 14 | P15: 3 | Q15: 6 | R15: 1 | S15: 5 | T15: 6 | U15: 0 | V15: 0 | W15: 0 | X15: 0 | Y15: 0 | Z15: 0 | AA15: 3 | AB15: 11 | AC15: 0
A16: 2569 | B16: 1987 | C16: Graduation | D16: Married | E16: 17323 | F16: 0 | G16: 0 | H16: 10-10-2012 | I16: 38 | J16: 3 | K16: 14 | L16: 17 | M16: 6 | N16: 1 | O16: 5 | P16: 1 | Q16: 1 | R16: 0 | S16: 3 | T16: 8 | U16: 0 | V16: 0 | W16: 0 | X16: 0 | Y16: 0 | Z16: 0 | AA16: 3 | AB16: 11 | AC16: 0
A17: 2114 | B17: 1946 | C17: PhD | D17: Single | E17: 82800 | F17: 0 | G17: 0 | H17: 24-11-2012 | I17: 23 | J17: 1006 | K17: 22 | L17: 115 | M17: 59 | N17: 68 | O17: 45 | P17: 1 | Q17: 7 | R17: 6 | S17: 12 | T17: 3 | U17: 0 | V17: 0 | W17: 1 | X17: 1 | Y17: 0 | Z17: 0 | AA17: 3 | AB17: 11 | AC17: 1
A18: 9736 | B18: 1980 | C18: Graduation | D18: Married | E18: 41850 | F18: 1 | G18: 1 | H18: 24-12-2012 | I18: 51 | J18: 53 | K18: 5 | L18: 19 | M18: 2 | N18: 13 | O18: 4 | P18: 3 | Q18: 3 | R18: 0 | S18: 3 | T18: 8 | U18: 0 | V18: 0 | W18: 0 | X18: 0 | Y18: 0 | Z18: 0 | AA18: 3 | AB18: 11 | AC18: 0
A19: 4939 | B19: 1946 | C19: Graduation | D19: Together | E19: 37760 | F19: 0 | G19: 0 | H19: 31-08-2012 | I19: 20 | J19: 84 | K19: 5 | L19: 38 | M19: 150 | N19: 12 | O19: 28 | P19: 2 | Q19: 4 | R19: 1 | S19: 6 | T19: 7 | U19: 0 | V19: 0 | W19: 0 | X19: 0 | Y19: 0 | Z19: 0 | AA19: 3 | AB19: 11 | AC19: 0
A20: 6565 | B20: 1949 | C20: Master | D20: Married | E20: 76995 | F20: 0 | G20: 1 | H20: 28-03-2013 | I20: 91 | J20: 1012 | K20: 80 | L20: 498 | M20: 0 | N20: 16 | O20: 176 | P20: 2 | Q20: 11 | R20: 4 | S20: 9 | T20: 5 | U20: 0 | V20: 0 | W20: 0 | X20: 1 | Y20: 0 | Z20: 0 | AA20: 3 | AB20: 11 | AC20: 0
A21: 2278 | B21: 1985 | C21: 2n Cycle | D21: Single | E21: 33812 | F21: 1 | G21: 0 | H21: 03-11-2012 | I21: 86 | J21: 4 | K21: 17 | L21: 19 | M21: 30 | N21: 24 | O21: 39 | P21: 2 | Q21: 2 | R21: 1 | S21: 3 | T21: 6 | U21: 0 | V21: 0 | W21: 0 | X21: 0 | Y21: 0 | Z21: 0 | AA21: 3 | AB21: 11 | AC21: 0
A22: 9360 | B22: 1982 | C22: Graduation | D22: Married | E22: 37040 | F22: 0 | G22: 0 | H22: 08-08-2012 | I22: 41 | J22: 86 | K22: 2 | L22: 73 | M22: 69 | N22: 38 | O22: 48 | P22: 1 | Q22: 4 | R22: 2 | S22: 5 | T22: 8 | U22: 0 | V22: 0 | W22: 0 | X22: 0 | Y22: 0 | Z22: 0 | AA22: 3 | AB22: 11 | AC22: 0
A23: 5376 | B23: 1979 | C23: Graduation | D23: Married | E23: 2447 | F23: 1 | G23: 0 | H23: 06-01-2013 | I23: 42 | J23: 1 | K23: 1 | L23: 1725 | M23: 1 | N23: 1 | O23: 1 | P23: 15 | Q23: 0 | R23: 28 | S23: 0 | T23: 1 | U23: 0 | V23: 0 | W23: 0 | X23: 0 | Y23: 0 | Z23: 0 | AA23: 3 | AB23: 11 | AC23: 0
A24: 1993 | B24: 1949 | C24: PhD | D24: Married | E24: 58607 | F24: 0 | G24: 1 | H24: 23-12-2012 | I24: 63 | J24: 867 | K24: 0 | L24: 86 | M24: 0 | N24: 0 | O24: 19 | P24: 3 | Q24: 2 | R24: 3 | S24: 9 | T24: 8 | U24: 0 | V24: 1 | W24: 0 | X24: 0 | Y24: 0 | Z24: 0 | AA24: 3 | AB24: 11 | AC24: 0
... A28: 2404 | B28: 1976 | C28: Graduation | D28: Married | E28: 53359 | F28: 1 | G28: 1 | H28: 27-05-2013 | I28: 4 | J28: 173 | K28: 4 | L28: 30 | M28: 3 | N28: 6 | O28: 41 | P28: 4 | Q28: 5 | R28: 1 | S28: 4 | T28: 7 | U28: 0 | V28: 0 | W28: 0 | X28: 0 | Y28: 0 | Z28: 0 | AA28: 3 | AB28: 11 | AC28: 0
A29: 5255 | B29: 1986 | C29: Graduation | D29: Single | F29: 1 | G29: 0 | H29: 20-02-2013 | I29: 19 | J29: 5 | K29: 1 | L29: 3 | M29: 3 | N29: 263 | O29: 362 | P29: 0 | Q29: 27 | R29: 0 | S29: 0 | T29: 1 | U29: 0 | V29: 0 | W29: 0 | X29: 0 | Y29: 0 | Z29: 0 | AA29: 3 | AB29: 11 | AC29: 0
A30: 9422 | B30: 1989 | C30: Graduation | D30: Married | E30: 38360 | F30: 1 | G30: 0 | H30: 31-05-2013 | I30: 26 | J30: 36 | K30: 2 | L30: 42 | M30: 20 | N30: 21 | O30: 10 | P30: 2 | Q30: 2 | R30: 1 | S30: 4 | T30: 3 | U30: 0 | V30: 0 | W30: 0 | X30: 0 | Y30: 0 | Z30: 0 | AA30: 3 | AB30: 11 | AC30: 0
A31: 1966 | B31: 1965 | C31: PhD | D31: Married | E31: 84618 | F31: 0 | G31: 0 | H31: 22-11-2013 | I31: 96 | J31: 684 | K31: 100 | L31: 801 | M31: 21 | N31: 66 | O31: 0 | P31: 1 | Q31: 6 | R31: 9 | S31: 10 | T31: 2 | U31: 0 | V31: 0 | W31: 1 | X31: 0 | Y31: 0 | Z31: 0 | AA31: 3 | AB31: 11 | AC31: 0
A32: 6864 | B32: 1989 | C32: Master | D32: Divorced | E32: 10979 | F32: 0 | G32: 0 | H32: 22-05-2014 | I32: 34 | J32: 8 | K32: 4 | L32: 10 | M32: 2 | N32: 2 | O32: 4 | P32: 2 | Q32: 3 | R32: 0 | S32: 3 | T32: 5 | U32: 0 | V32: 0 | W32: 0 | X32: 0 | Y32: 0 | Z32: 0 | AA32: 3 | AB32: 11 | AC32: 0
A33: 3033 | B33: 1963 | C33: Master | D33: Together | E33: 38620 | F33: 0 | G33: 0 | H33: 11-05-2013 | I33: 56 | J33: 112 | K33: 17 | L33: 44 | M33: 34 | N33: 22 | O33: 89 | P33: 1 | Q33: 2 | R33: 5 | S33: 3 | T33: 3 | U33: 0 | V33: 0 | W33: 0 | X33: 0 | Y33: 0 | Z33: 0 | AA33: 3 | AB33: 11 | AC33: 0
A34: 5710 | B34: 1970 | C34: Graduation | D34: Together | E34: 40548 | F34: 0 | G34: 1 | H34: 10-10-2012 | I34: 31 | J34: 110 | K34: 0 | L34: 5 | M34: 2 | N34: 0 | O34: 3 | P34: 2 | Q34: 2 | R34: 1 | S34: 4 | T34: 5 | U34: 0 | V34: 1 | W34: 0 | X34: 0 | Y34: 0 | Z34: 0 | AA34: 3 | AB34: 11 | AC34: 0
A35: 7373 | B35: 1952 | C35: PhD | D35: Divorced | E35: 46610 | F35: 0 | G35: 2 | H35: 29-10-2012 | I35: 8 | J35: 96 | K35: 12 | L35: 96 | M35: 33 | N35: 22 | O35: 43 | P35: 6 | Q35: 4 | R35: 1 | S35: 6 | T35: 6 | U35: 0 | V35: 0 | W35: 0 | X35: 0 | Y35: 0 | Z35: 0 | AA35: 3 | AB35: 11 | AC35: 1
A36: 8755 | B36: 1946 | C36: Master | D36: Married | E36: 68657 | F36: 0 | G36: 0 | H36: 20-02-2013 | I36: 4 | J36: 482 | K36: 34 | L36: 471 | M36: 119 | N36: 68 | O36: 22 | P36: 1 | Q36: 3 | R36: 5 | S36: 9 | T36: 7 | U36: 0 | V36: 0 | W36: 0 | X36: 0 | Y36: 0 | Z36: 0 | AA36: 3 | AB36: 11 | AC36: 0
A37: 10738 | B37: 1951 | C37: Master | D37: Single | E37: 49389 | F37: 1 | G37: 1 | H37: 29-08-2013 | I37: 55 | J37: 40 | K37: 0 | L37: 19 | M37: 2 | N37: 1 | O37: 3 | P37: 1 | Q37: 2 | R37: 0 | S37: 3 | T37: 7 | U37: 0 | V37: 0 | W37: 0 | X37: 0 | Y37: 0 | Z37: 0 | AA37: 3 | AB37: 11 | AC37: 0
A38: 4339 | B38: 1970 | C38: PhD | D38: Married | E38: 67353 | F38: 0 | G38: 1 | H38: 31-12-2013 | I38: 37 | J38: 702 | K38: 17 | L38: 151 | M38: 0 | N38: 8 | O38: 35 | P38: 5 | Q38: 5 | R38: 6 | S38: 12 | T38: 2 | U38: 0 | V38: 0 | W38: 0 | X38: 0 | Y38: 0 | Z38: 0 | AA38: 3 | AB38: 11 | AC38: 0
A39: 10755 | B39: 1976 | C39: 2n Cycle | D39: Married | E39: 23718 | F39: 1 | G39: 0 | H39: 02-09-2013 | I39: 76 | J39: 6 | K39: 3 | L39: 14 | M39: 15 | N39: 7 | O39: 36 | P39: 3 | Q39: 3 | R39: 1 | S39: 2 | T39: 7 | U39: 0 | V39: 0 | W39: 0 | X39: 0 | Y39: 0 | Z39: 0 | AA39: 3 | AB39: 11 | AC39: 0
A40: 8595 | B40: 1973 | C40: Graduation | D40: Widow | E40: 42429 | F40: 0 | G40: 1 | H40: 11-02-2014 | I40: 99 | J40: 55 | K40: 0 | L40: 6 | M40: 2 | N40: 0 | O40: 4 | P40: 2 | Q40: 1 | R40: 1 | S40: 3 | T40: 5 | U40: 0 | V40: 0 | W40: 0 | X40: 0 | Y40: 0 | Z40: 0 | AA40: 3 | AB40: 11 | AC40: 0
A41: 2968 | B41: 1943 | C41: PhD | D41: Divorced | E41: 48948 | F41: 0 | G41: 0 | H41: 01-02-2013 | I41: 53 | J41: 437 | K41: 8 | L41: 206 | M41: 160 | N41: 49 | O41: 42 | P41: 2 | Q41: 7 | R41: 10 | S41: 5 | T41: 6 | U41: 1 | V41: 0 | W41: 0 | X41: 0 | Y41: 0 | Z41: 0 | AA41: 3 | AB41: 11 | AC41: 1
... A44: 8430 | B44: 1957 | C44: Graduation | D44: Together | E44: 21994 | F44: 0 | G44: 1 | H44: 24-12-2012 | I44: 4 | J44: 9 | K44: 0 | L44: 6 | M44: 3 | N44: 1 | O44: 3 | P44: 1 | Q44: 0 | R44: 0 | S44: 3 | T44: 5 | U44: 0 | V44: 0 | W44: 0 | X44: 0 | Y44: 0 | Z44: 0 | AA44: 3 | AB44: 11 | AC44: 0
A45: 7281 | B45: 1959 | C45: PhD | D45: Single | F45: 0 | G45: 0 | H45: 05-11-2013 | I45: 80 | J45: 81 | K45: 11 | L45: 50 | M45: 3 | N45: 2 | O45: 39 | P45: 1 | Q45: 1 | R45: 3 | S45: 4 | T45: 2 | U45: 0 | V45: 0 | W45: 0 | X45: 0 | Y45: 0 | Z45: 0 | AA45: 3 | AB45: 11 | AC45: 0
A46: 2139 | B46: 1975 | C46: Master | D46: Married | E46: 7500 | F46: 1 | G46: 0 | H46: 02-10-2013 | I46: 19 | J46: 3 | K46: 1 | L46: 10 | M46: 3 | N46: 2 | O46: 12 | P46: 3 | Q46: 2 | R46: 0 | S46: 3 | T46: 5 | U46: 0 | V46: 0 | W46: 0 | X46: 0 | Y46: 0 | Z46: 0 | AA46: 3 | AB46: 11 | AC46: 0
A47: 1371 | B47: 1976 | C47: Graduation | D47: Single | E47: 79941 | F47: 0 | G47: 0 | H47: 28-06-2014 | I47: 72 | J47: 123 | K47: 164 | L47: 266 | M47: 227 | N47: 30 | O47: 174 | P47: 1 | Q47: 2 | R47: 4 | S47: 9 | T47: 1 | U47: 0 | V47: 0 | W47: 0 | X47: 0 | Y47: 0 | Z47: 0 | AA47: 3 | AB47: 11 | AC47: 0
A48: 9909 | B48: 1996 | C48: 2n Cycle | D48: Married | E48: 7500 | F48: 0 | G48: 0 | H48: 09-11-2012 | I48: 24 | J48: 3 | K48: 18 | L48: 14 | M48: 15 | N48: 22 | O48: 50 | P48: 3 | Q48: 3 | R48: 1 | S48: 3 | T48: 9 | U48: 0 | V48: 0 | W48: 0 | X48: 0 | Y48: 0 | Z48: 0 | AA48: 3 | AB48: 11 | AC48: 1
A49: 7286 | B49: 1968 | C49: Graduation | D49: Together | E49: 41728 | F49: 1 | G49: 0 | H49: 24-05-2013 | I49: 92 | J49: 13 | K49: 6 | L49: 15 | M49: 3 | N49: 5 | O49: 13 | P49: 1 | Q49: 2 | R49: 0 | S49: 2 | T49: 10 | U49: 0 | V49: 0 | W49: 0 | X49: 0 | Y49: 0 | Z49: 0 | AA49: 3 | AB49: 11 | AC49: 0
A50: 7244 | B50: 1951 | C50: Graduation | D50: Single | F50: 2 | G50: 1 | H50: 01-01-2014 | I50: 96 | J50: 48 | K50: 5 | L50: 48 | M50: 6 | N50: 10 | O50: 7 | P50: 3 | Q50: 2 | R50: 1 | S50: 4 | T50: 6 | U50: 0 | V50: 0 | W50: 0 | X50: 0 | Y50: 0 | Z50: 0 | AA50: 3 | AB50: 11 | AC50: 0
A51: 6566 | B51: 1954 | C51: PhD | D51: Married | E51: 72550 | F51: 1 | G51: 1 | H51: 08-11-2012 | I51: 39 | J51: 826 | K51: 50 | L51: 317 | M51: 50 | N51: 38 | O51: 38 | P51: 9 | Q51: 5 | R51: 2 | S51: 12 | T51: 8 | U51: 0 | V51: 0 | W51: 0 | X51: 0 | Y51: 0 | Z51: 0 | AA51: 3 | AB51: 11 | AC51: 0
A52: 8614 | B52: 1957 | C52: Graduation | D52: Widow | E52: 65486 | F52: 0 | G52: 1 | H52: 12-05-2014 | I52: 29 | J52: 245 | K52: 19 | L52: 125 | M52: 37 | N52: 67 | O52: 14 | P52: 1 | Q52: 4 | R52: 2 | S52: 10 | T52: 2 | U52: 0 | V52: 0 | W52: 0 | X52: 0 | Y52: 0 | Z52: 0 | AA52: 3 | AB52: 11 | AC52: 0
A53: 4114 | B53: 1964 | C53: Master | D53: Married | E53: 79143 | F53: 0 | G53: 0 | H53: 11-08-2012 | I53: 2 | J53: 650 | K53: 37 | L53: 780 | M53: 27 | N53: 167 | O53: 32 | P53: 1 | Q53: 6 | R53: 9 | S53: 13 | T53: 3 | U53: 0 | V53: 0 | W53: 0 | X53: 0 | Y53: 0 | Z53: 0 | AA53: 3 | AB53: 11 | AC53: 0
A54: 1331 | B54: 1977 | C54: Graduation | D54: Single | E54: 35790 | F54: 1 | G54: 0 | H54: 02-01-2013 | I54: 54 | J54: 12 | K54: 6 | L54: 20 | M54: 30 | N54: 1 | O54: 3 | P54: 2 | Q54: 2 | R54: 0 | S54: 3 | T54: 7 | U54: 0 | V54: 0 | W54: 0 | X54: 0 | Y54: 0 | Z54: 0 | AA54: 3 | AB54: 11 | AC54: 0
A55: 2225 | B55: 1977 | C55: Graduation | D55: Divorced | E55: 82582 | F55: 0 | G55: 0 | H55: 07-06-2014 | I55: 54 | J55: 510 | K55: 120 | L55: 550 | M55: 156 | N55: 40 | O55: 241 | P55: 1 | Q55: 4 | R55: 9 | S55: 7 | T55: 1 | U55: 1 | V55: 0 | W55: 0 | X55: 1 | Y55: 0 | Z55: 0 | AA55: 3 | AB55: 11 | AC55: 1
A56: 9381 | B56: 1978 | C56: Graduation | D56: Married | E56: 66373 | F56: 1 | G56: 1 | H56: 12-06-2013 | I56: 57 | J56: 328 | K56: 9 | L56: 124 | M56: 12 | N56: 24 | O56: 109 | P56: 7 | Q56: 4 | R56: 2 | S56: 10 | T56: 3 | U56: 0 | V56: 0 | W56: 0 | X56: 0 | Y56: 0 | Z56: 0 | AA56: 3 | AB56: 11 | AC56: 0
A57: 6260 | B57: 1955 | C57: Master | D57: Together | E57: 82384 | F57: 0 | G57: 0 | H57: 19-11-2012 | I57: 55 | J57: 984 | K57: 51 | L57: 432 | M57: 180 | N57: 120 | O57: 190 | P57: 1 | Q57: 3 | R57: 10 | S57: 13 | T57: 1 | U57: 0 | V57: 0 | W57: 1 | X57: 0 | Y57: 0 | Z57: 0 | AA57: 3 | AB57: 11 | AC57: 1
A58: 10383 | B58: 1966 | C58: Graduation | D58: Divorced | E58: 70287 | F58: 0 | G58: 0 | H58: 02-04-2013 | I58: 30 | J58: 295 | K58: 35 | L58: 482 | M58: 121 | N58: 120 | O58: 40 | P58: 1 | Q58: 5 | R58: 5 | S58: 10 | T58: 3 | U58: 0 | V58: 0 | W58: 0 | X58: 0 | Y58: 0 | Z58: 0 | AA58: 3 | AB58: 11 | AC58: 1
A59: 7437 | B59: 1988 | C59: Graduation | D59: Single | E59: 27938 | F59: 1 | G59: 0 | H59: 28-04-2014 | I59: 31 | J59: 13 | K59: 0 | L59: 8 | M59: 2 | N59: 1 | O59: 5 | P59: 1 | Q59: 1 | R59: 0 | S59: 4 | T59: 3 | U59: 0 | V59: 0 | W59: 0 | X59: 0 | Y59: 0 | Z59: 0 | AA59: 3 | AB59: 11 | AC59: 0
A60: 8557 | B60: 1982 | C60: Graduation | D60: Single | F60: 1 | G60: 0 | H60: 17-06-2013 | I60: 57 | J60: 11 | K60: 3 | L60: 22 | M60: 2 | N60: 2 | O60: 6 | P60: 2 | Q60: 2 | R60: 0 | S60: 3 | T60: 6 | U60: 0 | V60: 0 | W60: 0 | X60: 0 | Y60: 0 | Z60: 0 | AA60: 3 | AB60: 11 | AC60: 0
A61: 8375 | B61: 1968 | C61: PhD | D61: Married | E61: 55954 | F61: 0 | G61: 1 | H61: 03-03-2014 | I61: 63 | J61: 447 | K61: 0 | L61: 28 | M61: 0 | N61: 0 | O61: 43 | P61: 3 | Q61: 8 | R61: 2 | S61: 6 | T61: 7 | U61: 0 | V61: 0 | W61: 0 | X61: 0 | Y61: 0 | Z61: 0 | AA61: 3 | AB61: 11 | AC61: 0
A62: 6853 | B62: 1982 | C62: Master | D62: Single | E62: 75777 | F62: 0 | G62: 0 | H62: 04-07-2013 | I62: 12 | J62: 712 | K62: 26 | L62: 538 | M62: 69 | N62: 13 | O62: 80 | P62: 1 | Q62: 3 | R62: 6 | S62: 11 | T62: 1 | U62: 0 | V62: 1 | W62: 1 | X62: 0 | Y62: 0 | Z62: 0 | AA62: 3 | AB62: 11 | AC62: 1
A63: 3076 | B63: 1975 | C63: Graduation | D63: Together | E63: 66653 | F63: 1 | G63: 1 | H63: 07-09-2012 | I63: 18 | J63: 452 | K63: 18 | L63: 102 | M63: 16 | N63: 18 | O63: 6 | P63: 4 | Q63: 4 | R63: 2 | S63: 12 | T63: 3 | U63: 0 | V63: 0 | W63: 0 | X63: 0 | Y63: 0 | Z63: 0 | AA63: 3 | AB63: 11 | AC63: 0
A64: 1012 | B64: 1952 | C64: Graduation | D64: Single | E64: 61823 | F64: 0 | G64: 1 | H64: 18-02-2013 | I64: 26 | J64: 523 | K64: 7 | L64: 134 | M64: 37 | N64: 14 | O64: 169 | P64: 4 | Q64: 8 | R64: 2 | S64: 10 | T64: 7 | U64: 0 | V64: 0 | W64: 0 | X64: 0 | Y64: 0 | Z64: 0 | AA64: 3 | AB64: 11 | AC64: 0
A65: 6518 | B65: 1951 | C65: PhD | D65: Widow | E65: 67680 | F65: 0 | G65: 1 | H65: 11-06-2013 | I65: 8 | J65: 546 | K65: 0 | L65: 48 | M65: 0 | N65: 6 | O65: 6 | P65: 1 | Q65: 7 | R65: 3 | S65: 8 | T65: 5 | U65: 0 | V65: 0 | W65: 0 | X65: 0 | Y65: 0 | Z65: 0 | AA65: 3 | AB65: 11 | AC65: 0
A66: 4137 | B66: 1948 | C66: Graduation | D66: Together | E66: 70666 | F66: 0 | G66: 0 | H66: 06-12-2013 | I66: 29 | J66: 398 | K66: 40 | L66: 367 | M66: 119 | N66: 122 | O66: 30 | P66: 1 | Q66: 7 | R66: 4 | S66: 4 | T66: 4 | U66: 0 | V66: 0 | W66: 0 | X66: 0 | Y66: 0 | Z66: 0 | AA66: 3 | AB66: 11 | AC66: 0
A67: 8082 | B67: 1971 | C67: Graduation | D67: Married | E67: 25721 | F67: 1 | G67: 0 | H67: 21-05-2013 | I67: 75 | J67: 1 | K67: 3 | L67: 6 | M67: 3 | N67: 6 | O67: 15 | P67: 1 | Q67: 1 | R67: 1 | S67: 2 | T67: 7 | U67: 0 | V67: 0 | W67: 0 | X67: 0 | Y67: 0 | Z67: 0 | AA67: 3 | AB67: 11 | AC67: 1
A68: 1386 | B68: 1967 | C68: Graduation | D68: Together | E68: 32474 | F68: 1 | G68: 1 | H68: 11-05-2014 | I68: 0 | J68: 10 | K68: 0 | L68: 1 | M68: 0 | N68: 0 | O68: 0 | P68: 1 | Q68: 1 | R68: 0 | S68: 2 | T68: 7 | U68: 0 | V68: 0 | W68: 0 | X68: 0 | Y68: 0 | Z68: 0 | AA68: 3 | AB68: 11 | AC68: 0
A69: 9369 | B69: 1979 | C69: 2n Cycle | D69: Single | E69: 88194 | F69: 0 | G69: 1 | H69: 19-03-2014 | I69: 19 | J69: 688 | K69: 14 | L69: 309 | M69: 201 | N69: 24 | O69: 38 | P69: 1 | Q69: 11 | R69: 10 | S69: 10 | T69: 5 | U69: 1 | V69: 0 | W69: 0 | X69: 1 | Y69: 0 | Z69: 0 | AA69: 3 | AB69: 11 | AC69: 1
A70: 4477 | B70: 1958 | C70: Graduation | D70: Together | E70: 69096 | F70: 0 | G70: 1 | H70: 27-09-2013 | I70: 4 | J70: 247 | K70: 49 | L70: 159 | M70: 7 | N70: 82 | O70: 109 | P70: 1 | Q70: 5 | R70: 2 | S70: 10 | T70: 4 | U70: 0 | V70: 0 | W70: 0 | X70: 0 | Y70: 0 | Z70: 0 | AA70: 3 | AB70: 11 | AC70: 0
A71: 1357 | B71: 1970 | C71: Graduation | D71: Together | E71: 74854 | F71: 1 | G71: 2 | H71: 08-04-2013 | I71: 90 | J71: 856 | K71: 59 | L71: 487 | M71: 58 | N71: 29 | O71: 73 | P71: 7 | Q71: 2 | R71: 5 | S71: 5 | T71: 5 | U71: 0 | V71: 0 | W71: 0 | X71: 0 | Y71: 0 | Z71: 0 | AA71: 3 | AB71: 11 | AC71: 0
A72: 1402 | B72: 1954 | C72: Master | D72: Married | E72: 66991 | F72: 0 | G72: 0 | H72: 11-09-2012 | I72: 1 | J72: 496 | K72: 36 | L72: 460 | M72: 189 | N72: 60 | O72: 12 | P72: 3 | Q72: 4 | R72: 8 | S72: 6 | T72: 3 | U72: 0 | V72: 0 | W72: 0 | X72: 0 | Y72: 0 | Z72: 0 | AA72: 3 | AB72: 11 | AC72: 0
A73: 10629 | B73: 1973 | C73: 2n Cycle | D73: Married | F73: 1 | G73: 0 | H73: 14-09-2012 | I73: 25 | J73: 25 | K73: 3 | L73: 43 | M73: 17 | N73: 4 | O73: 17 | P73: 3 | Q73: 3 | R73: 0 | S73: 3 | T73: 8 | U73: 0 | V73: 0 | W73: 0 | X73: 0 | Y73: 0 | Z73: 0 | AA73: 3 | AB73: 11 | AC73: 0
A74: 6312 | B74: 1959 | C74: Graduation | D74: Married | E74: 65031 | F74: 0 | G74: 1 | H74: 17-03-2013 | I74: 29 | J74: 258 | K74: 107 | L74: 291 | M74: 84 | N74: 37 | O74: 86 | P74: 4 | Q74: 10 | R74: 3 | S74: 13 | T74: 7 | U74: 0 | V74: 0 | W74: 0 | X74: 0 | Y74: 0 | Z74: 0 | AA74: 3 | AB74: 11 | AC74: 0
A75: 8132 | B75: 1975 | C75: PhD | D75: Married | E75: 60631 | F75: 1 | G75: 1 | H75: 05-04-2013 | I75: 88 | J75: 565 | K75: 6 | L75: 65 | M75: 0 | N75: 6 | O75: 19 | P75: 5 | Q75: 9 | R75: 2 | S75: 8 | T75: 7 | U75: 0 | V75: 1 | W75: 0 | X75: 0 | Y75: 0 | Z75: 0 | AA75: 3 | AB75: 11 | AC75: 0
A76: 1050 | B76: 1952 | C76: Graduation | D76: Married | E76: 28332 | F76: 0 | G76: 0 | H76: 30-04-2014 | I76: 58 | J76: 14 | K76: 10 | L76: 13 | M76: 4 | N76: 15 | O76: 9 | P76: 1 | Q76: 2 | R76: 1 | S76: 4 | T76: 2 | U76: 0 | V76: 0 | W76: 0 | X76: 0 | Y76: 0 | Z76: 0 | AA76: 3 | AB76: 11 | AC76: 0
A77: 5846 | B77: 1977 | C77: Graduation | D77: Divorced | E77: 40246 | F77: 1 | G77: 0 | H77: 19-12-2012 | I77: 68 | J77: 2 | K77: 1 | L77: 6 | M77: 2 | N77: 1 | O77: 1 | P77: 1 | Q77: 1 | R77: 0 | S77: 2 | T77: 6 | U77: 0 | V77: 0 | W77: 0 | X77: 0 | Y77: 0 | Z77: 0 | AA77: 3 | AB77: 11 | AC77: 0
A78: 1859 | B78: 1972 | C78: Master | D78: Married | E78: 75251 | F78: 0 | G78: 0 | H78: 27-08-2012 | I78: 34 | J78: 721 | K78: 111 | L78: 925 | M78: 97 | N78: 18 | O78: 18 | P78: 1 | Q78: 7 | R78: 6 | S78: 5 | T78: 5 | U78: 0 | V78: 0 | W78: 0 | X78: 0 | Y78: 0 | Z78: 0 | AA78: 3 | AB78: 11 | AC78: 1
A79: 7503 | B79: 1976 | C79: Graduation | D79: Single | E79: 75825 | F79: 0 | G79: 0 | H79: 12-10-2012 | I79: 40 | J79: 1032 | K79: 105 | L79: 779 | M79: 137 | N79: 105 | O79: 51 | P79: 0 | Q79: 5 | R79: 8 | S79: 9 | T79: 4 | U79: 1 | V79: 0 | W79: 0 | X79: 0 | Y79: 0 | Z79: 0 | AA79: 3 | AB79: 11 | AC79: 1
A80: 10401 | B80: 1976 | C80: 2n Cycle | D80: Together | E80: 26326 | F80: 0 | G80: 0 | H80: 04-09-2013 | I80: 12 | J80: 1 | K80: 0 | L80: 5 | M80: 0 | N80: 3 | O80: 9 | P80: 1 | Q80: 0 | R80: 0 | S80: 3 | T80: 3 | U80: 0 | V80: 0 | W80: 0 | X80: 0 | Y80: 0 | Z80: 1 | AA80: 3 | AB80: 11 | AC80: 0
A81: 1618 | B81: 1965 | C81: Graduation | D81: Together | E81: 56046 | F81: 0 | G81: 0 | H81: 02-01-2013 | I81: 9 | J81: 577 | K81: 0 | L81: 64 | M81: 0 | N81: 0 | O81: 51 | P81: 2 | Q81: 10 | R81: 1 | S81: 8 | T81: 8 | U81: 1 | V81: 0 | W81: 0 | X81: 0 | Y81: 0 | Z81: 0 | AA81: 3 | AB81: 11 | AC81: 1
A82: 3332 | B82: 1985 | C82: Graduation | D82: Single | E82: 29760 | F82: 1 | G82: 0 | H82: 29-08-2012 | I82: 87 | J82: 64 | K82: 4 | L82: 68 | M82: 7 | N82: 5 | O82: 17 | P82: 4 | Q82: 3 | R82: 1 | S82: 4 | T82: 8 | U82: 0 | V82: 0 | W82: 0 | X82: 0 | Y82: 0 | Z82: 0 | AA82: 3 | AB82: 11 | AC82: 0
A83: 2261 | B83: 1969 | C83: Graduation | D83: Married | E83: 26304 | F83: 1 | G83: 0 | H83: 23-06-2013 | I83: 5 | J83: 4 | K83: 1 | L83: 5 | M83: 2 | N83: 0 | O83: 4 | P83: 1 | Q83: 1 | R83: 0 | S83: 2 | T83: 7 | U83: 0 | V83: 0 | W83: 0 | X83: 0 | Y83: 0 | Z83: 0 | AA83: 3 | AB83: 11 | AC83: 0
A84: 5346 | B84: 1973 | C84: 2n Cycle | D84: Married | E84: 23559 | F84: 1 | G84: 0 | H84: 03-07-2013 | I84: 87 | J84: 25 | K84: 5 | L84: 19 | M84: 7 | N84: 0 | O84: 23 | P84: 3 | Q84: 3 | R84: 0 | S84: 3 | T84: 7 | U84: 0 | V84: 0 | W84: 0 | X84: 0 | Y84: 0 | Z84: 0 | AA84: 3 | AB84: 11 | AC84: 0
A85: 4119 | B85: 1963 | C85: Master | D85: Together | E85: 38620 | F85: 0 | G85: 0 | H85: 11-05-2013 | I85: 56 | J85: 112 | K85: 17 | L85: 44 | M85: 34 | N85: 22 | O85: 89 | P85: 1 | Q85: 2 | R85: 5 | S85: 3 | T85: 3 | U85: 0 | V85: 0 | W85: 0 | X85: 0 | Y85: 0 | Z85: 0 | AA85: 3 | AB85: 11 | AC85: 0
... A91: 771 | B91: 1967 | C91: Graduation | D91: Together | E91: 54178 | F91: 0 | G91: 1 | H91: 21-01-2014 | I91: 79 | J91: 135 | K91: 9 | L91: 39 | M91: 4 | N91: 0 | O91: 7 | P91: 1 | Q91: 2 | R91: 2 | S91: 5 | T91: 2 | U91: 0 | V91: 0 | W91: 0 | X91: 0 | Y91: 0 | Z91: 0 | AA91: 3 | AB91: 11 | AC91: 0
A92: 8996 | B92: 1957 | C92: PhD | D92: Married | F92: 2 | G92: 1 | H92: 19-11-2012 | I92: 4 | J92: 230 | K92: 42 | L92: 192 | M92: 49 | N92: 37 | O92: 53 | P92: 12 | Q92: 7 | R92: 2 | S92: 8 | T92: 9 | U92: 0 | V92: 0 | W92: 0 | X92: 0 | Y92: 0 | Z92: 0 | AA92: 3 | AB92: 11 | AC92: 0
A93: 9235 | B93: 1957 | C93: Graduation | D93: Single | F93: 1 | G93: 1 | H93: 27-05-2014 | I93: 45 | J93: 7 | K93: 0 | L93: 8 | M93: 2 | N93: 0 | O93: 1 | P93: 1 | Q93: 1 | R93: 0 | S93: 2 | T93: 7 | U93: 0 | V93: 0 | W93: 0 | X93: 0 | Y93: 0 | Z93: 0 | AA93: 3 | AB93: 11 | AC93: 0
A94: 5798 | B94: 1973 | C94: Master | D94: Together | F94: 0 | G94: 0 | H94: 23-11-2013 | I94: 87 | J94: 445 | K94: 37 | L94: 359 | M94: 98 | N94: 28 | O94: 18 | P94: 1 | Q94: 2 | R94: 4 | S94: 8 | T94: 1 | U94: 0 | V94: 0 | W94: 0 | X94: 0 | Y94: 0 | Z94: 0 | AA94: 3 | AB94: 11 | AC94: 0
A95: 11178 | B95: 1972 | C95: Master | D95: Single | E95: 42394 | F95: 1 | G95: 0 | H95: 23-03-2014 | I95: 69 | J95: 15 | K95: 2 | L95: 10 | M95: 0 | N95: 1 | O95: 4 | P95: 1 | Q95: 1 | R95: 0 | S95: 3 | T95: 7 | U95: 0 | V95: 0 | W95: 0 | X95: 0 | Y95: 0 | Z95: 0 | AA95: 3 | AB95: 11 | AC95: 0
A96: 2230 | B96: 1970 | C96: PhD | D96: Married | E96: 23626 | F96: 1 | G96: 0 | H96: 24-05-2014 | I96: 84 | J96: 27 | K96: 2 | L96: 14 | M96: 0 | N96: 0 | O96: 0 | P96: 3 | Q96: 3 | R96: 1 | S96: 3 | T96: 5 | U96: 0 | V96: 0 | W96: 0 | X96: 0 | Y96: 0 | Z96: 0 | AA96: 3 | AB96: 11 | AC96: 0
A97: 7516 | B97: 1983 | C97: Graduation | D97: Married | E97: 30096 | F97: 1 | G97: 0 | H97: 22-05-2014 | I97: 30 | J97: 5 | K97: 3 | L97: 11 | M97: 12 | N97: 5 | O97: 9 | P97: 1 | Q97: 2 | R97: 0 | S97: 3 | T97: 6 | U97: 0 | V97: 0 | W97: 0 | X97: 0 | Y97: 0 | Z97: 0 | AA97: 3 | AB97: 11 | AC97: 0
A98: 7247 | B98: 1960 | C98: Graduation | D98: Widow | E98: 47916 | F98: 0 | G98: 1 | H98: 22-11-2012 | I98: 72 | J98: 505 | K98: 0 | L98: 26 | M98: 0 | N98: 0 | O98: 75 | P98: 5 | Q98: 7 | R98: 4 | S98: 6 | T98: 6 | U98: 0 | V98: 1 | W98: 0 | X98: 0 | Y98: 0 | Z98: 0 | AA98: 3 | AB98: 11 | AC98: 0
A99: 11100 | B99: 1972 | C99: Graduation | D99: Divorced | E99: 51813 | F99: 1 | G99: 1 | H99: 11-04-2013 | I99: 37 | J99: 51 | K99: 2 | L99: 7 | M99: 0 | N99: 1 | O99: 2 | P99: 2 | Q99: 2 | R99: 0 | S99: 3 | T99: 7 | U99: 0 | V99: 0 | W99: 0 | X99: 0 | Y99: 0 | Z99: 0 | AA99: 3 | AB99: 11 | AC99: 0
A100: 4646 | B100: 1951 | C100: 2n Cycle | D100: Married | E100: 78497 | F100: 0 | G100: 0 | H100: 01-12-2013 | I100: 44 | J100: 207 | K100: 26 | L100: 447 | M100: 75 | N100: 0 | O100: 223 | P100: 1 | Q100: 5 | R100: 7 | S100: 12 | T100: 2 | U100: 0 | V100: 0 | W100: 0 | X100: 1 | Y100: 0 | Z100: 0 | AA100: 3 | AB100: 11 | AC100: 0
A101: 3037 | B101: 1983 | C101: PhD | D101: Married | E101: 50150 | F101: 0 | G101: 0 | H101: 20-06-2013 | I101: 32 | J101: 135 | K101: 46 | L101: 92 | M101: 65 | N101: 61 | O101: 11 | P101: 2 | Q101: 5 | R101: 2 | S101: 7 | T101: 5 | U101: 0 | V101: 0 | W101: 0 | X101: 0 | Y101: 0 | Z101: 0 | AA101: 3 | AB101: 11 | AC101: 0
A102: 1473 | B102: 1960 | C102: 2n Cycle | D102: Single | E102: 47823 | F102: 0 | G102: 1 | H102: 23-07-2013 | I102: 0 | J102: 53 | K102: 1 | L102: 5 | M102: 2 | N102: 1 | O102: 10 | P102: 2 | Q102: 2 | R102: 0 | S102: 3 | T102: 8 | U102: 0 | V102: 0 | W102: 0 | X102: 0 | Y102: 0 | Z102: 0 | AA102: 3 | AB102: 11 | AC102: 0
A103: 1016 | B103: 1959 | C103: PhD | D103: Single | E103: 34554 | F103: 0 | G103: 1 | H103: 30-03-2014 | I103: 43 | J103: 41 | K103: 1 | L103: 6 | M103: 2 | N103: 0 | O103: 5 | P103: 2 | Q103: 2 | R103: 0 | S103: 3 | T103: 6 | U103: 0 | V103: 0 | W103: 0 | X103: 0 | Y103: 0 | Z103: 0 | AA103: 3 | AB103: 11 | AC103: 0
A104: 4518 | B104: 1979 | C104: Graduation | D104: Together | E104: 85693 | F104: 0 | G104: 1 | H104: 20-04-2013 | I104: 59 | J104: 386 | K104: 172 | L104: 183 | M104: 185 | N104: 132 | O104: 111 | P104: 2 | Q104: 9 | R104: 5 | S104: 11 | T104: 5 | U104: 0 | V104: 0 | W104: 0 | X104: 0 | Y104: 0 | Z104: 0 | AA104: 3 | AB104: 11 | AC104: 0
A105: 9370 | B105: 1945 | C105: PhD | D105: Married | E105: 65846 | F105: 0 | G105: 0 | H105: 17-05-2013 | I105: 68 | J105: 562 | K105: 81 | L105: 276 | M105: 80 | N105: 40 | O105: 81 | P105: 1 | Q105: 6 | R105: 3 | S105: 6 | T105: 4 | U105: 0 | V105: 0 | W105: 0 | X105: 0 | Y105: 0 | Z105: 0 | AA105: 3 | AB105: 11 | AC105: 0
A106: 8908 | B106: 1959 | C106: Graduation | D106: Married | E106: 87195 | F106: 0 | G106: 0 | H106: 08-05-2014 | I106: 35 | J106: 217 | K106: 76 | L106: 690 | M106: 50 | N106: 26 | O106: 38 | P106: 1 | Q106: 3 | R106: 11 | S106: 5 | T106: 1 | U106: 0 | V106: 0 | W106: 0 | X106: 0 | Y106: 0 | Z106: 0 | AA106: 3 | AB106: 11 | AC106: 1
... A129: 3381 | B129: 1953 | C129: Master | D129: Married | E129: 54348 | F129: 1 | G129: 1 | H129: 08-06-2014 | I129: 51 | J129: 70 | K129: 0 | L129: 16 | M129: 0 | N129: 0 | O129: 4 | P129: 2 | Q129: 2 | R129: 0 | S129: 4 | T129: 6 | U129: 0 | V129: 0 | W129: 0 | X129: 0 | Y129: 0 | Z129: 0 | AA129: 3 | AB129: 11 | AC129: 0
A130: 8268 | B130: 1961 | C130: PhD | D130: Married | F130: 0 | G130: 1 | H130: 11-07-2013 | I130: 23 | J130: 352 | K130: 0 | L130: 27 | M130: 10 | N130: 0 | O130: 15 | P130: 3 | Q130: 6 | R130: 1 | S130: 7 | T130: 6 | U130: 0 | V130: 0 | W130: 0 | X130: 0 | Y130: 0 | Z130: 0 | AA130: 3 | AB130: 11 | AC130: 0
A131: 11051 | B131: 1956 | C131: PhD | D131: Together | E131: 77376 | F131: 1 | G131: 1 | H131: 10-05-2014 | I131: 72 | J131: 492 | K131: 19 | L131: 110 | M131: 16 | N131: 12 | O131: 12 | P131: 4 | Q131: 6 | R131: 3 | S131: 10 | T131: 4 | U131: 0 | V131: 0 | W131: 0 | X131: 0 | Y131: 0 | Z131: 0 | AA131: 3 | AB131: 11 | AC131: 0
A132: 8026 | B132: 1952 | C132: Graduation | D132: Married | E132: 62998 | F132: 0 | G132: 1 | H132: 30-09-2013 | I132: 10 | J132: 120 | K132: 58 | L132: 73 | M132: 65 | N132: 89 | O132: 58 | P132: 5 | Q132: 5 | R132: 4 | S132: 5 | T132: 5 | U132: 0 | V132: 0 | W132: 0 | X132: 0 | Y132: 0 | Z132: 0 | AA132: 3 | AB132: 11 | AC132: 0
...

Sheet CLEAN
A1: ID | B1: Année de naissance | C1: Âge | D1: Tranche_âge | E1: Education | F1: Statut_marital | G1: Revenus | H1: Enfantmaison | I1: AdoMaison | J1: Enfant_total | K1: Date_inscription client | L1: Ancienneté client | M1: R_Récence | N1: F_TOTAL_achat | O1: M_TOTAL_dépensé | P1: R_SCORE | Q1: F_SCORE | R1: M_SCORE | S1: RFM_SCORE | T1: Segment_RFM | U1: Montant_Vin_2ans | V1: Montant_Fruits_2ans | W1: Montant_Viande_2ans | X1: Montant_Poisson_2ans | Y1: Montant_Sucreries_2ans | Z1: Montant_Or_2ans | AA1: NbrAchatsRemise | AB1: NbrAchatWeb | AC1: NbrAchatCatalogue | AD1: NbrAchatMagasin | AE1: Nbr de visite web (last month) | AF1: Campagne3Acceptée | AG1: Campagne4Acceptée | AH1: Campagne5Acceptée | AI1: Campagne1Acceptée | AJ1: Campagne2Acceptée | AK1: Réclamation | AL1: Coût contact client | AM1: Revenue client | AN1: Réponse dernière campagne
A2: 9432 | B2: 1977 | C2: =YEAR(TODAY())-CLEAN!$B2 -> 48 | D2: 45-59 ans | E2: BAC+3 | F2: Conjoint | G2: 666666 | H2: 1 | I2: 0 | J2: =CLEAN!$H2+CLEAN!$I2 -> 1 | K2: 41427 | L2: =YEAR(TODAY())-YEAR(CLEAN!$K2) -> 12 | M2: 23 | N2: =SUM(CLEAN!$AB2:$AE2) -> 13 | O2: =CLEAN!$U2+CLEAN!$V2+CLEAN!$W2+CLEAN!$X2+CLEAN!$Y2+CLEAN!$Z2 -> 62 | P2: =IF(CLEAN!$M2<=32,3,IF(CLEAN!$M2<=65,2,1)) -> 3 | Q2: =IF(Table_Market[[#This Row],[F_TOTAL_achat]]<=14,1,IF(Table_Market[[#This Row],[F_TOTAL_achat]]<=21,2,3)) -> 1 | R2: =IF(Table_Market[[#This Row],[M_TOTAL_dépensé]]<=115,1,IF(Table_Market[[#This Row],[M_TOTAL_dépensé]]<=833,2,3)) -> 1 | S2: =Table_Market[[#This Row],[R_SCORE]]&Table_Market[[#This Row],[F_SCORE]]&Table_Market[[#This Row],[M_SCORE]] -> 311 | T2: =IF(Table_Market[[#This Row],[RFM_SCORE]]="333","Clients élites",IF(LEFT(Table_Market[[#This Row],[RFM_SCORE]],1)="3","Récents prometteurs",IF(LEFT(Table_Market[[#This Row],[RFM_SCORE]],1)="1","Inactifs",IF(AND(LEFT(Table_Market[[#This Row],[RFM_SCORE]],1)>="2",MID(Table_Market[[#This Row],[RFM_SCORE]],2,1)>="2",RIGHT(Table_Market[[#This Row],[RFM_SCORE]],1)>="2"),"Fidèles rentables","Occasionnels")))) -> Récents prometteurs | U2: 9 | V2: 14 | W2: 18 | X2: 8 | Y2: 1 | Z2: 12 | AA2: 4 | AB2: 3 | AC2: 1 | AD2: 3 | AE2: 6 | AF2: 0 | AG2: 0 | AH2: 0 | AI2: 0 | AJ2: 0 | AK2: 0 | AL2: 3 | AM2: 11 | AN2: 0
A3: 1503 | B3: 1976 | C3: =YEAR(TODAY())-CLEAN!$B3 -> 49 | D3: 45-59 ans | E3: Doctorat | F3: Conjoint | G3: 162397 | H3: 1 | I3: 1 | J3: =CLEAN!$H3+CLEAN!$I3 -> 2 | K3: 41428 | L3: =YEAR(TODAY())-YEAR(CLEAN!$K3) -> 12 | M3: 31 | N3: =SUM(CLEAN!$AB3:$AE3) -> 2 | O3: =CLEAN!$U3+CLEAN!$V3+CLEAN!$W3+CLEAN!$X3+CLEAN!$Y3+CLEAN!$Z3 -> 107 | P3: =IF(CLEAN!$M3<=32,3,IF(CLEAN!$M3<=65,2,1)) -> 3 | Q3: =IF(Table_Market[[#This Row],[F_TOTAL_achat]]<=14,1,IF(Table_Market[[#This Row],[F_TOTAL_achat]]<=21,2,3)) -> 1 | R3: =IF(Table_Market[[#This Row],[M_TOTAL_dépensé]]<=115,1,IF(Table_Market[[#This Row],[M_TOTAL_dépensé]]<=833,2,3)) -> 1 | S3: =Table_Market[[#This Row],[R_SCORE]]&Table_Market[[#This Row],[F_SCORE]]&Table_Market[[#This Row],[M_SCORE]] -> 311 | T3: =IF(Table_Market[[#This Row],[RFM_SCORE]]="333","Clients élites",IF(LEFT(Table_Market[[#This Row],[RFM_SCORE]],1)="3","Récents prometteurs",IF(LEFT(Table_Market[[#This Row],[RFM_SCORE]],1)="1","Inactifs",IF(AND(LEFT(Table_Market[[#This Row],[RFM_SCORE]],1)>="2",MID(Table_Market[[#This Row],[RFM_SCORE]],2,1)>="2",RIGHT(Table_Market[[#This Row],[RFM_SCORE]],1)>="2"),"Fidèles rentables","Occasionnels")))) -> Récents prometteurs | U3: 85 | V3: 1 | W3: 16 | X3: 2 | Y3: 1 | Z3: 2 | AA3: 0 | AB3: 0 | AC3: 0 | AD3: 1 | AE3: 1 | AF3: 0 | AG3: 0 | AH3: 0 | AI3: 0 | AJ3: 0 | AK3: 0 | AL3: 3 | AM3: 11 | AN3: 0
A4: 1501 | B4: 1982 | C4: =YEAR(TODAY())-CLEAN!$B4 -> 43 | D4: 30-44 ans | E4: Doctorat | F4: Marié | G4: 160803 | H4: 0 | I4: 0 | J4: =CLEAN!$H4+CLEAN!$I4 -> 0 | K4: 41125 | L4: =YEAR(TODAY())-YEAR(CLEAN!$K4) -> 13 | M4: 21 | N4: =SUM(CLEAN!$AB4:$AE4) -> 29 | O4: =CLEAN!$U4+CLEAN!$V4+CLEAN!$W4+CLEAN!$X4+CLEAN!$Y4+CLEAN!$Z4 -> 1717 | P4: =IF(CLEAN!$M4<=32,3,IF(CLEAN!$M4<=65,2,1)) -> 3 | Q4: =IF(Table_Market[[#This Row],[F_TOTAL_achat]]<=14,1,IF(Table_Market[[#This Row],[F_TOTAL_achat]]<=21,2,3)) -> 3 | R4: =IF(Table_Market[[#This Row],[M_TOTAL_dépensé]]<=115,1,IF(Table_Market[[#This Row],[M_TOTAL_dépensé]]<=833,2,3)) -> 3 | S4: =Table_Market[[#This Row],[R_SCORE]]&Table_Market[[#This Row],[F_SCORE]]&Table_Market[[#This Row],[M_SCORE]] -> 333 | T4: =IF(Table_Market[[#This Row],[RFM_SCORE]]="333","Clients élites",IF(LEFT(Table_Market[[#This Row],[RFM_SCORE]],1)="3","Récents prometteurs",IF(LEFT(Table_Market[[#This Row],[RFM_SCORE]],1)="1","Inactifs",IF(AND(LEFT(Table_Market[[#This Row],[RFM_SCORE]],1)>="2",MID(Table_Market[[#This Row],[RFM_SCORE]],2,1)>="2",RIGHT(Table_Market[[#This Row],[RFM_SCORE]],1)>="2"),"Fidèles rentables","Occasionnels")))) -> Clients élites | U4: 55 | V4: 16 | W4: 1622 | X4: 17 | Y4: 3 | Z4: 4 | AA4: 15 | AB4: 0 | AC4: 28 | AD4: 1 | AE4: 0 | AF4: 0 | AG4: 0 | AH4: 0 | AI4: 0 | AJ4: 0 | AK4: 0 | AL4: 3 | AM4: 11 | AN4: 0
A5: 5336 | B5: 1971 | C5: =YEAR(TODAY())-CLEAN!$B5 -> 54 | D5: 45-59 ans | E5: BAC+5 | F5: Conjoint | G5: 157733 | H5: 1 | I5: 0 | J5: =CLEAN!$H5+CLEAN!$I5 -> 1 | K5: 41429 | L5: =YEAR(TODAY())-YEAR(CLEAN!$K5) -> 12 | M5: 37 | N5: =SUM(CLEAN!$AB5:$AE5) -> 3 | O5: =CLEAN!$U5+CLEAN!$V5+CLEAN!$W5+CLEAN!$X5+CLEAN!$Y5+CLEAN!$Z5 -> 59 | P5: =IF(CLEAN!$M5<=32,3,IF(CLEAN!$M5<=65,2,1)) -> 2 | Q5: =IF(Table_Market[[#This Row],[F_TOTAL_achat]]<=14,1,IF(Table_Market[[#This Row],[F_TOTAL_achat]]<=21,2,3)) -> 1 | R5: =IF(Table_Market[[#This Row],[M_TOTAL_dépensé]]<=115,1,IF(Table_Market[[#This Row],[M_TOTAL_dépensé]]<=833,2,3)) -> 1 | S5: =Table_Market[[#This Row],[R_SCORE]]&Table_Market[[#This Row],[F_SCORE]]&Table_Market[[#This Row],[M_SCORE]] -> 211 | T5: =IF(Table_Market[[#This Row],[RFM_SCORE]]="333","Clients élites",IF(LEFT(Table_Market[[#This Row],[RFM_SCORE]],1)="3","Récents prometteurs",IF(LEFT(Table_Market[[#This Row],[RFM_SCORE]],1)="1","Inactifs",IF(AND(LEFT(Table_Market[[#This Row],[RFM_SCORE]],1)>="2",MID(Table_Market[[#This Row],[RFM_SCORE]],2,1)>="2",RIGHT(Table_Market[[#This Row],[RFM_SCORE]],1)>="2"),"Fidèles rentables","Occasionnels")))) -> Occasionnels | U5: 39 | V5: 1 | W5: 9 | X5: 2 | Y5: 0 | Z5: 8 | AA5: 0 | AB5: 1 | AC5: 0 | AD5: 1 | AE5: 1 | AF5: 0 | AG5: 0 | AH5: 0 | AI5: 0 | AJ5: 0 | AK5: 0 | AL5: 3 | AM5: 11 | AN5: 0
A6: 8475 | B6: 1973 | C6: =YEAR(TODAY())-CLEAN!$B6 -> 52 | D6: 45-59 ans | E6: Doctorat | F6: Marié | G6: 157243 | H6: 0 | I6: 1 | J6: =CLEAN!$H6+CLEAN!$I6 -> 1 | K6: 41699 | L6: =YEAR(TODAY())-YEAR(CLEAN!$K6) -> 11 | M6: 98 | N6: =SUM(CLEAN!$AB6:$AE6) -> 22 | O6: =CLEAN!$U6+CLEAN!$V6+CLEAN!$W6+CLEAN!$X6+CLEAN!$Y6+CLEAN!$Z6 -> 1608 | P6: =IF(CLEAN!$M6<=32,3,IF(CLEAN!$M6<=65,2,1)) -> 1 | Q6: =IF(Table_Market[[#This Row],[F_TOTAL_achat]]<=14,1,IF(Table_Market[[#This Row],[F_TOTAL_achat]]<=21,2,3)) -> 3 | R6: =IF(Table_Market[[#This Row],[M_TOTAL_dépensé]]<=115,1,IF(Table_Market[[#This Row],[M_TOTAL_dépensé]]<=833,2,3)) -> 3 | S6: =Table_Market[[#This Row],[R_SCORE]]&Table_Market[[#This Row],[F_SCORE]]&Table_Market[[#This Row],[M_SCORE]] -> 133 | T6: =IF(Table_Market[[#This Row],[RFM_SCORE]]="333","Clients élites",IF(LEFT(Table_Market[[#This Row],[RFM_SCORE]],1)="3","Récents prometteurs",IF(LEFT(Table_Market[[#This Row],[RFM_SCORE]],1)="1","Inactifs",IF(AND(LEFT(Table_Market[[#This Row],[RFM_SCORE]],1)>="2",MID(Table_Market[[#This Row],[RFM_SCORE]],2,1)>="2",RIGHT(Table_Market[[#This Row],[RFM_SCORE]],1)>="2"),"Fidèles rentables","Occasionnels")))) -> Inactifs | U6: 20 | V6: 2 | W6: 1582 | X6: 1 | Y6: 2 | Z6: 1 | AA6: 15 | AB6: 0 | AC6: 22 | AD6: 0 | AE6: 0 | AF6: 0 | AG6: 0 | AH6: 0 | AI6: 0 | AJ6: 0 | AK6: 0 | AL6: 3 | AM6: 11 | AN6: 0
A7: 4931 | B7: 1977 | C7: =YEAR(TODAY())-CLEAN!$B7 -> 48 | D7: 45-59 ans | E7: BAC+3 | F7: Conjoint | G7: 157146 | H7: 0 | I7: 0 | J7: =CLEAN!$H7+CLEAN!$I7 -> 0 | K7: 41393 | L7: =YEAR(TODAY())-YEAR(CLEAN!$K7) -> 12 | M7: 13 | N7: =SUM(CLEAN!$AB7:$AE7) -> 29 | O7: =CLEAN!$U7+CLEAN!$V7+CLEAN!$W7+CLEAN!$X7+CLEAN!$Y7+CLEAN!$Z7 -> 1730 | P7: =IF(CLEAN!$M7<=32,3,IF(CLEAN!$M7<=65,2,1)) -> 3 | Q7: =IF(Table_Market[[#This Row],[F_TOTAL_achat]]<=14,1,IF(Table_Market[[#This Row],[F_TOTAL_achat]]<=21,2,3)) -> 3 | R7: =IF(Table_Market[[#This Row],[M_TOTAL_dépensé]]<=115,1,IF(Table_Market[[#This Row],[M_TOTAL_dépensé]]<=833,2,3)) -> 3 | S7: =Table_Market[[#This Row],[R_SCORE]]&Table_Market[[#This Row],[F_SCORE]]&Table_Market[[#This Row],[M_SCORE]] -> 333 | T7: =IF(Table_Market[[#This Row],[RFM_SCORE]]="333","Clients élites",IF(LEFT(Table_Market[[#This Row],[RFM_SCORE]],1)="3","Récents prometteurs",IF(LEFT(Table_Market[[#This Row],[RFM_SCORE]],1)="1","Inactifs",IF(AND(LEFT(Table_Market[[#This Row],[RFM_SCORE]],1)>="2",MID(Table_Market[[#This Row],[RFM_SCORE]],2,1)>="2",RIGHT(Table_Market[[#This Row],[RFM_SCORE]],1)>="2"),"Fidèles rentables","Occasionnels")))) -> Clients élites | U7: 1 | V7: 0 | W7: 1725 | X7: 2 | Y7: 1 | Z7: 1 | AA7: 0 | AB7: 0 | AC7: 28 | AD7: 0 | AE7: 1 | AF7: 0 | AG7: 0 | AH7: 0 | AI7: 0 | AJ7: 0 | AK7: 0 | AL7: 3 | AM7: 11 | AN7: 0
A8: 11181 | B8: 1949 | C8: =YEAR(TODAY())-CLEAN!$B8 -> 76 | D8: 60 ans et + | E8: Doctorat | F8: Marié | G8: 156924 | H8: 0 | I8: 0 | J8: =CLEAN!$H8+CLEAN!$I8 -> 0 | K8: 41515 | L8: =YEAR(TODAY())-YEAR(CLEAN!$K8) -> 12 | M8: 85 | N8: =SUM(CLEAN!$AB8:$AE8) -> 0 | O8: =CLEAN!$U8+CLEAN!$V8+CLEAN!$W8+CLEAN!$X8+CLEAN!$Y8+CLEAN!$Z8 -> 8 | P8: =IF(CLEAN!$M8<=32,3,IF(CLEAN!$M8<=65,2,1)) -> 1 | Q8: =IF(Table_Market[[#This Row],[F_TOTAL_achat]]<=14,1,IF(Table_Market[[#This Row],[F_TOTAL_achat]]<=21,2,3)) -> 1 | R8: =IF(Table_Market[[#This Row],[M_TOTAL_dépensé]]<=115,1,IF(Table_Market[[#This Row],[M_TOTAL_dépensé]]<=833,2,3)) -> 1 | S8: =Table_Market[[#This Row],[R_SCORE]]&Table_Market[[#This Row],[F_SCORE]]&Table_Market[[#This Row],[M_SCORE]] -> 111 | T8: =IF(Table_Market[[#This Row],[RFM_SCORE]]="333","Clients élites",IF(LEFT(Table_Market[[#This Row],[RFM_SCORE]],1)="3","Récents prometteurs",IF(LEFT(Table_Market[[#This Row],[RFM_SCORE]],1)="1","Inactifs",IF(AND(LEFT(Table_Market[[#This Row],[RFM_SCORE]],1)>="2",MID(Table_Market[[#This Row],[RFM_SCORE]],2,1)>="2",RIGHT(Table_Market[[#This Row],[RFM_SCORE]],1)>="2"),"Fidèles rentables","Occasionnels")))) -> Inactifs | U8: 2 | V8: 1 | W8: 2 | X8: 1 | Y8: 1 | Z8: 1 | AA8: 0 | AB8: 0 | AC8: 0 | AD8: 0 | AE8: 0 | AF8: 0 | AG8: 0 | AH8: 0 | AI8: 0 | AJ8: 0 | AK8: 0 | AL8: 3 | AM8: 11 | AN8: 0
A9: 5555 | B9: 1975 | C9: =YEAR(TODAY())-CLEAN!$B9 -> 50 | D9: 45-59 ans | E9: BAC+3 | F9: Divorcé | G9: 153924 | H9: 0 | I9: 0 | J9: =CLEAN!$H9+CLEAN!$I9 -> 0 | K9: 41677 | L9: =YEAR(TODAY())-YEAR(CLEAN!$K9) -> 11 | M9: 81 | N9: =SUM(CLEAN!$AB9:$AE9) -> 0 | O9: =CLEAN!$U9+CLEAN!$V9+CLEAN!$W9+CLEAN!$X9+CLEAN!$Y9+CLEAN!$Z9 -> 6 | P9: =IF(CLEAN!$M9<=32,3,IF(CLEAN!$M9<=65,2,1)) -> 1 | Q9: =IF(Table_Market[[#This Row],[F_TOTAL_achat]]<=14,1,IF(Table_Market[[#This Row],[F_TOTAL_achat]]<=21,2,3)) -> 1 | R9: =IF(Table_Market[[#This Row],[M_TOTAL_dépensé]]<=115,1,IF(Table_Market[[#This Row],[M_TOTAL_dépensé]]<=833,2,3)) -> 1 | S9: =Table_Market[[#This Row],[R_SCORE]]&Table_Market[[#This Row],[F_SCORE]]&Table_Market[[#This Row],[M_SCORE]] -> 111 | T9: =IF(Table_Market[[#This Row],[RFM_SCORE]]="333","Clients élites",IF(LEFT(Table_Market[[#This Row],[RFM_SCORE]],1)="3","Récents prometteurs",IF(LEFT(Table_Market[[#This Row],[RFM_SCORE]],1)="1","Inactifs",IF(AND(LEFT(Table_Market[[#This Row],[RFM_SCORE]],1)>="2",MID(Table_Market[[#This Row],[RFM_SCORE]],2,1)>="2",RIGHT(Table_Market[[#This Row],[RFM_SCORE]],1)>="2"),"Fidèles rentables","Occasionnels")))) -> Inactifs | U9: 1 | V9: 1 | W9: 1 | X9: 1 | Y9: 1 | Z9: 1 | AA9: 0 | AB9: 0 | AC9: 0 | AD9: 0 | AE9: 0 | AF9: 0 | AG9: 0 | AH9: 0 | AI9: 0 | AJ9: 0 | AK9: 0 | AL9: 3 | AM9: 11 | AN9: 0
A10: 4619 | B10: 1945 | C10: =YEAR(TODAY())-CLEAN!$B10 -> 80 | D10: 60 ans et + | E10: Doctorat | F10: Célibataire | G10: 113734 | H10: 0 | I10: 0 | J10: =CLEAN!$H10+CLEAN!$I10 -> 0 | K10: 41787 | L10: =YEAR(TODAY())-YEAR(CLEAN!$K10) -> 11 | M10: 9 | N10: =SUM(CLEAN!$AB10:$AE10) -> 28 | O10: =CLEAN!$U10+CLEAN!$V10+CLEAN!$W10+CLEAN!$X10+CLEAN!$Y10+CLEAN!$Z10 -> 277 | P10: =IF(CLEAN!$M10<=32,3,IF(CLEAN!$M10<=65,2,1)) -> 3 | Q10: =IF(Table_Market[[#This Row],[F_TOTAL_achat]]<=14,1,IF(Table_Market[[#This Row],[F_TOTAL_achat]]<=21,2,3)) -> 3 | R10: =IF(Table_Market[[#This Row],[M_TOTAL_dépensé]]<=115,1,IF(Table_Market[[#This Row],[M_TOTAL_dépensé]]<=833,2,3)) -> 2 | S10: =Table_Market[[#This Row],[R_SCORE]]&Table_Market[[#This Row],[F_SCORE]]&Table_Market[[#This Row],[M_SCORE]] -> 332 | T10: =IF(Table_Market[[#This Row],[RFM_SCORE]]="333","Clients élites",IF(LEFT(Table_Market[[#This Row],[RFM_SCORE]],1)="3","Récents prometteurs",IF(LEFT(Table_Market[[#This Row],[RFM_SCORE]],1)="1","Inactifs",IF(AND(LEFT(Table_Market[[#This Row],[RFM_SCORE]],1)>="2",MID(Table_Market[[#This Row],[RFM_SCORE]],2,1)>="2",RIGHT(Table_Market[[#This Row],[RFM_SCORE]],1)>="2"),"Fidèles rentables","Occasionnels")))) -> Récents prometteurs | U10: 6 | V10: 2 | W10: 3 | X10: 1 | Y10: 262 | Z10: 3 | AA10: 0 | AB10: 27 | AC10: 0 | AD10: 0 | AE10: 1 | AF10: 0 | AG10: 0 | AH10: 0 | AI10: 0 | AJ10: 0 | AK10: 0 | AL10: 3 | AM10: 11 | AN10: 0
A11: 4611 | B11: 1970 | C11: =YEAR(TODAY())-CLEAN!$B11 -> 55 | D11: 45-59 ans | E11: BAC+3 | F11: Conjoint | G11: 105471 | H11: 0 | I11: 0 | J11: =CLEAN!$H11+CLEAN!$I11 -> 0 | K11: 41295 | L11: =YEAR(TODAY())-YEAR(CLEAN!$K11) -> 12 | M11: 36 | N11: =SUM(CLEAN!$AB11:$AE11) -> 33 | O11: =CLEAN!$U11+CLEAN!$V11+CLEAN!$W11+CLEAN!$X11+CLEAN!$Y11+CLEAN!$Z11 -> 1724 | P11: =IF(CLEAN!$M11<=32,3,IF(CLEAN!$M11<=65,2,1)) -> 2 | Q11: =IF(Table_Market[[#This Row],[F_TOTAL_achat]]<=14,1,IF(Table_Market[[#This Row],[F_TOTAL_achat]]<=21,2,3)) -> 3 | R11: =IF(Table_Market[[#This Row],[M_TOTAL_dépensé]]<=115,1,IF(Table_Market[[#This Row],[M_TOTAL_dépensé]]<=833,2,3)) -> 3 | S11: =Table_Market[[#This Row],[R_SCORE]]&Table_Market[[#This Row],[F_SCORE]]&Table_Market[[#This Row],[M_SCORE]] -> 233 | T11: =IF(Table_Market[[#This Row],[RFM_SCORE]]="333","Clients élites",IF(LEFT(Table_Market[[#This Row],[RFM_SCORE]],1)="3","Récents prometteurs",IF(LEFT(Table_Market[[#This Row],[RFM_SCORE]],1)="1","Inactifs",IF(AND(LEFT(Table_Market[[#This Row],[RFM_SCORE]],1)>="2",MID(Table_Market[[#This Row],[RFM_SCORE]],2,1)>="2",RIGHT(Table_Market[[#This Row],[RFM_SCORE]],1)>="2"),"Fidèles rentables","Occasionnels")))) -> Fidèles rentables | U11: 1009 | V11: 181 | W11: 104 | X11: 202 | Y11: 21 | Z11: 207 | AA11: 0 | AB11: 9 | AC11: 8 | AD11: 13 | AE11: 3 | AF11: 0 | AG11: 0 | AH11: 1 | AI11: 1 | AJ11: 0 | AK11: 0 | AL11: 3 | AM11: 11 | AN11: 1
A12: 10089 | B12: 1974 | C12: =YEAR(TODAY())-CLEAN!$B12 -> 51 | D12: 45-59 ans | E12: BAC+3 | F12: Divorcé | G12: 102692 | H12: 0 | I12: 0 | J12: =CLEAN!$H12+CLEAN!$I12 -> 0 | K12: 41369 | L12: =YEAR(TODAY())-YEAR(CLEAN!$K12) -> 12 | M12: 5 | N12: =SUM(CLEAN!$AB12:$AE12) -> 30 | O12: =CLEAN!$U12+CLEAN!$V12+CLEAN!$W12+CLEAN!$X12+CLEAN!$Y12+CLEAN!$Z12 -> 1112 | P12: =IF(CLEAN!$M12<=32,3,IF(CLEAN!$M12<=65,2,1)) -> 3 | Q12: =IF(Table_Market[[#This Row],[F_TOTAL_achat]]<=14,1,IF(Table_Market[[#This Row],[F_TOTAL_achat]]<=21,2,3)) -> 3 | R12: =IF(Table_Market[[#This Row],[M_TOTAL_dépensé]]<=115,1,IF(Table_Market[[#This Row],[M_TOTAL_dépensé]]<=833,2,3)) -> 3 | S12: =Table_Market[[#This Row],[R_SCORE]]&Table_Market[[#This Row],[F_SCORE]]&Table_Market[[#This Row],[M_SCORE]] -> 333 | T12: =IF(Table_Market[[#This Row],[RFM_SCORE]]="333","Clients élites",IF(LEFT(Table_Market[[#This Row],[RFM_SCORE]],1)="3","Récents prometteurs",IF(LEFT(Table_Market[[#This Row],[RFM_SCORE]],1)="1","Inactifs",IF(AND(LEFT(Table_Market[[#This Row],[RFM_SCORE]],1)>="2",MID(Table_Market[[#This Row],[RFM_SCORE]],2,1)>="2",RIGHT(Table_Market[[#This Row],[RFM_SCORE]],1)>="2"),"Fidèles rentables","Occasionnels")))) -> Clients élites | U12: 168 | V12: 148 | W12: 444 | X12: 32 | Y12: 172 | Z12: 148 | AA12: 1 | AB12: 6 | AC12: 9 | AD12: 13 | AE12: 2 | AF12: 0 | AG12: 1 | AH12: 1 | AI12: 1 | AJ12: 1 | AK12: 0 | AL12: 3 | AM12: 11 | AN12: 1
A13: 2798 | B13: 1977 | C13: =YEAR(TODAY())-CLEAN!$B13 -> 48 | D13: 45-59 ans | E13: Doctorat | F13: Conjoint | G13: 102160 | H13: 0 | I13: 0 | J13: =CLEAN!$H13+CLEAN!$I13 -> 0 | K13: 41215 | L13: =YEAR(TODAY())-YEAR(CLEAN!$K13) -> 13 | M13: 54 | N13: =SUM(CLEAN!$AB13:$AE13) -> 30 | O13: =CLEAN!$U13+CLEAN!$V13+CLEAN!$W13+CLEAN!$X13+CLEAN!$Y13+CLEAN!$Z13 -> 1240 | P13: =IF(CLEAN!$M13<=32,3,IF(CLEAN!$M13<=65,2,1)) -> 2 | Q13: =IF(Table_Market[[#This Row],[F_TOTAL_achat]]<=14,1,IF(Table_Market[[#This Row],[F_TOTAL_achat]]<=21,2,3)) -> 3 | R13: =IF(Table_Market[[#This Row],[M_TOTAL_dépensé]]<=115,1,IF(Table_Market[[#This Row],[M_TOTAL_dépensé]]<=833,2,3)) -> 3 | S13: =Table_Market[[#This Row],[R_SCORE]]&Table_Market[[#This Row],[F_SCORE]]&Table_Market[[#This Row],[M_SCORE]] -> 233 | T13: =IF(Table_Market[[#This Row],[RFM_SCORE]]="333","Clients élites",IF(LEFT(Table_Market[[#This Row],[RFM_SCORE]],1)="3","Récents prometteurs",IF(LEFT(Table_Market[[#This Row],[RFM_SCORE]],1)="1","Inactifs",IF(AND(LEFT(Table_Market[[#This Row],[RFM_SCORE]],1)>="2",MID(Table_Market[[#This Row],[RFM_SCORE]],2,1)>="2",RIGHT(Table_Market[[#This Row],[RFM_SCORE]],1)>="2"),"Fidèles rentables","Occasionnels")))) -> Fidèles rentables | U13: 763 | V13: 29 | W13: 138 | X13: 76 | Y13: 176 | Z13: 58 | AA13: 0 | AB13: 7 | AC13: 9 | AD13: 10 | AE13: 4 | AF13: 0 | AG13: 1 | AH13: 1 | AI13: 1 | AJ13: 0 | AK13: 0 | AL13: 3 | AM13: 11 | AN13: 1
... A63: 6421 | B63: 1961 | C63: =YEAR(TODAY())-CLEAN!$B63 -> 64 | D63: 60 ans et + | E63: BAC+3 | F63: Conjoint | G63: 88347 | H63: 0 | I63: 0 | J63: =CLEAN!$H63+CLEAN!$I63 -> 0 | K63: 41458 | L63: =YEAR(TODAY())-YEAR(CLEAN!$K63) -> 12 | M63: 32 | N63: =SUM(CLEAN!$AB63:$AE63) -> 21 | O63: =CLEAN!$U63+CLEAN!$V63+CLEAN!$W63+CLEAN!$X63+CLEAN!$Y63+CLEAN!$Z63 -> 2116 | P63: =IF(CLEAN!$M63<=32,3,IF(CLEAN!$M63<=65,2,1)) -> 3 | Q63: =IF(Table_Market[[#This Row],[F_TOTAL_achat]]<=14,1,IF(Table_Market[[#This Row],[F_TOTAL_achat]]<=21,2,3)) -> 2 | R63: =IF(Table_Market[[#This Row],[M_TOTAL_dépensé]]<=115,1,IF(Table_Market[[#This Row],[M_TOTAL_dépensé]]<=833,2,3)) -> 3 | S63: =Table_Market[[#This Row],[R_SCORE]]&Table_Market[[#This Row],[F_SCORE]]&Table_Market[[#This Row],[M_SCORE]] -> 323 | T63: =IF(Table_Market[[#This Row],[RFM_SCORE]]="333","Clients élites",IF(LEFT(Table_Market[[#This Row],[RFM_SCORE]],1)="3","Récents prometteurs",IF(LEFT(Table_Market[[#This Row],[RFM_SCORE]],1)="1","Inactifs",IF(AND(LEFT(Table_Market[[#This Row],[RFM_SCORE]],1)>="2",MID(Table_Market[[#This Row],[RFM_SCORE]],2,1)>="2",RIGHT(Table_Market[[#This Row],[RFM_SCORE]],1)>="2"),"Fidèles rentables","Occasionnels")))) -> Récents prometteurs | U63: 1050 | V63: 178 | W63: 555 | X63: 77 | Y63: 138 | Z63: 118 | AA63: 1 | AB63: 4 | AC63: 7 | AD63: 9 | AE63: 1 | AF63: 0 | AG63: 0 | AH63: 0 | AI63: 1 | AJ63: 0 | AK63: 0 | AL63: 3 | AM63: 11 | AN63: 0
A64: 10469 | B64: 1981 | C64: =YEAR(TODAY())-CLEAN!$B64 -> 44 | D64: 30-44 ans | E64: BAC+3 | F64: Conjoint | G64: 88325 | H64: 0 | I64: 0 | J64: =CLEAN!$H64+CLEAN!$I64 -> 0 | K64: 41675 | M64: 42 | N64: =SUM(CLEAN!$AB64:$AE64) -> 19 | O64: =CLEAN!$U64+CLEAN!$V64+CLEAN!$W64+CLEAN!$X64+CLEAN!$Y64+CLEAN!$Z64 -> 1623 | P64: =IF(CLEAN!$M64<=32,3,IF(CLEAN!$M64<=65,2,1)) -> 2 | Q64: =IF(Table_Market[[#This Row],[F_TOTAL_achat]]<=14,1,IF(Table_Market[[#This Row],[F_TOTAL_achat]]<=21,2,3)) -> 2 | R64: =IF(Table_Market[[#This Row],[M_TOTAL_dépensé]]<=115,1,IF(Table_Market[[#This Row],[M_TOTAL_dépensé]]<=833,2,3)) -> 3 | S64: =Table_Market[[#This Row],[R_SCORE]]&Table_Market[[#This Row],[F_SCORE]]&Table_Market[[#This Row],[M_SCORE]] -> 223 | T64: =IF(Table_Market[[#This Row],[RFM_SCORE]]="333","Clients élites",IF(LEFT(Table_Market[[#This Row],[RFM_SCORE]],1)="3","Récents prometteurs",IF(LEFT(Table_Market[[#This Row],[RFM_SCORE]],1)="1","Inactifs",IF(AND(LEFT(Table_Market[[#This Row],[RFM_SCORE]],1)>="2",MID(Table_Market[[#This Row],[RFM_SCORE]],2,1)>="2",RIGHT(Table_Market[[#This Row],[RFM_SCORE]],1)>="2"),"Fidèles rentables","Occasionnels")))) -> Fidèles rentables | U64: 519 | V64: 71 | W64: 860 | X64: 93 | Y64: 27 | Z64: 53 | AA64: 1 | AB64: 6 | AC64: 2 | AD64: 9 | AE64: 2 | AF64: 0 | AG64: 0 | AH64: 0 | AI64: 0 | AJ64: 0 | AK64: 0 | AL64: 3 | AM64: 11 | AN64: 0
A65: 9369 | B65: 1979 | C65: =YEAR(TODAY())-CLEAN!$B65 -> 46 | D65: 45-59 ans | E65: BAC+5 | F65: Célibataire | G65: 88194 | H65: 0 | I65: 1 | J65: =CLEAN!$H65+CLEAN!$I65 -> 1 | K65: 41717 | L65: =YEAR(TODAY())-YEAR(CLEAN!$K65) -> 11 | M65: 19 | N65: =SUM(CLEAN!$AB65:$AE65) -> 36 | O65: =CLEAN!$U65+CLEAN!$V65+CLEAN!$W65+CLEAN!$X65+CLEAN!$Y65+CLEAN!$Z65 -> 1274 | P65: =IF(CLEAN!$M65<=32,3,IF(CLEAN!$M65<=65,2,1)) -> 3 | Q65: =IF(Table_Market[[#This Row],[F_TOTAL_achat]]<=14,1,IF(Table_Market[[#This Row],[F_TOTAL_achat]]<=21,2,3)) -> 3 | R65: =IF(Table_Market[[#This Row],[M_TOTAL_dépensé]]<=115,1,IF(Table_Market[[#This Row],[M_TOTAL_dépensé]]<=833,2,3)) -> 3 | S65: =Table_Market[[#This Row],[R_SCORE]]&Table_Market[[#This Row],[F_SCORE]]&Table_Market[[#This Row],[M_SCORE]] -> 333 | T65: =IF(Table_Market[[#This Row],[RFM_SCORE]]="333","Clients élites",IF(LEFT(Table_Market[[#This Row],[RFM_SCORE]],1)="3","Récents prometteurs",IF(LEFT(Table_Market[[#This Row],[RFM_SCORE]],1)="1","Inactifs",IF(AND(LEFT(Table_Market[[#This Row],[RFM_SCORE]],1)>="2",MID(Table_Market[[#This Row],[RFM_SCORE]],2,1)>="2",RIGHT(Table_Market[[#This Row],[RFM_SCORE]],1)>="2"),"Fidèles rentables","Occasionnels")))) -> Clients élites | U65: 688 | V65: 14 | W65: 309 | X65: 201 | Y65: 24 | Z65: 38 | AA65: 1 | AB65: 11 | AC65: 10 | AD65: 10 | AE65: 5 | AF65: 1 | AG65: 0 | AH65: 0 | AI65: 1 | AJ65: 0 | AK65: 0 | AL65: 3 | AM65: 11 | AN65: 1
A66: 2535 | B66: 1978 | C66: =YEAR(TODAY())-CLEAN!$B66 -> 47 | D66: 45-59 ans | E66: BAC+5 | F66: Marié | G66: 88097 | H66: 1 | I66: 0 | J66: =CLEAN!$H66+CLEAN!$I66 -> 1 | K66: 41139 | L66: =YEAR(TODAY())-YEAR(CLEAN!$K66) -> 13 | M66: 24 | N66: =SUM(CLEAN!$AB66:$AE66) -> 28 | O66: =CLEAN!$U66+CLEAN!$V66+CLEAN!$W66+CLEAN!$X66+CLEAN!$Y66+CLEAN!$Z66 -> 844 | P66: =IF(CLEAN!$M66<=32,3,IF(CLEAN!$M66<=65,2,1)) -> 3 | Q66: =IF(Table_Market[[#This Row],[F_TOTAL_achat]]<=14,1,IF(Table_Market[[#This Row],[F_TOTAL_achat]]<=21,2,3)) -> 3 | R66: =IF(Table_Market[[#This Row],[M_TOTAL_dépensé]]<=115,1,IF(Table_Market[[#This Row],[M_TOTAL_dépensé]]<=833,2,3)) -> 3 | S66: =Table_Market[[#This Row],[R_SCORE]]&Table_Market[[#This Row],[F_SCORE]]&Table_Market[[#This Row],[M_SCORE]] -> 333 | T66: =IF(Table_Market[[#This Row],[RFM_SCORE]]="333","Clients élites",IF(LEFT(Table_Market[[#This Row],[RFM_SCORE]],1)="3","Récents prometteurs",IF(LEFT(Table_Market[[#This Row],[RFM_SCORE]],1)="1","Inactifs",IF(AND(LEFT(Table_Market[[#This Row],[RFM_SCORE]],1)>="2",MID(Table_Market[[#This Row],[RFM_SCORE]],2,1)>="2",RIGHT(Table_Market[[#This Row],[RFM_SCORE]],1)>="2"),"Fidèles rentables","Occasionnels")))) -> Clients élites | U66: 163 | V66: 0 | W66: 480 | X66: 0 | Y66: 126 | Z66: 75 | AA66: 1 | AB66: 6 | AC66: 5 | AD66: 8 | AE66: 9 | AF66: 0 | AG66: 1 | AH66: 1 | AI66: 1 | AJ66: 0 | AK66: 0 | AL66: 3 | AM66: 11 | AN66: 1
A67: 3174 | B67: 1959 | C67: =YEAR(TODAY())-CLEAN!$B67 -> 66 | D67: 60 ans et + | E67: BAC+3 | F67: Conjoint | G67: 87771 | H67: 0 | I67: 1 | J67: =CLEAN!$H67+CLEAN!$I67 -> 1 | K67: 41416 | L67: =YEAR(TODAY())-YEAR(CLEAN!$K67) -> 12 | M67: 61 | N67: =SUM(CLEAN!$AB67:$AE67) -> 25 | O67: =CLEAN!$U67+CLEAN!$V67+CLEAN!$W67+CLEAN!$X67+CLEAN!$Y67+CLEAN!$Z67 -> 1957 | P67: =IF(CLEAN!$M67<=32,3,IF(CLEAN!$M67<=65,2,1)) -> 2 | Q67: =IF(Table_Market[[#This Row],[F_TOTAL_achat]]<=14,1,IF(Table_Market[[#This Row],[F_TOTAL_achat]]<=21,2,3)) -> 3 | R67: =IF(Table_Market[[#This Row],[M_TOTAL_dépensé]]<=115,1,IF(Table_Market[[#This Row],[M_TOTAL_dépensé]]<=833,2,3)) -> 3 | S67: =Table_Market[[#This Row],[R_SCORE]]&Table_Market[[#This Row],[F_SCORE]]&Table_Market[[#This Row],[M_SCORE]] -> 233 | T67: =IF(Table_Market[[#This Row],[RFM_SCORE]]="333","Clients élites",IF(LEFT(Table_Market[[#This Row],[RFM_SCORE]],1)="3","Récents prometteurs",IF(LEFT(Table_Market[[#This Row],[RFM_SCORE]],1)="1","Inactifs",IF(AND(LEFT(Table_Market[[#This Row],[RFM_SCORE]],1)>="2",MID(Table_Market[[#This Row],[RFM_SCORE]],2,1)>="2",RIGHT(Table_Market[[#This Row],[RFM_SCORE]],1)>="2"),"Fidèles rentables","Occasionnels")))) -> Fidèles rentables | U67: 1492 | V67: 38 | W67: 287 | X67: 50 | Y67: 57 | Z67: 33 | AA67: 1 | AB67: 5 | AC67: 10 | AD67: 4 | AE67: 6 | AF67: 0 | AG67: 1 | AH67: 1 | AI67: 1 | AJ67: 1 | AK67: 0 | AL67: 3 | AM67: 11 | AN67: 1
A68: 5536 | B68: 1959 | C68: =YEAR(TODAY())-CLEAN!$B68 -> 66 | D68: 60 ans et + | E68: BAC+3 | F68: Conjoint | G68: 87771 | H68: 0 | I68: 1 | J68: =CLEAN!$H68+CLEAN!$I68 -> 1 | K68: 41416 | L68: =YEAR(TODAY())-YEAR(CLEAN!$K68) -> 12 | M68: 61 | N68: =SUM(CLEAN!$AB68:$AE68) -> 25 | O68: =CLEAN!$U68+CLEAN!$V68+CLEAN!$W68+CLEAN!$X68+CLEAN!$Y68+CLEAN!$Z68 -> 1957 | P68: =IF(CLEAN!$M68<=32,3,IF(CLEAN!$M68<=65,2,1)) -> 2 | Q68: =IF(Table_Market[[#This Row],[F_TOTAL_achat]]<=14,1,IF(Table_Market[[#This Row],[F_TOTAL_achat]]<=21,2,3)) -> 3 | R68: =IF(Table_Market[[#This Row],[M_TOTAL_dépensé]]<=115,1,IF(Table_Market[[#This Row],[M_TOTAL_dépensé]]<=833,2,3)) -> 3 | S68: =Table_Market[[#This Row],[R_SCORE]]&Table_Market[[#This Row],[F_SCORE]]&Table_Market[[#This Row],[M_SCORE]] -> 233 | T68: =IF(Table_Market[[#This Row],[RFM_SCORE]]="333","Clients élites",IF(LEFT(Table_Market[[#This Row],[RFM_SCORE]],1)="3","Récents prometteurs",IF(LEFT(Table_Market[[#This Row],[RFM_SCORE]],1)="1","Inactifs",IF(AND(LEFT(Table_Market[[#This Row],[RFM_SCORE]],1)>="2",MID(Table_Market[[#This Row],[RFM_SCORE]],2,1)>="2",RIGHT(Table_Market[[#This Row],[RFM_SCORE]],1)>="2"),"Fidèles rentables","Occasionnels")))) -> Fidèles rentables | U68: 1492 | V68: 38 | W68: 287 | X68: 50 | Y68: 57 | Z68: 33 | AA68: 1 | AB68: 5 | AC68: 10 | AD68: 4 | AE68: 6 | AF68: 0 | AG68: 1 | AH68: 1 | AI68: 1 | AJ68: 1 | AK68: 0 | AL68: 3 | AM68: 11 | AN68: 1
A69: 1763 | B69: 1988 | C69: =YEAR(TODAY())-CLEAN!$B69 -> 37 | D69: 30-44 ans | E69: BAC+3 | F69: Conjoint | G69: 87679 | H69: 0 | I69: 0 | J69: =CLEAN!$H69+CLEAN!$I69 -> 0 | K69: 41482 | L69: =YEAR(TODAY())-YEAR(CLEAN!$K69) -> 12 | M69: 62 | N69: =SUM(CLEAN!$AB69:$AE69) -> 32 | O69: =CLEAN!$U69+CLEAN!$V69+CLEAN!$W69+CLEAN!$X69+CLEAN!$Y69+CLEAN!$Z69 -> 2524 | P69: =IF(CLEAN!$M69<=32,3,IF(CLEAN!$M69<=65,2,1)) -> 2 | Q69: =IF(Table_Market[[#This Row],[F_TOTAL_achat]]<=14,1,IF(Table_Market[[#This Row],[F_TOTAL_achat]]<=21,2,3)) -> 3 | R69: =IF(Table_Market[[#This Row],[M_TOTAL_dépensé]]<=115,1,IF(Table_Market[[#This Row],[M_TOTAL_dépensé]]<=833,2,3)) -> 3 | S69: =Table_Market[[#This Row],[R_SCORE]]&Table_Market[[#This Row],[F_SCORE]]&Table_Market[[#This Row],[M_SCORE]] -> 233 | T69: =IF(Table_Market[[#This Row],[RFM_SCORE]]="333","Clients élites",IF(LEFT(Table_Market[[#This Row],[RFM_SCORE]],1)="3","Récents prometteurs",IF(LEFT(Table_Market[[#This Row],[RFM_SCORE]],1)="1","Inactifs",IF(AND(LEFT(Table_Market[[#This Row],[RFM_SCORE]],1)>="2",MID(Table_Market[[#This Row],[RFM_SCORE]],2,1)>="2",RIGHT(Table_Market[[#This Row],[RFM_SCORE]],1)>="2"),"Fidèles rentables","Occasionnels")))) -> Fidèles rentables | U69: 1259 | V69: 172 | W69: 815 | X69: 97 | Y69: 148 | Z69: 33 | AA69: 1 | AB69: 7 | AC69: 11 | AD69: 10 | AE69: 4 | AF69: 1 | AG69: 0 | AH69: 1 | AI69: 1 | AJ69: 0 | AK69: 0 | AL69: 3 | AM69: 11 | AN69: 1
A70: 3619 | B70: 1960 | C70: =YEAR(TODAY())-CLEAN!$B70 -> 65 | D70: 60 ans et + | E70: BAC+5 | F70: Divorcé | G70: 87305 | H70: 0 | I70: 0 | J70: =CLEAN!$H70+CLEAN!$I70 -> 0 | K70: 41175 | L70: =YEAR(TODAY())-YEAR(CLEAN!$K70) -> 13 | M70: 19 | N70: =SUM(CLEAN!$AB70:$AE70) -> 18 | O70: =CLEAN!$U70+CLEAN!$V70+CLEAN!$W70+CLEAN!$X70+CLEAN!$Y70+CLEAN!$Z70 -> 1152 | P70: =IF(CLEAN!$M70<=32,3,IF(CLEAN!$M70<=65,2,1)) -> 3 | Q70: =IF(Table_Market[[#This Row],[F_TOTAL_achat]]<=14,1,IF(Table_Market[[#This Row],[F_TOTAL_achat]]<=21,2,3)) -> 2 | R70: =IF(Table_Market[[#This Row],[M_TOTAL_dépensé]]<=115,1,IF(Table_Market[[#This Row],[M_TOTAL_dépensé]]<=833,2,3)) -> 3 | S70: =Table_Market[[#This Row],[R_SCORE]]&Table_Market[[#This Row],[F_SCORE]]&Table_Market[[#This Row],[M_SCORE]] -> 323 | T70: =IF(Table_Market[[#This Row],[RFM_SCORE]]="333","Clients élites",IF(LEFT(Table_Market[[#This Row],[RFM_SCORE]],1)="3","Récents prometteurs",IF(LEFT(Table_Market[[#This Row],[RFM_SCORE]],1)="1","Inactifs",IF(AND(LEFT(Table_Market[[#This Row],[RFM_SCORE]],1)>="2",MID(Table_Market[[#This Row],[RFM_SCORE]],2,1)>="2",RIGHT(Table_Market[[#This Row],[RFM_SCORE]],1)>="2"),"Fidèles rentables","Occasionnels")))) -> Récents prometteurs | U70: 345 | V70: 25 | W70: 501 | X70: 63 | Y70: 138 | Z70: 80 | AA70: 1 | AB70: 5 | AC70: 3 | AD70: 8 | AE70: 2 | AF70: 0 | AG70: 0 | AH70: 1 | AI70: 0 | AJ70: 0 | AK70: 0 | AL70: 3 | AM70: 11 | AN70: 1
A71: 8908 | B71: 1959 | C71: =YEAR(TODAY())-CLEAN!$B71 -> 66 | D71: 60 ans et + | E71: BAC+3 | F71: Marié | G71: 87195 | H71: 0 | I71: 0 | J71: =CLEAN!$H71+CLEAN!$I71 -> 0 | K71: 41767 | L71: =YEAR(TODAY())-YEAR(CLEAN!$K71) -> 11 | M71: 35 | N71: =SUM(CLEAN!$AB71:$AE71) -> 20 | O71: =CLEAN!$U71+CLEAN!$V71+CLEAN!$W71+CLEAN!$X71+CLEAN!$Y71+CLEAN!$Z71 -> 1097 | P71: =IF(CLEAN!$M71<=32,3,IF(CLEAN!$M71<=65,2,1)) -> 2 | Q71: =IF(Table_Market[[#This Row],[F_TOTAL_achat]]<=14,1,IF(Table_Market[[#This Row],[F_TOTAL_achat]]<=21,2,3)) -> 2 | R71: =IF(Table_Market[[#This Row],[M_TOTAL_dépensé]]<=115,1,IF(Table_Market[[#This Row],[M_TOTAL_dépensé]]<=833,2,3)) -> 3 | S71: =Table_Market[[#This Row],[R_SCORE]]&Table_Market[[#This Row],[F_SCORE]]&Table_Market[[#This Row],[M_SCORE]] -> 223 | T71: =IF(Table_Market[[#This Row],[RFM_SCORE]]="333","Clients élites",IF(LEFT(Table_Market[[#This Row],[RFM_SCORE]],1)="3","Récents prometteurs",IF(LEFT(Table_Market[[#This Row],[RFM_SCORE]],1)="1","Inactifs",IF(AND(LEFT(Table_Market[[#This Row],[RFM_SCORE]],1)>="2",MID(Table_Market[[#This Row],[RFM_SCORE]],2,1)>="2",RIGHT(Table_Market[[#This Row],[RFM_SCORE]],1)>="2"),"Fidèles rentables","Occasionnels")))) -> Fidèles rentables | U71: 217 | V71: 76 | W71: 690 | X71: 50 | Y71: 26 | Z71: 38 | AA71: 1 | AB71: 3 | AC71: 11 | AD71: 5 | AE71: 1 | AF71: 0 | AG71: 0 | AH71: 0 | AI71: 0 | AJ71: 0 | AK71: 0 | AL71: 3 | AM71: 11 | AN71: 1
A72: 4278 | B72: 1983 | C72: =YEAR(TODAY())-CLEAN!$B72 -> 42 | D72: 30-44 ans | E72: Doctorat | F72: Célibataire | G72: 87188 | H72: 0 | I72: 0 | J72: =CLEAN!$H72+CLEAN!$I72 -> 0 | K72: 41428 | L72: =YEAR(TODAY())-YEAR(CLEAN!$K72) -> 12 | M72: 73 | N72: =SUM(CLEAN!$AB72:$AE72) -> 21 | O72: =CLEAN!$U72+CLEAN!$V72+CLEAN!$W72+CLEAN!$X72+CLEAN!$Y72+CLEAN!$Z72 -> 1923 | P72: =IF(CLEAN!$M72<=32,3,IF(CLEAN!$M72<=65,2,1)) -> 1 | Q72: =IF(Table_Market[[#This Row],[F_TOTAL_achat]]<=14,1,IF(Table_Market[[#This Row],[F_TOTAL_achat]]<=21,2,3)) -> 2 | R72: =IF(Table_Market[[#This Row],[M_TOTAL_dépensé]]<=115,1,IF(Table_Market[[#This Row],[M_TOTAL_dépensé]]<=833,2,3)) -> 3 | S72: =Table_Market[[#This Row],[R_SCORE]]&Table_Market[[#This Row],[F_SCORE]]&Table_Market[[#This Row],[M_SCORE]] -> 123 | T72: =IF(Table_Market[[#This Row],[RFM_SCORE]]="333","Clients élites",IF(LEFT(Table_Market[[#This Row],[RFM_SCORE]],1)="3","Récents prometteurs",IF(LEFT(Table_Market[[#This Row],[RFM_SCORE]],1)="1","Inactifs",IF(AND(LEFT(Table_Market[[#This Row],[RFM_SCORE]],1)>="2",MID(Table_Market[[#This Row],[RFM_SCORE]],2,1)>="2",RIGHT(Table_Market[[#This Row],[RFM_SCORE]],1)>="2"),"Fidèles rentables","Occasionnels")))) -> Inactifs | U72: 910 | V72: 111 | W72: 724 | X72: 49 | Y72: 74 | Z72: 55 | AA72: 1 | AB72: 10 | AC72: 2 | AD72: 6 | AE72: 3 | AF72: 0 | AG72: 0 | AH72: 0 | AI72: 0 | AJ72: 0 | AK72: 0 | AL72: 3 | AM72: 11 | AN72: 1
A73: 4207 | B73: 1981 | C73: =YEAR(TODAY())-CLEAN!$B73 -> 44 | D73: 30-44 ans | E73: Doctorat | F73: Marié | G73: 87171 | H73: 0 | I73: 0 | J73: =CLEAN!$H73+CLEAN!$I73 -> 0 | K73: 41395 | L73: =YEAR(TODAY())-YEAR(CLEAN!$K73) -> 12 | M73: 27 | N73: =SUM(CLEAN!$AB73:$AE73) -> 26 | O73: =CLEAN!$U73+CLEAN!$V73+CLEAN!$W73+CLEAN!$X73+CLEAN!$Y73+CLEAN!$Z73 -> 1298 | P73: =IF(CLEAN!$M73<=32,3,IF(CLEAN!$M73<=65,2,1)) -> 3 | Q73: =IF(Table_Market[[#This Row],[F_TOTAL_achat]]<=14,1,IF(Table_Market[[#This Row],[F_TOTAL_achat]]<=21,2,3)) -> 3 | R73: =IF(Table_Market[[#This Row],[M_TOTAL_dépensé]]<=115,1,IF(Table_Market[[#This Row],[M_TOTAL_dépensé]]<=833,2,3)) -> 3 | S73: =Table_Market[[#This Row],[R_SCORE]]&Table_Market[[#This Row],[F_SCORE]]&Table_Market[[#This Row],[M_SCORE]] -> 333 | T73: =IF(Table_Market[[#This Row],[RFM_SCORE]]="333","Clients élites",IF(LEFT(Table_Market[[#This Row],[RFM_SCORE]],1)="3","Récents prometteurs",IF(LEFT(Table_Market[[#This Row],[RFM_SCORE]],1)="1","Inactifs",IF(AND(LEFT(Table_Market[[#This Row],[RFM_SCORE]],1)>="2",MID(Table_Market[[#This Row],[RFM_SCORE]],2,1)>="2",RIGHT(Table_Market[[#This Row],[RFM_SCORE]],1)>="2"),"Fidèles rentables","Occasionnels")))) -> Clients élites | U73: 1001 | V73: 44 | W73: 107 | X73: 58 | Y73: 44 | Z73: 44 | AA73: 1 | AB73: 6 | AC73: 7 | AD73: 11 | AE73: 2 | AF73: 1 | AG73: 0 | AH73: 1 | AI73: 0 | AJ73: 0 | AK73: 0 | AL73: 3 | AM73: 11 | AN73: 0
A74: 2802 | B74: 1992 | C74: =YEAR(TODAY())-CLEAN!$B74 -> 33 | D74: 30-44 ans | E74: BAC+5 | F74: Marié | G74: 87000 | H74: 0 | I74: 0 | J74: =CLEAN!$H74+CLEAN!$I74 -> 0 | K74: 41258 | L74: =YEAR(TODAY())-YEAR(CLEAN!$K74) -> 13 | M74: 61 | N74: =SUM(CLEAN!$AB74:$AE74) -> 19 | O74: =CLEAN!$U74+CLEAN!$V74+CLEAN!$W74+CLEAN!$X74+CLEAN!$Y74+CLEAN!$Z74 -> 961 | P74: =IF(CLEAN!$M74<=32,3,IF(CLEAN!$M74<=65,2,1)) -> 2 | Q74: =IF(Table_Market[[#This Row],[F_TOTAL_achat]]<=14,1,IF(Table_Market[[#This Row],[F_TOTAL_achat]]<=21,2,3)) -> 2 | R74: =IF(Table_Market[[#This Row],[M_TOTAL_dépensé]]<=115,1,IF(Table_Market[[#This Row],[M_TOTAL_dépensé]]<=833,2,3)) -> 3 | S74: =Table_Market[[#This Row],[R_SCORE]]&Table_Market[[#This Row],[F_SCORE]]&Table_Market[[#This Row],[M_SCORE]] -> 223 | T74: =IF(Table_Market[[#This Row],[RFM_SCORE]]="333","Clients élites",IF(LEFT(Table_Market[[#This Row],[RFM_SCORE]],1)="3","Récents prometteurs",IF(LEFT(Table_Market[[#This Row],[RFM_SCORE]],1)="1","Inactifs",IF(AND(LEFT(Table_Market[[#This Row],[RFM_SCORE]],1)>="2",MID(Table_Market[[#This Row],[RFM_SCORE]],2,1)>="2",RIGHT(Table_Market[[#This Row],[RFM_SCORE]],1)>="2"),"Fidèles rentables","Occasionnels")))) -> Fidèles rentables | U74: 196 | V74: 25 | W74: 607 | X74: 67 | Y74: 17 | Z74: 49 | AA74: 1 | AB74: 4 | AC74: 6 | AD74: 7 | AE74: 2 | AF74: 0 | AG74: 0 | AH74: 0 | AI74: 0 | AJ74: 0 | AK74: 0 | AL74: 3 | AM74: 11 | AN74: 0
A75: 5113 | B75: 1971 | C75: =YEAR(TODAY())-CLEAN!$B75 -> 54 | D75: 45-59 ans | E75: Doctorat | F75: Divorcé | G75: 86979 | H75: 0 | I75: 0 | J75: =CLEAN!$H75+CLEAN!$I75 -> 0 | K75: 41585 | L75: =YEAR(TODAY())-YEAR(CLEAN!$K75) -> 12 | M75: 67 | N75: =SUM(CLEAN!$AB75:$AE75) -> 17 | O75: =CLEAN!$U75+CLEAN!$V75+CLEAN!$W75+CLEAN!$X75+CLEAN!$Y75+CLEAN!$Z75 -> 1702 | P75: =IF(CLEAN!$M75<=32,3,IF(CLEAN!$M75<=65,2,1)) -> 1 | Q75: =IF(Table_Market[[#This Row],[F_TOTAL_achat]]<=14,1,IF(Table_Market[[#This Row],[F_TOTAL_achat]]<=21,2,3)) -> 2 | R75: =IF(Table_Market[[#This Row],[M_TOTAL_dépensé]]<=115,1,IF(Table_Market[[#This Row],[M_TOTAL_dépensé]]<=833,2,3)) -> 3 | S75: =Table_Market[[#This Row],[R_SCORE]]&Table_Market[[#This Row],[F_SCORE]]&Table_Market[[#This Row],[M_SCORE]] -> 123 | T75: =IF(Table_Market[[#This Row],[RFM_SCORE]]="333","Clients élites",IF(LEFT(Table_Market[[#This Row],[RFM_SCORE]],1)="3","Récents prometteurs",IF(LEFT(Table_Market[[#This Row],[RFM_SCORE]],1)="1","Inactifs",IF(AND(LEFT(Table_Market[[#This Row],[RFM_SCORE]],1)>="2",MID(Table_Market[[#This Row],[RFM_SCORE]],2,1)>="2",RIGHT(Table_Market[[#This Row],[RFM_SCORE]],1)>="2"),"Fidèles rentables","Occasionnels")))) -> Inactifs | U75: 584 | V75: 100 | W75: 835 | X75: 65 | Y75: 83 | Z75: 35 | AA75: 1 | AB75: 5 | AC75: 5 | AD75: 5 | AE75: 2 | AF75: 1 | AG75: 0 | AH75: 0 | AI75: 0 | AJ75: 0 | AK75: 0 | AL75: 3 | AM75: 11 | AN75: 1
A76: 9826 | B76: 1972 | C76: =YEAR(TODAY())-CLEAN!$B76 -> 53 | D76: 45-59 ans | E76: Doctorat | F76: Célibataire | G76: 86857 | H76: 0 | I76: 0 | J76: =CLEAN!$H76+CLEAN!$I76 -> 0 | K76: 41164 | L76: =YEAR(TODAY())-YEAR(CLEAN!$K76) -> 13 | M76: 96 | N76: =SUM(CLEAN!$AB76:$AE76) -> 23 | O76: =CLEAN!$U76+CLEAN!$V76+CLEAN!$W76+CLEAN!$X76+CLEAN!$Y76+CLEAN!$Z76 -> 2114 | P76: =IF(CLEAN!$M76<=32,3,IF(CLEAN!$M76<=65,2,1)) -> 1 | Q76: =IF(Table_Market[[#This Row],[F_TOTAL_achat]]<=14,1,IF(Table_Market[[#This Row],[F_TOTAL_achat]]<=21,2,3)) -> 3 | R76: =IF(Table_Market[[#This Row],[M_TOTAL_dépensé]]<=115,1,IF(Table_Market[[#This Row],[M_TOTAL_dépensé]]<=833,2,3)) -> 3 | S76: =Table_Market[[#This Row],[R_SCORE]]&Table_Market[[#This Row],[F_SCORE]]&Table_Market[[#This Row],[M_SCORE]] -> 133 | T76: =IF(Table_Market[[#This Row],[RFM_SCORE]]="333","Clients élites",IF(LEFT(Table_Market[[#This Row],[RFM_SCORE]],1)="3","Récents prometteurs",IF(LEFT(Table_Market[[#This Row],[RFM_SCORE]],1)="1","Inactifs",IF(AND(LEFT(Table_Market[[#This Row],[RFM_SCORE]],1)>="2",MID(Table_Market[[#This Row],[RFM_SCORE]],2,1)>="2",RIGHT(Table_Market[[#This Row],[RFM_SCORE]],1)>="2"),"Fidèles rentables","Occasionnels")))) -> Inactifs | U76: 899 | V76: 102 | W76: 838 | X76: 133 | Y76: 102 | Z76: 40 | AA76: 1 | AB76: 5 | AC76: 6 | AD76: 10 | AE76: 2 | AF76: 0 | AG76: 0 | AH76: 0 | AI76: 0 | AJ76: 0 | AK76: 0 | AL76: 3 | AM76: 11 | AN76: 1
... A160: 9589 | B160: 1948 | C160: =YEAR(TODAY())-CLEAN!$B160 -> 77 | D160: 60 ans et + | E160: Doctorat | F160: Veuf | G160: 82032 | H160: 0 | I160: 0 | J160: =CLEAN!$H160+CLEAN!$I160 -> 0 | K160: 41734 | L160: =YEAR(TODAY())-YEAR(CLEAN!$K160) -> 11 | M160: 54 | N160: =SUM(CLEAN!$AB160:$AE160) -> 18 | O160: =CLEAN!$U160+CLEAN!$V160+CLEAN!$W160+CLEAN!$X160+CLEAN!$Y160+CLEAN!$Z160 -> 1234 | P160: =IF(CLEAN!$M160<=32,3,IF(CLEAN!$M160<=65,2,1)) -> 2 | Q160: =IF(Table_Market[[#This Row],[F_TOTAL_achat]]<=14,1,IF(Table_Market[[#This Row],[F_TOTAL_achat]]<=21,2,3)) -> 2 | R160: =IF(Table_Market[[#This Row],[M_TOTAL_dépensé]]<=115,1,IF(Table_Market[[#This Row],[M_TOTAL_dépensé]]<=833,2,3)) -> 3 | S160: =Table_Market[[#This Row],[R_SCORE]]&Table_Market[[#This Row],[F_SCORE]]&Table_Market[[#This Row],[M_SCORE]] -> 223 | T160: =IF(Table_Market[[#This Row],[RFM_SCORE]]="333","Clients élites",IF(LEFT(Table_Market[[#This Row],[RFM_SCORE]],1)="3","Récents prometteurs",IF(LEFT(Table_Market[[#This Row],[RFM_SCORE]],1)="1","Inactifs",IF(AND(LEFT(Table_Market[[#This Row],[RFM_SCORE]],1)>="2",MID(Table_Market[[#This Row],[RFM_SCORE]],2,1)>="2",RIGHT(Table_Market[[#This Row],[RFM_SCORE]],1)>="2"),"Fidèles rentables","Occasionnels")))) -> Fidèles rentables | U160: 332 | V160: 194 | W160: 377 | X160: 149 | Y160: 125 | Z160: 57 | AA160: 0 | AB160: 4 | AC160: 6 | AD160: 7 | AE160: 1 | AF160: 0 | AG160: 0 | AH160: 0 | AI160: 0 | AJ160: 0 | AK160: 0 | AL160: 3 | AM160: 11 | AN160: 0
A161: 6810 | B161: 1983 | C161: =YEAR(TODAY())-CLEAN!$B161 -> 42 | D161: 30-44 ans | E161: BAC+3 | F161: Divorcé | G161: 82025 | H161: 0 | I161: 0 | J161: =CLEAN!$H161+CLEAN!$I161 -> 0 | K161: 41422 | M161: 76 | N161: =SUM(CLEAN!$AB161:$AE161) -> 12 | O161: =CLEAN!$U161+CLEAN!$V161+CLEAN!$W161+CLEAN!$X161+CLEAN!$Y161+CLEAN!$Z161 -> 1187 | P161: =IF(CLEAN!$M161<=32,3,IF(CLEAN!$M161<=65,2,1)) -> 1 | Q161: =IF(Table_Market[[#This Row],[F_TOTAL_achat]]<=14,1,IF(Table_Market[[#This Row],[F_TOTAL_achat]]<=21,2,3)) -> 1 | R161: =IF(Table_Market[[#This Row],[M_TOTAL_dépensé]]<=115,1,IF(Table_Market[[#This Row],[M_TOTAL_dépensé]]<=833,2,3)) -> 3 | S161: =Table_Market[[#This Row],[R_SCORE]]&Table_Market[[#This Row],[F_SCORE]]&Table_Market[[#This Row],[M_SCORE]] -> 113 | T161: =IF(Table_Market[[#This Row],[RFM_SCORE]]="333","Clients élites",IF(LEFT(Table_Market[[#This Row],[RFM_SCORE]],1)="3","Récents prometteurs",IF(LEFT(Table_Market[[#This Row],[RFM_SCORE]],1)="1","Inactifs",IF(AND(LEFT(Table_Market[[#This Row],[RFM_SCORE]],1)>="2",MID(Table_Market[[#This Row],[RFM_SCORE]],2,1)>="2",RIGHT(Table_Market[[#This Row],[RFM_SCORE]],1)>="2"),"Fidèles rentables","Occasionnels")))) -> Inactifs | U161: 267 | V161: 98 | W161: 606 | X161: 48 | Y161: 70 | Z161: 98 | AA161: 1 | AB161: 3 | AC161: 2 | AD161: 6 | AE161: 1 | AF161: 0 | AG161: 0 | AH161: 1 | AI161: 0 | AJ161: 0 | AK161: 0 | AL161: 3 | AM161: 11 | AN161: 1
A162: 10446 | B162: 1957 | C162: =YEAR(TODAY())-CLEAN!$B162 -> 68 | D162: 60 ans et + | E162: Doctorat | F162: Marié | G162: 82017 | H162: 0 | I162: 0 | J162: =CLEAN!$H162+CLEAN!$I162 -> 0 | K162: 41220 | L162: =YEAR(TODAY())-YEAR(CLEAN!$K162) -> 13 | M162: 58 | N162: =SUM(CLEAN!$AB162:$AE162) -> 18 | O162: =CLEAN!$U162+CLEAN!$V162+CLEAN!$W162+CLEAN!$X162+CLEAN!$Y162+CLEAN!$Z162 -> 729 | P162: =IF(CLEAN!$M162<=32,3,IF(CLEAN!$M162<=65,2,1)) -> 2 | Q162: =IF(Table_Market[[#This Row],[F_TOTAL_achat]]<=14,1,IF(Table_Market[[#This Row],[F_TOTAL_achat]]<=21,2,3)) -> 2 | R162: =IF(Table_Market[[#This Row],[M_TOTAL_dépensé]]<=115,1,IF(Table_Market[[#This Row],[M_TOTAL_dépensé]]<=833,2,3)) -> 2 | S162: =Table_Market[[#This Row],[R_SCORE]]&Table_Market[[#This Row],[F_SCORE]]&Table_Market[[#This Row],[M_SCORE]] -> 222 | T162: =IF(Table_Market[[#This Row],[RFM_SCORE]]="333","Clients élites",IF(LEFT(Table_Market[[#This Row],[RFM_SCORE]],1)="3","Récents prometteurs",IF(LEFT(Table_Market[[#This Row],[RFM_SCORE]],1)="1","Inactifs",IF(AND(LEFT(Table_Market[[#This Row],[RFM_SCORE]],1)>="2",MID(Table_Market[[#This Row],[RFM_SCORE]],2,1)>="2",RIGHT(Table_Market[[#This Row],[RFM_SCORE]],1)>="2"),"Fidèles rentables","Occasionnels")))) -> Fidèles rentables | U162: 184 | V162: 23 | W162: 446 | X162: 30 | Y162: 23 | Z162: 23 | AA162: 1 | AB162: 5 | AC162: 4 | AD162: 7 | AE162: 2 | AF162: 0 | AG162: 1 | AH162: 1 | AI162: 1 | AJ162: 0 | AK162: 0 | AL162: 3 | AM162: 11 | AN162: 1
A163: 8395 | B163: 1961 | C163: =YEAR(TODAY())-CLEAN!$B163 -> 64 | D163: 60 ans et + | E163: BAC+3 | F163: Célibataire | G163: 82014 | H163: 0 | I163: 0 | J163: =CLEAN!$H163+CLEAN!$I163 -> 0 | K163: 41141 | L163: =YEAR(TODAY())-YEAR(CLEAN!$K163) -> 13 | M163: 48 | N163: =SUM(CLEAN!$AB163:$AE163) -> 27 | O163: =CLEAN!$U163+CLEAN!$V163+CLEAN!$W163+CLEAN!$X163+CLEAN!$Y163+CLEAN!$Z163 -> 1511 | P163: =IF(CLEAN!$M163<=32,3,IF(CLEAN!$M163<=65,2,1)) -> 2 | Q163: =IF(Table_Market[[#This Row],[F_TOTAL_achat]]<=14,1,IF(Table_Market[[#This Row],[F_TOTAL_achat]]<=21,2,3)) -> 3 | R163: =IF(Table_Market[[#This Row],[M_TOTAL_dépensé]]<=115,1,IF(Table_Market[[#This Row],[M_TOTAL_dépensé]]<=833,2,3)) -> 3 | S163: =Table_Market[[#This Row],[R_SCORE]]&Table_Market[[#This Row],[F_SCORE]]&Table_Market[[#This Row],[M_SCORE]] -> 233 | T163: =IF(Table_Market[[#This Row],[RFM_SCORE]]="333","Clients élites",IF(LEFT(Table_Market[[#This Row],[RFM_SCORE]],1)="3","Récents prometteurs",IF(LEFT(Table_Market[[#This Row],[RFM_SCORE]],1)="1","Inactifs",IF(AND(LEFT(Table_Market[[#This Row],[RFM_SCORE]],1)>="2",MID(Table_Market[[#This Row],[RFM_SCORE]],2,1)>="2",RIGHT(Table_Market[[#This Row],[RFM_SCORE]],1)>="2"),"Fidèles rentables","Occasionnels")))) -> Fidèles rentables | U163: 980 | V163: 37 | W163: 265 | X163: 35 | Y163: 163 | Z163: 31 | AA163: 1 | AB163: 3 | AC163: 6 | AD163: 12 | AE163: 6 | AF163: 0 | AG163: 0 | AH163: 0 | AI163: 0 | AJ163: 0 | AK163: 0 | AL163: 3 | AM163: 11 | AN163: 1
A164: 5341 | B164: 1962 | C164: =YEAR(TODAY())-CLEAN!$B164 -> 63 | D164: 60 ans et + | E164: BAC+5 | F164: Divorcé | G164: 81975 | H164: 0 | I164: 1 | J164: =CLEAN!$H164+CLEAN!$I164 -> 1 | K164: 41279 | L164: =YEAR(TODAY())-YEAR(CLEAN!$K164) -> 12 | M164: 2 | N164: =SUM(CLEAN!$AB164:$AE164) -> 20 | O164: =CLEAN!$U164+CLEAN!$V164+CLEAN!$W164+CLEAN!$X164+CLEAN!$Y164+CLEAN!$Z164 -> 1588 | P164: =IF(CLEAN!$M164<=32,3,IF(CLEAN!$M164<=65,2,1)) -> 3 | Q164: =IF(Table_Market[[#This Row],[F_TOTAL_achat]]<=14,1,IF(Table_Market[[#This Row],[F_TOTAL_achat]]<=21,2,3)) -> 2 | R164: =IF(Table_Market[[#This Row],[M_TOTAL_dépensé]]<=115,1,IF(Table_Market[[#This Row],[M_TOTAL_dépensé]]<=833,2,3)) -> 3 | S164: =Table_Market[[#This Row],[R_SCORE]]&Table_Market[[#This Row],[F_SCORE]]&Table_Market[[#This Row],[M_SCORE]] -> 323 | T164: =IF(Table_Market[[#This Row],[RFM_SCORE]]="333","Clients élites",IF(LEFT(Table_Market[[#This Row],[RFM_SCORE]],1)="3","Récents prometteurs",IF(LEFT(Table_Market[[#This Row],[RFM_SCORE]],1)="1","Inactifs",IF(AND(LEFT(Table_Market[[#This Row],[RFM_SCORE]],1)>="2",MID(Table_Market[[#This Row],[RFM_SCORE]],2,1)>="2",RIGHT(Table_Market[[#This Row],[RFM_SCORE]],1)>="2"),"Fidèles rentables","Occasionnels")))) -> Récents prometteurs | U164: 983 | V164: 76 | W164: 184 | X164: 180 | Y164: 138 | Z164: 27 | AA164: 1 | AB164: 6 | AC164: 3 | AD164: 4 | AE164: 7 | AF164: 0 | AG164: 0 | AH164: 1 | AI164: 0 | AJ164: 0 | AK164: 0 | AL164: 3 | AM164: 11 | AN164: 0
A165: 1103 | B165: 1976 | C165: =YEAR(TODAY())-CLEAN!$B165 -> 49 | D165: 45-59 ans | E165: BAC+5 | F165: Marié | G165: 81929 | H165: 1 | I165: 0 | J165: =CLEAN!$H165+CLEAN!$I165 -> 1 | K165: 41181 | L165: =YEAR(TODAY())-YEAR(CLEAN!$K165) -> 13 | M165: 60 | N165: =SUM(CLEAN!$AB165:$AE165) -> 24 | O165: =CLEAN!$U165+CLEAN!$V165+CLEAN!$W165+CLEAN!$X165+CLEAN!$Y165+CLEAN!$Z165 -> 2053 | P165: =IF(CLEAN!$M165<=32,3,IF(CLEAN!$M165<=65,2,1)) -> 2 | Q165: =IF(Table_Market[[#This Row],[F_TOTAL_achat]]<=14,1,IF(Table_Market[[#This Row],[F_TOTAL_achat]]<=21,2,3)) -> 3 | R165: =IF(Table_Market[[#This Row],[M_TOTAL_dépensé]]<=115,1,IF(Table_Market[[#This Row],[M_TOTAL_dépensé]]<=833,2,3)) -> 3 | S165: =Table_Market[[#This Row],[R_SCORE]]&Table_Market[[#This Row],[F_SCORE]]&Table_Market[[#This Row],[M_SCORE]] -> 233 | T165: =IF(Table_Market[[#This Row],[RFM_SCORE]]="333","Clients élites",IF(LEFT(Table_Market[[#This Row],[RFM_SCORE]],1)="3","Récents prometteurs",IF(LEFT(Table_Market[[#This Row],[RFM_SCORE]],1)="1","Inactifs",IF(AND(LEFT(Table_Market[[#This Row],[RFM_SCORE]],1)>="2",MID(Table_Market[[#This Row],[RFM_SCORE]],2,1)>="2",RIGHT(Table_Market[[#This Row],[RFM_SCORE]],1)>="2"),"Fidèles rentables","Occasionnels")))) -> Fidèles rentables | U165: 1486 | V165: 55 | W165: 278 | X165: 49 | Y165: 0 | Z165: 185 | AA165: 2 | AB165: 4 | AC165: 4 | AD165: 10 | AE165: 6 | AF165: 1 | AG165: 0 | AH165: 1 | AI165: 0 | AJ165: 0 | AK165: 0 | AL165: 3 | AM165: 11 | AN165: 1
A166: 1650 | B166: 1960 | C166: =YEAR(TODAY())-CLEAN!$B166 -> 65 | D166: 60 ans et + | E166: BAC+5 | F166: Marié | G166: 81843 | H166: 0 | I166: 0 | J166: =CLEAN!$H166+CLEAN!$I166 -> 0 | K166: 41386 | L166: =YEAR(TODAY())-YEAR(CLEAN!$K166) -> 12 | M166: 13 | N166: =SUM(CLEAN!$AB166:$AE166) -> 29 | O166: =CLEAN!$U166+CLEAN!$V166+CLEAN!$W166+CLEAN!$X166+CLEAN!$Y166+CLEAN!$Z166 -> 1643 | P166: =IF(CLEAN!$M166<=32,3,IF(CLEAN!$M166<=65,2,1)) -> 3 | Q166: =IF(Table_Market[[#This Row],[F_TOTAL_achat]]<=14,1,IF(Table_Market[[#This Row],[F_TOTAL_achat]]<=21,2,3)) -> 3 | R166: =IF(Table_Market[[#This Row],[M_TOTAL_dépensé]]<=115,1,IF(Table_Market[[#This Row],[M_TOTAL_dépensé]]<=833,2,3)) -> 3 | S166: =Table_Market[[#This Row],[R_SCORE]]&Table_Market[[#This Row],[F_SCORE]]&Table_Market[[#This Row],[M_SCORE]] -> 333 | T166: =IF(Table_Market[[#This Row],[RFM_SCORE]]="333","Clients élites",IF(LEFT(Table_Market[[#This Row],[RFM_SCORE]],1)="3","Récents prometteurs",IF(LEFT(Table_Market[[#This Row],[RFM_SCORE]],1)="1","Inactifs",IF(AND(LEFT(Table_Market[[#This Row],[RFM_SCORE]],1)>="2",MID(Table_Market[[#This Row],[RFM_SCORE]],2,1)>="2",RIGHT(Table_Market[[#This Row],[RFM_SCORE]],1)>="2"),"Fidèles rentables","Occasionnels")))) -> Clients élites | U166: 779 | V166: 86 | W166: 537 | X166: 34 | Y166: 69 | Z166: 138 | AA166: 1 | AB166: 5 | AC166: 9 | AD166: 12 | AE166: 3 | AF166: 0 | AG166: 0 | AH166: 0 | AI166: 0 | AJ166: 0 | AK166: 0 | AL166: 3 | AM166: 11 | AN166: 0
A167: 9292 | B167: 1952 | C167: =YEAR(TODAY())-CLEAN!$B167 -> 73 | D167: 60 ans et + | E167: BAC+3 | F167: Marié | G167: 81795 | H167: 0 | I167: 0 | J167: =CLEAN!$H167+CLEAN!$I167 -> 0 | K167: 41208 | L167: =YEAR(TODAY())-YEAR(CLEAN!$K167) -> 13 | M167: 74 | N167: =SUM(CLEAN!$AB167:$AE167) -> 24 | O167: =CLEAN!$U167+CLEAN!$V167+CLEAN!$W167+CLEAN!$X167+CLEAN!$Y167+CLEAN!$Z167 -> 1382 | P167: =IF(CLEAN!$M167<=32,3,IF(CLEAN!$M167<=65,2,1)) -> 1 | Q167: =IF(Table_Market[[#This Row],[F_TOTAL_achat]]<=14,1,IF(Table_Market[[#This Row],[F_TOTAL_achat]]<=21,2,3)) -> 3 | R167: =IF(Table_Market[[#This Row],[M_TOTAL_dépensé]]<=115,1,IF(Table_Market[[#This Row],[M_TOTAL_dépensé]]<=833,2,3)) -> 3 | S167: =Table_Market[[#This Row],[R_SCORE]]&Table_Market[[#This Row],[F_SCORE]]&Table_Market[[#This Row],[M_SCORE]] -> 133 | T167: =IF(Table_Market[[#This Row],[RFM_SCORE]]="333","Clients élites",IF(LEFT(Table_Market[[#This Row],[RFM_SCORE]],1)="3","Récents prometteurs",IF(LEFT(Table_Market[[#This Row],[RFM_SCORE]],1)="1","Inactifs",IF(AND(LEFT(Table_Market[[#This Row],[RFM_SCORE]],1)>="2",MID(Table_Market[[#This Row],[RFM_SCORE]],2,1)>="2",RIGHT(Table_Market[[#This Row],[RFM_SCORE]],1)>="2"),"Fidèles rentables","Occasionnels")))) -> Inactifs | U167: 324 | V167: 132 | W167: 693 | X167: 27 | Y167: 118 | Z167: 88 | AA167: 1 | AB167: 4 | AC167: 11 | AD167: 7 | AE167: 2 | AF167: 0 | AG167: 0 | AH167: 0 | AI167: 0 | AJ167: 0 | AK167: 0 | AL167: 3 | AM167: 11 | AN167: 0
A168: 3179 | B168: 1980 | C168: =YEAR(TODAY())-CLEAN!$B168 -> 45 | D168: 45-59 ans | E168: BAC+3 | F168: Célibataire | G168: 81741 | H168: 0 | I168: 0 | J168: =CLEAN!$H168+CLEAN!$I168 -> 0 | K168: 41441 | L168: =YEAR(TODAY())-YEAR(CLEAN!$K168) -> 12 | M168: 75 | N168: =SUM(CLEAN!$AB168:$AE168) -> 21 | O168: =CLEAN!$U168+CLEAN!$V168+CLEAN!$W168+CLEAN!$X168+CLEAN!$Y168+CLEAN!$Z168 -> 1572 | P168: =IF(CLEAN!$M168<=32,3,IF(CLEAN!$M168<=65,2,1)) -> 1 | Q168: =IF(Table_Market[[#This Row],[F_TOTAL_achat]]<=14,1,IF(Table_Market[[#This Row],[F_TOTAL_achat]]<=21,2,3)) -> 2 | R168: =IF(Table_Market[[#This Row],[M_TOTAL_dépensé]]<=115,1,IF(Table_Market[[#This Row],[M_TOTAL_dépensé]]<=833,2,3)) -> 3 | S168: =Table_Market[[#This Row],[R_SCORE]]&Table_Market[[#This Row],[F_SCORE]]&Table_Market[[#This Row],[M_SCORE]] -> 123 | T168: =IF(Table_Market[[#This Row],[RFM_SCORE]]="333","Clients élites",IF(LEFT(Table_Market[[#This Row],[RFM_SCORE]],1)="3","Récents prometteurs",IF(LEFT(Table_Market[[#This Row],[RFM_SCORE]],1)="1","Inactifs",IF(AND(LEFT(Table_Market[[#This Row],[RFM_SCORE]],1)>="2",MID(Table_Market[[#This Row],[RFM_SCORE]],2,1)>="2",RIGHT(Table_Market[[#This Row],[RFM_SCORE]],1)>="2"),"Fidèles rentables","Occasionnels")))) -> Inactifs | U168: 249 | V168: 153 | W168: 940 | X168: 58 | Y168: 134 | Z168: 38 | AA168: 0 | AB168: 6 | AC168: 6 | AD168: 7 | AE168: 2 | AF168: 0 | AG168: 0 | AH168: 0 | AI168: 0 | AJ168: 0 | AK168: 0 | AL168: 3 | AM168: 11 | AN168: 0
A169: 5687 | B169: 1980 | C169: =YEAR(TODAY())-CLEAN!$B169 -> 45 | D169: 45-59 ans | E169: BAC+3 | F169: Divorcé | G169: 81702 | H169: 0 | I169: 0 | J169: =CLEAN!$H169+CLEAN!$I169 -> 0 | K169: 41175 | L169: =YEAR(TODAY())-YEAR(CLEAN!$K169) -> 13 | M169: 98 | N169: =SUM(CLEAN!$AB169:$AE169) -> 29 | O169: =CLEAN!$U169+CLEAN!$V169+CLEAN!$W169+CLEAN!$X169+CLEAN!$Y169+CLEAN!$Z169 -> 1633 | P169: =IF(CLEAN!$M169<=32,3,IF(CLEAN!$M169<=65,2,1)) -> 1 | Q169: =IF(Table_Market[[#This Row],[F_TOTAL_achat]]<=14,1,IF(Table_Market[[#This Row],[F_TOTAL_achat]]<=21,2,3)) -> 3 | R169: =IF(Table_Market[[#This Row],[M_TOTAL_dépensé]]<=115,1,IF(Table_Market[[#This Row],[M_TOTAL_dépensé]]<=833,2,3)) -> 3 | S169: =Table_Market[[#This Row],[R_SCORE]]&Table_Market[[#This Row],[F_SCORE]]&Table_Market[[#This Row],[M_SCORE]] -> 133 | T169: =IF(Table_Market[[#This Row],[RFM_SCORE]]="333","Clients élites",IF(LEFT(Table_Market[[#This Row],[RFM_SCORE]],1)="3","Récents prometteurs",IF(LEFT(Table_Market[[#This Row],[RFM_SCORE]],1)="1","Inactifs",IF(AND(LEFT(Table_Market[[#This Row],[RFM_SCORE]],1)>="2",MID(Table_Market[[#This Row],[RFM_SCORE]],2,1)>="2",RIGHT(Table_Market[[#This Row],[RFM_SCORE]],1)>="2"),"Fidèles rentables","Occasionnels")))) -> Inactifs | U169: 563 | V169: 50 | W169: 774 | X169: 28 | Y169: 31 | Z169: 187 | AA169: 1 | AB169: 7 | AC169: 7 | AD169: 12 | AE169: 3 | AF169: 0 | AG169: 0 | AH169: 0 | AI169: 0 | AJ169: 0 | AK169: 0 | AL169: 3 | AM169: 11 | AN169: 0
A170: 9504 | B170: 1949 | C170: =YEAR(TODAY())-CLEAN!$B170 -> 76 | D170: 60 ans et + | E170: BAC+5 | F170: Marié | G170: 81698 | H170: 0 | I170: 0 | J170: =CLEAN!$H170+CLEAN!$I170 -> 0 | K170: 41584 | L170: =YEAR(TODAY())-YEAR(CLEAN!$K170) -> 12 | M170: 4 | N170: =SUM(CLEAN!$AB170:$AE170) -> 25 | O170: =CLEAN!$U170+CLEAN!$V170+CLEAN!$W170+CLEAN!$X170+CLEAN!$Y170+CLEAN!$Z170 -> 1008 | P170: =IF(CLEAN!$M170<=32,3,IF(CLEAN!$M170<=65,2,1)) -> 3 | Q170: =IF(Table_Market[[#This Row],[F_TOTAL_achat]]<=14,1,IF(Table_Market[[#This Row],[F_TOTAL_achat]]<=21,2,3)) -> 3 | R170: =IF(Table_Market[[#This Row],[M_TOTAL_dépensé]]<=115,1,IF(Table_Market[[#This Row],[M_TOTAL_dépensé]]<=833,2,3)) -> 3 | S170: =Table_Market[[#This Row],[R_SCORE]]&Table_Market[[#This Row],[F_SCORE]]&Table_Market[[#This Row],[M_SCORE]] -> 333 | T170: =IF(Table_Market[[#This Row],[RFM_SCORE]]="333","Clients élites",IF(LEFT(Table_Market[[#This Row],[RFM_SCORE]],1)="3","Récents prometteurs",IF(LEFT(Table_Market[[#This Row],[RFM_SCORE]],1)="1","Inactifs",IF(AND(LEFT(Table_Market[[#This Row],[RFM_SCORE]],1)>="2",MID(Table_Market[[#This Row],[RFM_SCORE]],2,1)>="2",RIGHT(Table_Market[[#This Row],[RFM_SCORE]],1)>="2"),"Fidèles rentables","Occasionnels")))) -> Clients élites | U170: 179 | V170: 28 | W170: 520 | X170: 111 | Y170: 123 | Z170: 47 | AA170: 1 | AB170: 3 | AC170: 8 | AD170: 13 | AE170: 1 | AF170: 0 | AG170: 0 | AH170: 0 | AI170: 0 | AJ170: 0 | AK170: 0 | AL170: 3 | AM170: 11 | AN170: 1
A171: 1524 | B171: 1983 | C171: =YEAR(TODAY())-CLEAN!$B171 -> 42 | D171: 30-44 ans | E171: BAC+5 | F171: Célibataire | G171: 81698 | H171: 0 | I171: 0 | J171: =CLEAN!$H171+CLEAN!$I171 -> 0 | K171: 41334 | L171: =YEAR(TODAY())-YEAR(CLEAN!$K171) -> 12 | M171: 1 | N171: =SUM(CLEAN!$AB171:$AE171) -> 20 | O171: =CLEAN!$U171+CLEAN!$V171+CLEAN!$W171+CLEAN!$X171+CLEAN!$Y171+CLEAN!$Z171 -> 1104 | P171: =IF(CLEAN!$M171<=32,3,IF(CLEAN!$M171<=65,2,1)) -> 3 | Q171: =IF(Table_Market[[#This Row],[F_TOTAL_achat]]<=14,1,IF(Table_Market[[#This Row],[F_TOTAL_achat]]<=21,2,3)) -> 2 | R171: =IF(Table_Market[[#This Row],[M_TOTAL_dépensé]]<=115,1,IF(Table_Market[[#This Row],[M_TOTAL_dépensé]]<=833,2,3)) -> 3 | S171: =Table_Market[[#This Row],[R_SCORE]]&Table_Market[[#This Row],[F_SCORE]]&Table_Market[[#This Row],[M_SCORE]] -> 323 | T171: =IF(Table_Market[[#This Row],[RFM_SCORE]]="333","Clients élites",IF(LEFT(Table_Market[[#This Row],[RFM_SCORE]],1)="3","Récents prometteurs",IF(LEFT(Table_Market[[#This Row],[RFM_SCORE]],1)="1","Inactifs",IF(AND(LEFT(Table_Market[[#This Row],[RFM_SCORE]],1)>="2",MID(Table_Market[[#This Row],[RFM_SCORE]],2,1)>="2",RIGHT(Table_Market[[#This Row],[RFM_SCORE]],1)>="2"),"Fidèles rentables","Occasionnels")))) -> Récents prometteurs | U171: 709 | V171: 45 | W171: 115 | X171: 30 | Y171: 160 | Z171: 45 | AA171: 1 | AB171: 8 | AC171: 2 | AD171: 5 | AE171: 5 | AF171: 0 | AG171: 0 | AH171: 0 | AI171: 1 | AJ171: 0 | AK171: 0 | AL171: 3 | AM171: 11 | AN171: 1
A172: 2410 | B172: 1969 | C172: =YEAR(TODAY())-CLEAN!$B172 -> 56 | D172: 45-59 ans | E172: BAC+3 | F172: Célibataire | G172: 81657 | H172: 0 | I172: 0 | J172: =CLEAN!$H172+CLEAN!$I172 -> 0 | K172: 41661 | L172: =YEAR(TODAY())-YEAR(CLEAN!$K172) -> 11 | M172: 69 | N172: =SUM(CLEAN!$AB172:$AE172) -> 16 | O172: =CLEAN!$U172+CLEAN!$V172+CLEAN!$W172+CLEAN!$X172+CLEAN!$Y172+CLEAN!$Z172 -> 1097 | P172: =IF(CLEAN!$M172<=32,3,IF(CLEAN!$M172<=65,2,1)) -> 1 | Q172: =IF(Table_Market[[#This Row],[F_TOTAL_achat]]<=14,1,IF(Table_Market[[#This Row],[F_TOTAL_achat]]<=21,2,3)) -> 2 | R172: =IF(Table_Market[[#This Row],[M_TOTAL_dépensé]]<=115,1,IF(Table_Market[[#This Row],[M_TOTAL_dépensé]]<=833,2,3)) -> 3 | S172: =Table_Market[[#This Row],[R_SCORE]]&Table_Market[[#This Row],[F_SCORE]]&Table_Market[[#This Row],[M_SCORE]] -> 123 | T172: =IF(Table_Market[[#This Row],[RFM_SCORE]]="333","Clients élites",IF(LEFT(Table_Market[[#This Row],[RFM_SCORE]],1)="3","Récents prometteurs",IF(LEFT(Table_Market[[#This Row],[RFM_SCORE]],1)="1","Inactifs",IF(AND(LEFT(Table_Market[[#This Row],[RFM_SCORE]],1)>="2",MID(Table_Market[[#This Row],[RFM_SCORE]],2,1)>="2",RIGHT(Table_Market[[#This Row],[RFM_SCORE]],1)>="2"),"Fidèles rentables","Occasionnels")))) -> Inactifs | U172: 364 | V172: 40 | W172: 425 | X172: 158 | Y172: 60 | Z172: 50 | AA172: 1 | AB172: 3 | AC172: 4 | AD172: 8 | AE172: 1 | AF172: 0 | AG172: 0 | AH172: 0 | AI172: 0 | AJ172: 0 | AK172: 0 | AL172: 3 | AM172: 11 | AN172: 0
A173: 9298 | B173: 1947 | C173: =YEAR(TODAY())-CLEAN!$B173 -> 78 | D173: 60 ans et + | E173: Doctorat | F173: Conjoint | G173: 81574 | H173: 0 | I173: 0 | J173: =CLEAN!$H173+CLEAN!$I173 -> 0 | K173: 41757 | L173: =YEAR(TODAY())-YEAR(CLEAN!$K173) -> 11 | M173: 89 | N173: =SUM(CLEAN!$AB173:$AE173) -> 18 | O173: =CLEAN!$U173+CLEAN!$V173+CLEAN!$W173+CLEAN!$X173+CLEAN!$Y173+CLEAN!$Z173 -> 1798 | P173: =IF(CLEAN!$M173<=32,3,IF(CLEAN!$M173<=65,2,1)) -> 1 | Q173: =IF(Table_Market[[#This Row],[F_TOTAL_achat]]<=14,1,IF(Table_Market[[#This Row],[F_TOTAL_achat]]<=21,2,3)) -> 2 | R173: =IF(Table_Market[[#This Row],[M_TOTAL_dépensé]]<=115,1,IF(Table_Market[[#This Row],[M_TOTAL_dépensé]]<=833,2,3)) -> 3 | S173: =Table_Market[[#This Row],[R_SCORE]]&Table_Market[[#This Row],[F_SCORE]]&Table_Market[[#This Row],[M_SCORE]] -> 123 | T173: =IF(Table_Market[[#This Row],[RFM_SCORE]]="333","Clients élites",IF(LEFT(Table_Market[[#This Row],[RFM_SCORE]],1)="3","Récents prometteurs",IF(LEFT(Table_Market[[#This Row],[RFM_SCORE]],1)="1","Inactifs",IF(AND(LEFT(Table_Market[[#This Row],[RFM_SCORE]],1)>="2",MID(Table_Market[[#This Row],[RFM_SCORE]],2,1)>="2",RIGHT(Table_Market[[#This Row],[RFM_SCORE]],1)>="2"),"Fidèles rentables","Occasionnels")))) -> Inactifs | U173: 1252 | V173: 0 | W173: 465 | X173: 46 | Y173: 35 | Z173: 0 | AA173: 1 | AB173: 4 | AC173: 5 | AD173: 8 | AE173: 1 | AF173: 0 | AG173: 1 | AH173: 1 | AI173: 0 | AJ173: 0 | AK173: 0 | AL173: 3 | AM173: 11 | AN173: 0
... A198: 3661 | B198: 1995 | C198: =YEAR(TODAY())-CLEAN!$B198 -> 30 | D198: 30-44 ans | E198: BAC+5 | F198: Célibataire | G198: 80617 | H198: 0 | I198: 0 | J198: =CLEAN!$H198+CLEAN!$I198 -> 0 | K198: 41194 | L198: =YEAR(TODAY())-YEAR(CLEAN!$K198) -> 13 | M198: 42 | N198: =SUM(CLEAN!$AB198:$AE198) -> 20 | O198: =CLEAN!$U198+CLEAN!$V198+CLEAN!$W198+CLEAN!$X198+CLEAN!$Y198+CLEAN!$Z198 -> 1435 | P198: =IF(CLEAN!$M198<=32,3,IF(CLEAN!$M198<=65,2,1)) -> 2 | Q198: =IF(Table_Market[[#This Row],[F_TOTAL_achat]]<=14,1,IF(Table_Market[[#This Row],[F_TOTAL_achat]]<=21,2,3)) -> 2 | R198: =IF(Table_Market[[#This Row],[M_TOTAL_dépensé]]<=115,1,IF(Table_Market[[#This Row],[M_TOTAL_dépensé]]<=833,2,3)) -> 3 | S198: =Table_Market[[#This Row],[R_SCORE]]&Table_Market[[#This Row],[F_SCORE]]&Table_Market[[#This Row],[M_SCORE]] -> 223 | T198: =IF(Table_Market[[#This Row],[RFM_SCORE]]="333","Clients élites",IF(LEFT(Table_Market[[#This Row],[RFM_SCORE]],1)="3","Récents prometteurs",IF(LEFT(Table_Market[[#This Row],[RFM_SCORE]],1)="1","Inactifs",IF(AND(LEFT(Table_Market[[#This Row],[RFM_SCORE]],1)>="2",MID(Table_Market[[#This Row],[RFM_SCORE]],2,1)>="2",RIGHT(Table_Market[[#This Row],[RFM_SCORE]],1)>="2"),"Fidèles rentables","Occasionnels")))) -> Fidèles rentables | U198: 594 | V198: 51 | W198: 631 | X198: 72 | Y198: 55 | Z198: 32 | AA198: 1 | AB198: 4 | AC198: 6 | AD198: 8 | AE198: 2 | AF198: 0 | AG198: 0 | AH198: 0 | AI198: 0 | AJ198: 0 | AK198: 0 | AL198: 3 | AM198: 11 | AN198: 0
A199: 4310 | B199: 1944 | C199: =YEAR(TODAY())-CLEAN!$B199 -> 81 | D199: 60 ans et + | E199: BAC+3 | F199: Marié | G199: 80589 | H199: 0 | I199: 0 | J199: =CLEAN!$H199+CLEAN!$I199 -> 0 | K199: 41661 | M199: 25 | N199: =SUM(CLEAN!$AB199:$AE199) -> 21 | O199: =CLEAN!$U199+CLEAN!$V199+CLEAN!$W199+CLEAN!$X199+CLEAN!$Y199+CLEAN!$Z199 -> 1428 | P199: =IF(CLEAN!$M199<=32,3,IF(CLEAN!$M199<=65,2,1)) -> 3 | Q199: =IF(Table_Market[[#This Row],[F_TOTAL_achat]]<=14,1,IF(Table_Market[[#This Row],[F_TOTAL_achat]]<=21,2,3)) -> 2 | R199: =IF(Table_Market[[#This Row],[M_TOTAL_dépensé]]<=115,1,IF(Table_Market[[#This Row],[M_TOTAL_dépensé]]<=833,2,3)) -> 3 | S199: =Table_Market[[#This Row],[R_SCORE]]&Table_Market[[#This Row],[F_SCORE]]&Table_Market[[#This Row],[M_SCORE]] -> 323 | T199: =IF(Table_Market[[#This Row],[RFM_SCORE]]="333","Clients élites",IF(LEFT(Table_Market[[#This Row],[RFM_SCORE]],1)="3","Récents prometteurs",IF(LEFT(Table_Market[[#This Row],[RFM_SCORE]],1)="1","Inactifs",IF(AND(LEFT(Table_Market[[#This Row],[RFM_SCORE]],1)>="2",MID(Table_Market[[#This Row],[RFM_SCORE]],2,1)>="2",RIGHT(Table_Market[[#This Row],[RFM_SCORE]],1)>="2"),"Fidèles rentables","Occasionnels")))) -> Récents prometteurs | U199: 507 | V199: 93 | W199: 520 | X199: 242 | Y199: 40 | Z199: 26 | AA199: 1 | AB199: 5 | AC199: 10 | AD199: 5 | AE199: 1 | AF199: 0 | AG199: 0 | AH199: 0 | AI199: 1 | AJ199: 0 | AK199: 0 | AL199: 3 | AM199: 11 | AN199: 1
A200: 9209 | B200: 1971 | C200: =YEAR(TODAY())-CLEAN!$B200 -> 54 | D200: 45-59 ans | E200: BAC+5 | F200: Conjoint | G200: 80573 | H200: 0 | I200: 0 | J200: =CLEAN!$H200+CLEAN!$I200 -> 0 | K200: 41196 | L200: =YEAR(TODAY())-YEAR(CLEAN!$K200) -> 13 | M200: 85 | N200: =SUM(CLEAN!$AB200:$AE200) -> 25 | O200: =CLEAN!$U200+CLEAN!$V200+CLEAN!$W200+CLEAN!$X200+CLEAN!$Y200+CLEAN!$Z200 -> 1564 | P200: =IF(CLEAN!$M200<=32,3,IF(CLEAN!$M200<=65,2,1)) -> 1 | Q200: =IF(Table_Market[[#This Row],[F_TOTAL_achat]]<=14,1,IF(Table_Market[[#This Row],[F_TOTAL_achat]]<=21,2,3)) -> 3 | R200: =IF(Table_Market[[#This Row],[M_TOTAL_dépensé]]<=115,1,IF(Table_Market[[#This Row],[M_TOTAL_dépensé]]<=833,2,3)) -> 3 | S200: =Table_Market[[#This Row],[R_SCORE]]&Table_Market[[#This Row],[F_SCORE]]&Table_Market[[#This Row],[M_SCORE]] -> 133 | T200: =IF(Table_Market[[#This Row],[RFM_SCORE]]="333","Clients élites",IF(LEFT(Table_Market[[#This Row],[RFM_SCORE]],1)="3","Récents prometteurs",IF(LEFT(Table_Market[[#This Row],[RFM_SCORE]],1)="1","Inactifs",IF(AND(LEFT(Table_Market[[#This Row],[RFM_SCORE]],1)>="2",MID(Table_Market[[#This Row],[RFM_SCORE]],2,1)>="2",RIGHT(Table_Market[[#This Row],[RFM_SCORE]],1)>="2"),"Fidèles rentables","Occasionnels")))) -> Inactifs | U200: 829 | V200: 138 | W200: 430 | X200: 60 | Y200: 92 | Z200: 15 | AA200: 1 | AB200: 4 | AC200: 6 | AD200: 13 | AE200: 2 | AF200: 0 | AG200: 0 | AH200: 0 | AI200: 0 | AJ200: 0 | AK200: 0 | AL200: 3 | AM200: 11 | AN200: 0
A201: 6417 | B201: 1971 | C201: =YEAR(TODAY())-CLEAN!$B201 -> 54 | D201: 45-59 ans | E201: BAC+5 | F201: Conjoint | G201: 80573 | H201: 0 | I201: 0 | J201: =CLEAN!$H201+CLEAN!$I201 -> 0 | K201: 41196 | L201: =YEAR(TODAY())-YEAR(CLEAN!$K201) -> 13 | M201: 85 | N201: =SUM(CLEAN!$AB201:$AE201) -> 25 | O201: =CLEAN!$U201+CLEAN!$V201+CLEAN!$W201+CLEAN!$X201+CLEAN!$Y201+CLEAN!$Z201 -> 1564 | P201: =IF(CLEAN!$M201<=32,3,IF(CLEAN!$M201<=65,2,1)) -> 1 | Q201: =IF(Table_Market[[#This Row],[F_TOTAL_achat]]<=14,1,IF(Table_Market[[#This Row],[F_TOTAL_achat]]<=21,2,3)) -> 3 | R201: =IF(Table_Market[[#This Row],[M_TOTAL_dépensé]]<=115,1,IF(Table_Market[[#This Row],[M_TOTAL_dépensé]]<=833,2,3)) -> 3 | S201: =Table_Market[[#This Row],[R_SCORE]]&Table_Market[[#This Row],[F_SCORE]]&Table_Market[[#This Row],[M_SCORE]] -> 133 | T201: =IF(Table_Market[[#This Row],[RFM_SCORE]]="333","Clients élites",IF(LEFT(Table_Market[[#This Row],[RFM_SCORE]],1)="3","Récents prometteurs",IF(LEFT(Table_Market[[#This Row],[RFM_SCORE]],1)="1","Inactifs",IF(AND(LEFT(Table_Market[[#This Row],[RFM_SCORE]],1)>="2",MID(Table_Market[[#This Row],[RFM_SCORE]],2,1)>="2",RIGHT(Table_Market[[#This Row],[RFM_SCORE]],1)>="2"),"Fidèles rentables","Occasionnels")))) -> Inactifs | U201: 829 | V201: 138 | W201: 430 | X201: 60 | Y201: 92 | Z201: 15 | AA201: 1 | AB201: 4 | AC201: 6 | AD201: 13 | AE201: 2 | AF201: 0 | AG201: 0 | AH201: 0 | AI201: 0 | AJ201: 0 | AK201: 0 | AL201: 3 | AM201: 11 | AN201: 0
A202: 8717 | B202: 1975 | C202: =YEAR(TODAY())-CLEAN!$B202 -> 50 | D202: 45-59 ans | E202: Doctorat | F202: Marié | G202: 80427 | H202: 0 | I202: 1 | J202: =CLEAN!$H202+CLEAN!$I202 -> 1 | K202: 41164 | L202: =YEAR(TODAY())-YEAR(CLEAN!$K202) -> 13 | M202: 56 | N202: =SUM(CLEAN!$AB202:$AE202) -> 32 | O202: =CLEAN!$U202+CLEAN!$V202+CLEAN!$W202+CLEAN!$X202+CLEAN!$Y202+CLEAN!$Z202 -> 1835 | P202: =IF(CLEAN!$M202<=32,3,IF(CLEAN!$M202<=65,2,1)) -> 2 | Q202: =IF(Table_Market[[#This Row],[F_TOTAL_achat]]<=14,1,IF(Table_Market[[#This Row],[F_TOTAL_achat]]<=21,2,3)) -> 3 | R202: =IF(Table_Market[[#This Row],[M_TOTAL_dépensé]]<=115,1,IF(Table_Market[[#This Row],[M_TOTAL_dépensé]]<=833,2,3)) -> 3 | S202: =Table_Market[[#This Row],[R_SCORE]]&Table_Market[[#This Row],[F_SCORE]]&Table_Market[[#This Row],[M_SCORE]] -> 233 | T202: =IF(Table_Market[[#This Row],[RFM_SCORE]]="333","Clients élites",IF(LEFT(Table_Market[[#This Row],[RFM_SCORE]],1)="3","Récents prometteurs",IF(LEFT(Table_Market[[#This Row],[RFM_SCORE]],1)="1","Inactifs",IF(AND(LEFT(Table_Market[[#This Row],[RFM_SCORE]],1)>="2",MID(Table_Market[[#This Row],[RFM_SCORE]],2,1)>="2",RIGHT(Table_Market[[#This Row],[RFM_SCORE]],1)>="2"),"Fidèles rentables","Occasionnels")))) -> Fidèles rentables | U202: 1149 | V202: 71 | W202: 449 | X202: 69 | Y202: 71 | Z202: 26 | AA202: 1 | AB202: 11 | AC202: 8 | AD202: 8 | AE202: 5 | AF202: 0 | AG202: 0 | AH202: 0 | AI202: 0 | AJ202: 0 | AK202: 0 | AL202: 3 | AM202: 11 | AN202: 0
A203: 7396 | B203: 1966 | C203: =YEAR(TODAY())-CLEAN!$B203 -> 59 | D203: 45-59 ans | E203: BAC+3 | F203: Marié | G203: 80398 | H203: 0 | I203: 0 | J203: =CLEAN!$H203+CLEAN!$I203 -> 0 | K203: 41223 | L203: =YEAR(TODAY())-YEAR(CLEAN!$K203) -> 13 | M203: 92 | N203: =SUM(CLEAN!$AB203:$AE203) -> 28 | O203: =CLEAN!$U203+CLEAN!$V203+CLEAN!$W203+CLEAN!$X203+CLEAN!$Y203+CLEAN!$Z203 -> 1597 | P203: =IF(CLEAN!$M203<=32,3,IF(CLEAN!$M203<=65,2,1)) -> 1 | Q203: =IF(Table_Market[[#This Row],[F_TOTAL_achat]]<=14,1,IF(Table_Market[[#This Row],[F_TOTAL_achat]]<=21,2,3)) -> 3 | R203: =IF(Table_Market[[#This Row],[M_TOTAL_dépensé]]<=115,1,IF(Table_Market[[#This Row],[M_TOTAL_dépensé]]<=833,2,3)) -> 3 | S203: =Table_Market[[#This Row],[R_SCORE]]&Table_Market[[#This Row],[F_SCORE]]&Table_Market[[#This Row],[M_SCORE]] -> 133 | T203: =IF(Table_Market[[#This Row],[RFM_SCORE]]="333","Clients élites",IF(LEFT(Table_Market[[#This Row],[RFM_SCORE]],1)="3","Récents prometteurs",IF(LEFT(Table_Market[[#This Row],[RFM_SCORE]],1)="1","Inactifs",IF(AND(LEFT(Table_Market[[#This Row],[RFM_SCORE]],1)>="2",MID(Table_Market[[#This Row],[RFM_SCORE]],2,1)>="2",RIGHT(Table_Market[[#This Row],[RFM_SCORE]],1)>="2"),"Fidèles rentables","Occasionnels")))) -> Inactifs | U203: 342 | V203: 51 | W203: 936 | X203: 207 | Y203: 35 | Z203: 26 | AA203: 1 | AB203: 5 | AC203: 8 | AD203: 12 | AE203: 3 | AF203: 0 | AG203: 0 | AH203: 1 | AI203: 0 | AJ203: 0 | AK203: 0 | AL203: 3 | AM203: 11 | AN203: 0
A204: 6086 | B204: 1955 | C204: =YEAR(TODAY())-CLEAN!$B204 -> 70 | D204: 60 ans et + | E204: BAC+3 | F204: Marié | G204: 80395 | H204: 0 | I204: 0 | J204: =CLEAN!$H204+CLEAN!$I204 -> 0 | K204: 41601 | L204: =YEAR(TODAY())-YEAR(CLEAN!$K204) -> 12 | M204: 62 | N204: =SUM(CLEAN!$AB204:$AE204) -> 25 | O204: =CLEAN!$U204+CLEAN!$V204+CLEAN!$W204+CLEAN!$X204+CLEAN!$Y204+CLEAN!$Z204 -> 1380 | P204: =IF(CLEAN!$M204<=32,3,IF(CLEAN!$M204<=65,2,1)) -> 2 | Q204: =IF(Table_Market[[#This Row],[F_TOTAL_achat]]<=14,1,IF(Table_Market[[#This Row],[F_TOTAL_achat]]<=21,2,3)) -> 3 | R204: =IF(Table_Market[[#This Row],[M_TOTAL_dépensé]]<=115,1,IF(Table_Market[[#This Row],[M_TOTAL_dépensé]]<=833,2,3)) -> 3 | S204: =Table_Market[[#This Row],[R_SCORE]]&Table_Market[[#This Row],[F_SCORE]]&Table_Market[[#This Row],[M_SCORE]] -> 233 | T204: =IF(Table_Market[[#This Row],[RFM_SCORE]]="333","Clients élites",IF(LEFT(Table_Market[[#This Row],[RFM_SCORE]],1)="3","Récents prometteurs",IF(LEFT(Table_Market[[#This Row],[RFM_SCORE]],1)="1","Inactifs",IF(AND(LEFT(Table_Market[[#This Row],[RFM_SCORE]],1)>="2",MID(Table_Market[[#This Row],[RFM_SCORE]],2,1)>="2",RIGHT(Table_Market[[#This Row],[RFM_SCORE]],1)>="2"),"Fidèles rentables","Occasionnels")))) -> Fidèles rentables | U204: 445 | V204: 25 | W204: 706 | X204: 80 | Y204: 76 | Z204: 48 | AA204: 1 | AB204: 6 | AC204: 5 | AD204: 12 | AE204: 2 | AF204: 0 | AG204: 0 | AH204: 0 | AI204: 1 | AJ204: 0 | AK204: 0 | AL204: 3 | AM204: 11 | AN204: 0
A205: 737 | B205: 1949 | C205: =YEAR(TODAY())-CLEAN!$B205 -> 76 | D205: 60 ans et + | E205: Doctorat | F205: Marié | G205: 80360 | H205: 0 | I205: 0 | J205: =CLEAN!$H205+CLEAN!$I205 -> 0 | K205: 41336 | L205: =YEAR(TODAY())-YEAR(CLEAN!$K205) -> 12 | M205: 56 | N205: =SUM(CLEAN!$AB205:$AE205) -> 15 | O205: =CLEAN!$U205+CLEAN!$V205+CLEAN!$W205+CLEAN!$X205+CLEAN!$Y205+CLEAN!$Z205 -> 2231 | P205: =IF(CLEAN!$M205<=32,3,IF(CLEAN!$M205<=65,2,1)) -> 2 | Q205: =IF(Table_Market[[#This Row],[F_TOTAL_achat]]<=14,1,IF(Table_Market[[#This Row],[F_TOTAL_achat]]<=21,2,3)) -> 2 | R205: =IF(Table_Market[[#This Row],[M_TOTAL_dépensé]]<=115,1,IF(Table_Market[[#This Row],[M_TOTAL_dépensé]]<=833,2,3)) -> 3 | S205: =Table_Market[[#This Row],[R_SCORE]]&Table_Market[[#This Row],[F_SCORE]]&Table_Market[[#This Row],[M_SCORE]] -> 223 | T205: =IF(Table_Market[[#This Row],[RFM_SCORE]]="333","Clients élites",IF(LEFT(Table_Market[[#This Row],[RFM_SCORE]],1)="3","Récents prometteurs",IF(LEFT(Table_Market[[#This Row],[RFM_SCORE]],1)="1","Inactifs",IF(AND(LEFT(Table_Market[[#This Row],[RFM_SCORE]],1)>="2",MID(Table_Market[[#This Row],[RFM_SCORE]],2,1)>="2",RIGHT(Table_Market[[#This Row],[RFM_SCORE]],1)>="2"),"Fidèles rentables","Occasionnels")))) -> Fidèles rentables | U205: 1493 | V205: 86 | W205: 454 | X205: 112 | Y205: 43 | Z205: 43 | AA205: 2 | AB205: 4 | AC205: 4 | AD205: 5 | AE205: 2 | AF205: 0 | AG205: 1 | AH205: 1 | AI205: 1 | AJ205: 0 | AK205: 0 | AL205: 3 | AM205: 11 | AN205: 0
A206: 7849 | B206: 1970 | C206: =YEAR(TODAY())-CLEAN!$B206 -> 55 | D206: 45-59 ans | E206: Doctorat | F206: Marié | G206: 80336 | H206: 0 | I206: 0 | J206: =CLEAN!$H206+CLEAN!$I206 -> 0 | K206: 41526 | L206: =YEAR(TODAY())-YEAR(CLEAN!$K206) -> 12 | M206: 12 | N206: =SUM(CLEAN!$AB206:$AE206) -> 25 | O206: =CLEAN!$U206+CLEAN!$V206+CLEAN!$W206+CLEAN!$X206+CLEAN!$Y206+CLEAN!$Z206 -> 1052 | P206: =IF(CLEAN!$M206<=32,3,IF(CLEAN!$M206<=65,2,1)) -> 3 | Q206: =IF(Table_Market[[#This Row],[F_TOTAL_achat]]<=14,1,IF(Table_Market[[#This Row],[F_TOTAL_achat]]<=21,2,3)) -> 3 | R206: =IF(Table_Market[[#This Row],[M_TOTAL_dépensé]]<=115,1,IF(Table_Market[[#This Row],[M_TOTAL_dépensé]]<=833,2,3)) -> 3 | S206: =Table_Market[[#This Row],[R_SCORE]]&Table_Market[[#This Row],[F_SCORE]]&Table_Market[[#This Row],[M_SCORE]] -> 333 | T206: =IF(Table_Market[[#This Row],[RFM_SCORE]]="333","Clients élites",IF(LEFT(Table_Market[[#This Row],[RFM_SCORE]],1)="3","Récents prometteurs",IF(LEFT(Table_Market[[#This Row],[RFM_SCORE]],1)="1","Inactifs",IF(AND(LEFT(Table_Market[[#This Row],[RFM_SCORE]],1)>="2",MID(Table_Market[[#This Row],[RFM_SCORE]],2,1)>="2",RIGHT(Table_Market[[#This Row],[RFM_SCORE]],1)>="2"),"Fidèles rentables","Occasionnels")))) -> Clients élites | U206: 209 | V206: 19 | W206: 456 | X206: 160 | Y206: 142 | Z206: 66 | AA206: 1 | AB206: 2 | AC206: 9 | AD206: 13 | AE206: 1 | AF206: 0 | AG206: 0 | AH206: 0 | AI206: 0 | AJ206: 0 | AK206: 0 | AL206: 3 | AM206: 11 | AN206: 0
A207: 2730 | B207: 1955 | C207: =YEAR(TODAY())-CLEAN!$B207 -> 70 | D207: 60 ans et + | E207: BAC+3 | F207: Célibataire | G207: 80317 | H207: 0 | I207: 0 | J207: =CLEAN!$H207+CLEAN!$I207 -> 0 | K207: 41506 | L207: =YEAR(TODAY())-YEAR(CLEAN!$K207) -> 12 | M207: 64 | N207: =SUM(CLEAN!$AB207:$AE207) -> 18 | O207: =CLEAN!$U207+CLEAN!$V207+CLEAN!$W207+CLEAN!$X207+CLEAN!$Y207+CLEAN!$Z207 -> 1231 | P207: =IF(CLEAN!$M207<=32,3,IF(CLEAN!$M207<=65,2,1)) -> 2 | Q207: =IF(Table_Market[[#This Row],[F_TOTAL_achat]]<=14,1,IF(Table_Market[[#This Row],[F_TOTAL_achat]]<=21,2,3)) -> 2 | R207: =IF(Table_Market[[#This Row],[M_TOTAL_dépensé]]<=115,1,IF(Table_Market[[#This Row],[M_TOTAL_dépensé]]<=833,2,3)) -> 3 | S207: =Table_Market[[#This Row],[R_SCORE]]&Table_Market[[#This Row],[F_SCORE]]&Table_Market[[#This Row],[M_SCORE]] -> 223 | T207: =IF(Table_Market[[#This Row],[RFM_SCORE]]="333","Clients élites",IF(LEFT(Table_Market[[#This Row],[RFM_SCORE]],1)="3","Récents prometteurs",IF(LEFT(Table_Market[[#This Row],[RFM_SCORE]],1)="1","Inactifs",IF(AND(LEFT(Table_Market[[#This Row],[RFM_SCORE]],1)>="2",MID(Table_Market[[#This Row],[RFM_SCORE]],2,1)>="2",RIGHT(Table_Market[[#This Row],[RFM_SCORE]],1)>="2"),"Fidèles rentables","Occasionnels")))) -> Fidèles rentables | U207: 536 | V207: 11 | W207: 387 | X207: 149 | Y207: 91 | Z207: 57 | AA207: 1 | AB207: 3 | AC207: 4 | AD207: 10 | AE207: 1 | AF207: 0 | AG207: 0 | AH207: 0 | AI207: 0 | AJ207: 0 | AK207: 0 | AL207: 3 | AM207: 11 | AN207: 0
A208: 3711 | B208: 1944 | C208: =YEAR(TODAY())-CLEAN!$B208 -> 81 | D208: 60 ans et + | E208: BAC+5 | F208: Marié | G208: 80184 | H208: 0 | I208: 0 | J208: =CLEAN!$H208+CLEAN!$I208 -> 0 | K208: 41699 | L208: =YEAR(TODAY())-YEAR(CLEAN!$K208) -> 11 | M208: 19 | N208: =SUM(CLEAN!$AB208:$AE208) -> 22 | O208: =CLEAN!$U208+CLEAN!$V208+CLEAN!$W208+CLEAN!$X208+CLEAN!$Y208+CLEAN!$Z208 -> 1902 | P208: =IF(CLEAN!$M208<=32,3,IF(CLEAN!$M208<=65,2,1)) -> 3 | Q208: =IF(Table_Market[[#This Row],[F_TOTAL_achat]]<=14,1,IF(Table_Market[[#This Row],[F_TOTAL_achat]]<=21,2,3)) -> 3 | R208: =IF(Table_Market[[#This Row],[M_TOTAL_dépensé]]<=115,1,IF(Table_Market[[#This Row],[M_TOTAL_dépensé]]<=833,2,3)) -> 3 | S208: =Table_Market[[#This Row],[R_SCORE]]&Table_Market[[#This Row],[F_SCORE]]&Table_Market[[#This Row],[M_SCORE]] -> 333 | T208: =IF(Table_Market[[#This Row],[RFM_SCORE]]="333","Clients élites",IF(LEFT(Table_Market[[#This Row],[RFM_SCORE]],1)="3","Récents prometteurs",IF(LEFT(Table_Market[[#This Row],[RFM_SCORE]],1)="1","Inactifs",IF(AND(LEFT(Table_Market[[#This Row],[RFM_SCORE]],1)>="2",MID(Table_Market[[#This Row],[RFM_SCORE]],2,1)>="2",RIGHT(Table_Market[[#This Row],[RFM_SCORE]],1)>="2"),"Fidèles rentables","Occasionnels")))) -> Clients élites | U208: 1035 | V208: 134 | W208: 670 | X208: 25 | Y208: 38 | Z208: 0 | AA208: 1 | AB208: 6 | AC208: 3 | AD208: 10 | AE208: 3 | AF208: 0 | AG208: 0 | AH208: 1 | AI208: 1 | AJ208: 0 | AK208: 0 | AL208: 3 | AM208: 11 | AN208: 0
A209: 7428 | B209: 1975 | C209: =YEAR(TODAY())-CLEAN!$B209 -> 50 | D209: 45-59 ans | E209: BAC+3 | F209: Conjoint | G209: 80144 | H209: 0 | I209: 0 | J209: =CLEAN!$H209+CLEAN!$I209 -> 0 | K209: 41547 | L209: =YEAR(TODAY())-YEAR(CLEAN!$K209) -> 12 | M209: 47 | N209: =SUM(CLEAN!$AB209:$AE209) -> 19 | O209: =CLEAN!$U209+CLEAN!$V209+CLEAN!$W209+CLEAN!$X209+CLEAN!$Y209+CLEAN!$Z209 -> 1367 | P209: =IF(CLEAN!$M209<=32,3,IF(CLEAN!$M209<=65,2,1)) -> 2 | Q209: =IF(Table_Market[[#This Row],[F_TOTAL_achat]]<=14,1,IF(Table_Market[[#This Row],[F_TOTAL_achat]]<=21,2,3)) -> 2 | R209: =IF(Table_Market[[#This Row],[M_TOTAL_dépensé]]<=115,1,IF(Table_Market[[#This Row],[M_TOTAL_dépensé]]<=833,2,3)) -> 3 | S209: =Table_Market[[#This Row],[R_SCORE]]&Table_Market[[#This Row],[F_SCORE]]&Table_Market[[#This Row],[M_SCORE]] -> 223 | T209: =IF(Table_Market[[#This Row],[RFM_SCORE]]="333","Clients élites",IF(LEFT(Table_Market[[#This Row],[RFM_SCORE]],1)="3","Récents prometteurs",IF(LEFT(Table_Market[[#This Row],[RFM_SCORE]],1)="1","Inactifs",IF(AND(LEFT(Table_Market[[#This Row],[RFM_SCORE]],1)>="2",MID(Table_Market[[#This Row],[RFM_SCORE]],2,1)>="2",RIGHT(Table_Market[[#This Row],[RFM_SCORE]],1)>="2"),"Fidèles rentables","Occasionnels")))) -> Fidèles rentables | U209: 240 | V209: 132 | W209: 445 | X209: 250 | Y209: 192 | Z209: 108 | AA209: 1 | AB209: 3 | AC209: 7 | AD209: 8 | AE209: 1 | AF209: 0 | AG209: 0 | AH209: 0 | AI209: 0 | AJ209: 0 | AK209: 0 | AL209: 3 | AM209: 11 | AN209: 0
A210: 3690 | B210: 1986 | C210: =YEAR(TODAY())-CLEAN!$B210 -> 39 | D210: 30-44 ans | E210: BAC+5 | F210: Marié | G210: 80141 | H210: 0 | I210: 0 | J210: =CLEAN!$H210+CLEAN!$I210 -> 0 | K210: 41285 | L210: =YEAR(TODAY())-YEAR(CLEAN!$K210) -> 12 | M210: 20 | N210: =SUM(CLEAN!$AB210:$AE210) -> 27 | O210: =CLEAN!$U210+CLEAN!$V210+CLEAN!$W210+CLEAN!$X210+CLEAN!$Y210+CLEAN!$Z210 -> 2091 | P210: =IF(CLEAN!$M210<=32,3,IF(CLEAN!$M210<=65,2,1)) -> 3 | Q210: =IF(Table_Market[[#This Row],[F_TOTAL_achat]]<=14,1,IF(Table_Market[[#This Row],[F_TOTAL_achat]]<=21,2,3)) -> 3 | R210: =IF(Table_Market[[#This Row],[M_TOTAL_dépensé]]<=115,1,IF(Table_Market[[#This Row],[M_TOTAL_dépensé]]<=833,2,3)) -> 3 | S210: =Table_Market[[#This Row],[R_SCORE]]&Table_Market[[#This Row],[F_SCORE]]&Table_Market[[#This Row],[M_SCORE]] -> 333 | T210: =IF(Table_Market[[#This Row],[RFM_SCORE]]="333","Clients élites",IF(LEFT(Table_Market[[#This Row],[RFM_SCORE]],1)="3","Récents prometteurs",IF(LEFT(Table_Market[[#This Row],[RFM_SCORE]],1)="1","Inactifs",IF(AND(LEFT(Table_Market[[#This Row],[RFM_SCORE]],1)>="2",MID(Table_Market[[#This Row],[RFM_SCORE]],2,1)>="2",RIGHT(Table_Market[[#This Row],[RFM_SCORE]],1)>="2"),"Fidèles rentables","Occasionnels")))) -> Clients élites | U210: 1184 | V210: 102 | W210: 673 | X210: 52 | Y210: 40 | Z210: 40 | AA210: 1 | AB210: 7 | AC210: 4 | AD210: 10 | AE210: 6 | AF210: 0 | AG210: 0 | AH210: 1 | AI210: 0 | AJ210: 0 | AK210: 0 | AL210: 3 | AM210: 11 | AN210: 1
A211: 2176 | B211: 1972 | C211: =YEAR(TODAY())-CLEAN!$B211 -> 53 | D211: 45-59 ans | E211: BAC+3 | F211: Marié | G211: 80134 | H211: 1 | I211: 0 | J211: =CLEAN!$H211+CLEAN!$I211 -> 1 | K211: 41414 | L211: =YEAR(TODAY())-YEAR(CLEAN!$K211) -> 12 | M211: 40 | N211: =SUM(CLEAN!$AB211:$AE211) -> 20 | O211: =CLEAN!$U211+CLEAN!$V211+CLEAN!$W211+CLEAN!$X211+CLEAN!$Y211+CLEAN!$Z211 -> 1690 | P211: =IF(CLEAN!$M211<=32,3,IF(CLEAN!$M211<=65,2,1)) -> 2 | Q211: =IF(Table_Market[[#This Row],[F_TOTAL_achat]]<=14,1,IF(Table_Market[[#This Row],[F_TOTAL_achat]]<=21,2,3)) -> 2 | R211: =IF(Table_Market[[#This Row],[M_TOTAL_dépensé]]<=115,1,IF(Table_Market[[#This Row],[M_TOTAL_dépensé]]<=833,2,3)) -> 3 | S211: =Table_Market[[#This Row],[R_SCORE]]&Table_Market[[#This Row],[F_SCORE]]&Table_Market[[#This Row],[M_SCORE]] -> 223 | T211: =IF(Table_Market[[#This Row],[RFM_SCORE]]="333","Clients élites",IF(LEFT(Table_Market[[#This Row],[RFM_SCORE]],1)="3","Récents prometteurs",IF(LEFT(Table_Market[[#This Row],[RFM_SCORE]],1)="1","Inactifs",IF(AND(LEFT(Table_Market[[#This Row],[RFM_SCORE]],1)>="2",MID(Table_Market[[#This Row],[RFM_SCORE]],2,1)>="2",RIGHT(Table_Market[[#This Row],[RFM_SCORE]],1)>="2"),"Fidèles rentables","Occasionnels")))) -> Fidèles rentables | U211: 1218 | V211: 16 | W211: 272 | X211: 104 | Y211: 0 | Z211: 80 | AA211: 2 | AB211: 5 | AC211: 3 | AD211: 6 | AE211: 6 | AF211: 0 | AG211: 1 | AH211: 1 | AI211: 1 | AJ211: 0 | AK211: 0 | AL211: 3 | AM211: 11 | AN211: 1
... A330: 3091 | B330: 1981 | C330: =YEAR(TODAY())-CLEAN!$B330 -> 44 | D330: 30-44 ans | E330: BAC+5 | F330: Conjoint | G330: 75774 | H330: 1 | I330: 0 | J330: =CLEAN!$H330+CLEAN!$I330 -> 1 | K330: 41761 | L330: =YEAR(TODAY())-YEAR(CLEAN!$K330) -> 11 | M330: 27 | N330: =SUM(CLEAN!$AB330:$AE330) -> 24 | O330: =CLEAN!$U330+CLEAN!$V330+CLEAN!$W330+CLEAN!$X330+CLEAN!$Y330+CLEAN!$Z330 -> 823 | P330: =IF(CLEAN!$M330<=32,3,IF(CLEAN!$M330<=65,2,1)) -> 3 | Q330: =IF(Table_Market[[#This Row],[F_TOTAL_achat]]<=14,1,IF(Table_Market[[#This Row],[F_TOTAL_achat]]<=21,2,3)) -> 3 | R330: =IF(Table_Market[[#This Row],[M_TOTAL_dépensé]]<=115,1,IF(Table_Market[[#This Row],[M_TOTAL_dépensé]]<=833,2,3)) -> 2 | S330: =Table_Market[[#This Row],[R_SCORE]]&Table_Market[[#This Row],[F_SCORE]]&Table_Market[[#This Row],[M_SCORE]] -> 332 | T330: =IF(Table_Market[[#This Row],[RFM_SCORE]]="333","Clients élites",IF(LEFT(Table_Market[[#This Row],[RFM_SCORE]],1)="3","Récents prometteurs",IF(LEFT(Table_Market[[#This Row],[RFM_SCORE]],1)="1","Inactifs",IF(AND(LEFT(Table_Market[[#This Row],[RFM_SCORE]],1)>="2",MID(Table_Market[[#This Row],[RFM_SCORE]],2,1)>="2",RIGHT(Table_Market[[#This Row],[RFM_SCORE]],1)>="2"),"Fidèles rentables","Occasionnels")))) -> Récents prometteurs | U330: 340 | V330: 21 | W330: 134 | X330: 258 | Y330: 14 | Z330: 56 | AA330: 1 | AB330: 7 | AC330: 5 | AD330: 8 | AE330: 4 | AF330: 0 | AG330: 0 | AH330: 0 | AI330: 0 | AJ330: 0 | AK330: 0 | AL330: 3 | AM330: 11 | AN330: 0
A331: 762 | B331: 1981 | C331: =YEAR(TODAY())-CLEAN!$B331 -> 44 | D331: 30-44 ans | E331: BAC+5 | F331: Conjoint | G331: 75774 | H331: 1 | I331: 0 | J331: =CLEAN!$H331+CLEAN!$I331 -> 1 | K331: 41761 | M331: 27 | N331: =SUM(CLEAN!$AB331:$AE331) -> 24 | O331: =CLEAN!$U331+CLEAN!$V331+CLEAN!$W331+CLEAN!$X331+CLEAN!$Y331+CLEAN!$Z331 -> 823 | P331: =IF(CLEAN!$M331<=32,3,IF(CLEAN!$M331<=65,2,1)) -> 3 | Q331: =IF(Table_Market[[#This Row],[F_TOTAL_achat]]<=14,1,IF(Table_Market[[#This Row],[F_TOTAL_achat]]<=21,2,3)) -> 3 | R331: =IF(Table_Market[[#This Row],[M_TOTAL_dépensé]]<=115,1,IF(Table_Market[[#This Row],[M_TOTAL_dépensé]]<=833,2,3)) -> 2 | S331: =Table_Market[[#This Row],[R_SCORE]]&Table_Market[[#This Row],[F_SCORE]]&Table_Market[[#This Row],[M_SCORE]] -> 332 | T331: =IF(Table_Market[[#This Row],[RFM_SCORE]]="333","Clients élites",IF(LEFT(Table_Market[[#This Row],[RFM_SCORE]],1)="3","Récents prometteurs",IF(LEFT(Table_Market[[#This Row],[RFM_SCORE]],1)="1","Inactifs",IF(AND(LEFT(Table_Market[[#This Row],[RFM_SCORE]],1)>="2",MID(Table_Market[[#This Row],[RFM_SCORE]],2,1)>="2",RIGHT(Table_Market[[#This Row],[RFM_SCORE]],1)>="2"),"Fidèles rentables","Occasionnels")))) -> Récents prometteurs | U331: 340 | V331: 21 | W331: 134 | X331: 258 | Y331: 14 | Z331: 56 | AA331: 1 | AB331: 7 | AC331: 5 | AD331: 8 | AE331: 4 | AF331: 0 | AG331: 0 | AH331: 0 | AI331: 0 | AJ331: 0 | AK331: 0 | AL331: 3 | AM331: 11 | AN331: 0
A332: 4580 | B332: 1969 | C332: =YEAR(TODAY())-CLEAN!$B332 -> 56 | D332: 45-59 ans | E332: BAC+3 | F332: Marié | G332: 75759 | H332: 0 | I332: 0 | J332: =CLEAN!$H332+CLEAN!$I332 -> 0 | K332: 41572 | L332: =YEAR(TODAY())-YEAR(CLEAN!$K332) -> 12 | M332: 46 | N332: =SUM(CLEAN!$AB332:$AE332) -> 30 | O332: =CLEAN!$U332+CLEAN!$V332+CLEAN!$W332+CLEAN!$X332+CLEAN!$Y332+CLEAN!$Z332 -> 2486 | P332: =IF(CLEAN!$M332<=32,3,IF(CLEAN!$M332<=65,2,1)) -> 2 | Q332: =IF(Table_Market[[#This Row],[F_TOTAL_achat]]<=14,1,IF(Table_Market[[#This Row],[F_TOTAL_achat]]<=21,2,3)) -> 3 | R332: =IF(Table_Market[[#This Row],[M_TOTAL_dépensé]]<=115,1,IF(Table_Market[[#This Row],[M_TOTAL_dépensé]]<=833,2,3)) -> 3 | S332: =Table_Market[[#This Row],[R_SCORE]]&Table_Market[[#This Row],[F_SCORE]]&Table_Market[[#This Row],[M_SCORE]] -> 233 | T332: =IF(Table_Market[[#This Row],[RFM_SCORE]]="333","Clients élites",IF(LEFT(Table_Market[[#This Row],[RFM_SCORE]],1)="3","Récents prometteurs",IF(LEFT(Table_Market[[#This Row],[RFM_SCORE]],1)="1","Inactifs",IF(AND(LEFT(Table_Market[[#This Row],[RFM_SCORE]],1)>="2",MID(Table_Market[[#This Row],[RFM_SCORE]],2,1)>="2",RIGHT(Table_Market[[#This Row],[RFM_SCORE]],1)>="2"),"Fidèles rentables","Occasionnels")))) -> Fidèles rentables | U332: 1394 | V332: 22 | W332: 708 | X332: 89 | Y332: 91 | Z332: 182 | AA332: 1 | AB332: 9 | AC332: 7 | AD332: 9 | AE332: 5 | AF332: 1 | AG332: 0 | AH332: 1 | AI332: 1 | AJ332: 0 | AK332: 0 | AL332: 3 | AM332: 11 | AN332: 1
A333: 10992 | B333: 1967 | C333: =YEAR(TODAY())-CLEAN!$B333 -> 58 | D333: 45-59 ans | E333: BAC+3 | F333: Conjoint | G333: 75702 | H333: 1 | I333: 1 | J333: =CLEAN!$H333+CLEAN!$I333 -> 2 | K333: 41150 | L333: =YEAR(TODAY())-YEAR(CLEAN!$K333) -> 13 | M333: 77 | N333: =SUM(CLEAN!$AB333:$AE333) -> 29 | O333: =CLEAN!$U333+CLEAN!$V333+CLEAN!$W333+CLEAN!$X333+CLEAN!$Y333+CLEAN!$Z333 -> 1148 | P333: =IF(CLEAN!$M333<=32,3,IF(CLEAN!$M333<=65,2,1)) -> 1 | Q333: =IF(Table_Market[[#This Row],[F_TOTAL_achat]]<=14,1,IF(Table_Market[[#This Row],[F_TOTAL_achat]]<=21,2,3)) -> 3 | R333: =IF(Table_Market[[#This Row],[M_TOTAL_dépensé]]<=115,1,IF(Table_Market[[#This Row],[M_TOTAL_dépensé]]<=833,2,3)) -> 3 | S333: =Table_Market[[#This Row],[R_SCORE]]&Table_Market[[#This Row],[F_SCORE]]&Table_Market[[#This Row],[M_SCORE]] -> 133 | T333: =IF(Table_Market[[#This Row],[RFM_SCORE]]="333","Clients élites",IF(LEFT(Table_Market[[#This Row],[RFM_SCORE]],1)="3","Récents prometteurs",IF(LEFT(Table_Market[[#This Row],[RFM_SCORE]],1)="1","Inactifs",IF(AND(LEFT(Table_Market[[#This Row],[RFM_SCORE]],1)>="2",MID(Table_Market[[#This Row],[RFM_SCORE]],2,1)>="2",RIGHT(Table_Market[[#This Row],[RFM_SCORE]],1)>="2"),"Fidèles rentables","Occasionnels")))) -> Inactifs | U333: 650 | V333: 28 | W333: 353 | X333: 45 | Y333: 42 | Z333: 30 | AA333: 5 | AB333: 4 | AC333: 6 | AD333: 11 | AE333: 8 | AF333: 0 | AG333: 0 | AH333: 0 | AI333: 0 | AJ333: 0 | AK333: 0 | AL333: 3 | AM333: 11 | AN333: 0
A334: 6977 | B334: 1974 | C334: =YEAR(TODAY())-CLEAN!$B334 -> 51 | D334: 45-59 ans | E334: BAC+3 | F334: Conjoint | G334: 75702 | H334: 0 | I334: 1 | J334: =CLEAN!$H334+CLEAN!$I334 -> 1 | K334: 41196 | L334: =YEAR(TODAY())-YEAR(CLEAN!$K334) -> 13 | M334: 87 | N334: =SUM(CLEAN!$AB334:$AE334) -> 34 | O334: =CLEAN!$U334+CLEAN!$V334+CLEAN!$W334+CLEAN!$X334+CLEAN!$Y334+CLEAN!$Z334 -> 1921 | P334: =IF(CLEAN!$M334<=32,3,IF(CLEAN!$M334<=65,2,1)) -> 1 | Q334: =IF(Table_Market[[#This Row],[F_TOTAL_achat]]<=14,1,IF(Table_Market[[#This Row],[F_TOTAL_achat]]<=21,2,3)) -> 3 | R334: =IF(Table_Market[[#This Row],[M_TOTAL_dépensé]]<=115,1,IF(Table_Market[[#This Row],[M_TOTAL_dépensé]]<=833,2,3)) -> 3 | S334: =Table_Market[[#This Row],[R_SCORE]]&Table_Market[[#This Row],[F_SCORE]]&Table_Market[[#This Row],[M_SCORE]] -> 133 | T334: =IF(Table_Market[[#This Row],[RFM_SCORE]]="333","Clients élites",IF(LEFT(Table_Market[[#This Row],[RFM_SCORE]],1)="3","Récents prometteurs",IF(LEFT(Table_Market[[#This Row],[RFM_SCORE]],1)="1","Inactifs",IF(AND(LEFT(Table_Market[[#This Row],[RFM_SCORE]],1)>="2",MID(Table_Market[[#This Row],[RFM_SCORE]],2,1)>="2",RIGHT(Table_Market[[#This Row],[RFM_SCORE]],1)>="2"),"Fidèles rentables","Occasionnels")))) -> Inactifs | U334: 1073 | V334: 0 | W334: 629 | X334: 145 | Y334: 37 | Z334: 37 | AA334: 1 | AB334: 10 | AC334: 5 | AD334: 13 | AE334: 6 | AF334: 0 | AG334: 0 | AH334: 1 | AI334: 0 | AJ334: 0 | AK334: 0 | AL334: 3 | AM334: 11 | AN334: 0
A335: 7381 | B335: 1968 | C335: =YEAR(TODAY())-CLEAN!$B335 -> 57 | D335: 45-59 ans | E335: BAC+3 | F335: Divorcé | G335: 75693 | H335: 0 | I335: 0 | J335: =CLEAN!$H335+CLEAN!$I335 -> 0 | K335: 41249 | L335: =YEAR(TODAY())-YEAR(CLEAN!$K335) -> 13 | M335: 10 | N335: =SUM(CLEAN!$AB335:$AE335) -> 25 | O335: =CLEAN!$U335+CLEAN!$V335+CLEAN!$W335+CLEAN!$X335+CLEAN!$Y335+CLEAN!$Z335 -> 1442 | P335: =IF(CLEAN!$M335<=32,3,IF(CLEAN!$M335<=65,2,1)) -> 3 | Q335: =IF(Table_Market[[#This Row],[F_TOTAL_achat]]<=14,1,IF(Table_Market[[#This Row],[F_TOTAL_achat]]<=21,2,3)) -> 3 | R335: =IF(Table_Market[[#This Row],[M_TOTAL_dépensé]]<=115,1,IF(Table_Market[[#This Row],[M_TOTAL_dépensé]]<=833,2,3)) -> 3 | S335: =Table_Market[[#This Row],[R_SCORE]]&Table_Market[[#This Row],[F_SCORE]]&Table_Market[[#This Row],[M_SCORE]] -> 333 | T335: =IF(Table_Market[[#This Row],[RFM_SCORE]]="333","Clients élites",IF(LEFT(Table_Market[[#This Row],[RFM_SCORE]],1)="3","Récents prometteurs",IF(LEFT(Table_Market[[#This Row],[RFM_SCORE]],1)="1","Inactifs",IF(AND(LEFT(Table_Market[[#This Row],[RFM_SCORE]],1)>="2",MID(Table_Market[[#This Row],[RFM_SCORE]],2,1)>="2",RIGHT(Table_Market[[#This Row],[RFM_SCORE]],1)>="2"),"Fidèles rentables","Occasionnels")))) -> Clients élites | U335: 797 | V335: 153 | W335: 293 | X335: 72 | Y335: 97 | Z335: 30 | AA335: 1 | AB335: 11 | AC335: 4 | AD335: 6 | AE335: 4 | AF335: 0 | AG335: 1 | AH335: 1 | AI335: 1 | AJ335: 0 | AK335: 0 | AL335: 3 | AM335: 11 | AN335: 1
A336: 7723 | B336: 1979 | C336: =YEAR(TODAY())-CLEAN!$B336 -> 46 | D336: 45-59 ans | E336: BAC+3 | F336: Conjoint | G336: 75507 | H336: 0 | I336: 0 | J336: =CLEAN!$H336+CLEAN!$I336 -> 0 | K336: 41761 | L336: =YEAR(TODAY())-YEAR(CLEAN!$K336) -> 11 | M336: 56 | N336: =SUM(CLEAN!$AB336:$AE336) -> 23 | O336: =CLEAN!$U336+CLEAN!$V336+CLEAN!$W336+CLEAN!$X336+CLEAN!$Y336+CLEAN!$Z336 -> 1440 | P336: =IF(CLEAN!$M336<=32,3,IF(CLEAN!$M336<=65,2,1)) -> 2 | Q336: =IF(Table_Market[[#This Row],[F_TOTAL_achat]]<=14,1,IF(Table_Market[[#This Row],[F_TOTAL_achat]]<=21,2,3)) -> 3 | R336: =IF(Table_Market[[#This Row],[M_TOTAL_dépensé]]<=115,1,IF(Table_Market[[#This Row],[M_TOTAL_dépensé]]<=833,2,3)) -> 3 | S336: =Table_Market[[#This Row],[R_SCORE]]&Table_Market[[#This Row],[F_SCORE]]&Table_Market[[#This Row],[M_SCORE]] -> 233 | T336: =IF(Table_Market[[#This Row],[RFM_SCORE]]="333","Clients élites",IF(LEFT(Table_Market[[#This Row],[RFM_SCORE]],1)="3","Récents prometteurs",IF(LEFT(Table_Market[[#This Row],[RFM_SCORE]],1)="1","Inactifs",IF(AND(LEFT(Table_Market[[#This Row],[RFM_SCORE]],1)>="2",MID(Table_Market[[#This Row],[RFM_SCORE]],2,1)>="2",RIGHT(Table_Market[[#This Row],[RFM_SCORE]],1)>="2"),"Fidèles rentables","Occasionnels")))) -> Fidèles rentables | U336: 709 | V336: 93 | W336: 374 | X336: 104 | Y336: 80 | Z336: 80 | AA336: 1 | AB336: 8 | AC336: 6 | AD336: 6 | AE336: 3 | AF336: 0 | AG336: 0 | AH336: 0 | AI336: 0 | AJ336: 0 | AK336: 0 | AL336: 3 | AM336: 11 | AN336: 0
A337: 2963 | B337: 1979 | C337: =YEAR(TODAY())-CLEAN!$B337 -> 46 | D337: 45-59 ans | E337: BAC+3 | F337: Conjoint | G337: 75507 | H337: 0 | I337: 0 | J337: =CLEAN!$H337+CLEAN!$I337 -> 0 | K337: 41761 | L337: =YEAR(TODAY())-YEAR(CLEAN!$K337) -> 11 | M337: 56 | N337: =SUM(CLEAN!$AB337:$AE337) -> 23 | O337: =CLEAN!$U337+CLEAN!$V337+CLEAN!$W337+CLEAN!$X337+CLEAN!$Y337+CLEAN!$Z337 -> 1440 | P337: =IF(CLEAN!$M337<=32,3,IF(CLEAN!$M337<=65,2,1)) -> 2 | Q337: =IF(Table_Market[[#This Row],[F_TOTAL_achat]]<=14,1,IF(Table_Market[[#This Row],[F_TOTAL_achat]]<=21,2,3)) -> 3 | R337: =IF(Table_Market[[#This Row],[M_TOTAL_dépensé]]<=115,1,IF(Table_Market[[#This Row],[M_TOTAL_dépensé]]<=833,2,3)) -> 3 | S337: =Table_Market[[#This Row],[R_SCORE]]&Table_Market[[#This Row],[F_SCORE]]&Table_Market[[#This Row],[M_SCORE]] -> 233 | T337: =IF(Table_Market[[#This Row],[RFM_SCORE]]="333","Clients élites",IF(LEFT(Table_Market[[#This Row],[RFM_SCORE]],1)="3","Récents prometteurs",IF(LEFT(Table_Market[[#This Row],[RFM_SCORE]],1)="1","Inactifs",IF(AND(LEFT(Table_Market[[#This Row],[RFM_SCORE]],1)>="2",MID(Table_Market[[#This Row],[RFM_SCORE]],2,1)>="2",RIGHT(Table_Market[[#This Row],[RFM_SCORE]],1)>="2"),"Fidèles rentables","Occasionnels")))) -> Fidèles rentables | U337: 709 | V337: 93 | W337: 374 | X337: 104 | Y337: 80 | Z337: 80 | AA337: 1 | AB337: 8 | AC337: 6 | AD337: 6 | AE337: 3 | AF337: 0 | AG337: 0 | AH337: 0 | AI337: 0 | AJ337: 0 | AK337: 0 | AL337: 3 | AM337: 11 | AN337: 0
A338: 8370 | B338: 1976 | C338: =YEAR(TODAY())-CLEAN!$B338 -> 49 | D338: 45-59 ans | E338: BAC+5 | F338: Conjoint | G338: 75484 | H338: 0 | I338: 1 | J338: =CLEAN!$H338+CLEAN!$I338 -> 1 | K338: 41123 | L338: =YEAR(TODAY())-YEAR(CLEAN!$K338) -> 13 | M338: 50 | N338: =SUM(CLEAN!$AB338:$AE338) -> 20 | O338: =CLEAN!$U338+CLEAN!$V338+CLEAN!$W338+CLEAN!$X338+CLEAN!$Y338+CLEAN!$Z338 -> 1159 | P338: =IF(CLEAN!$M338<=32,3,IF(CLEAN!$M338<=65,2,1)) -> 2 | Q338: =IF(Table_Market[[#This Row],[F_TOTAL_achat]]<=14,1,IF(Table_Market[[#This Row],[F_TOTAL_achat]]<=21,2,3)) -> 2 | R338: =IF(Table_Market[[#This Row],[M_TOTAL_dépensé]]<=115,1,IF(Table_Market[[#This Row],[M_TOTAL_dépensé]]<=833,2,3)) -> 3 | S338: =Table_Market[[#This Row],[R_SCORE]]&Table_Market[[#This Row],[F_SCORE]]&Table_Market[[#This Row],[M_SCORE]] -> 223 | T338: =IF(Table_Market[[#This Row],[RFM_SCORE]]="333","Clients élites",IF(LEFT(Table_Market[[#This Row],[RFM_SCORE]],1)="3","Récents prometteurs",IF(LEFT(Table_Market[[#This Row],[RFM_SCORE]],1)="1","Inactifs",IF(AND(LEFT(Table_Market[[#This Row],[RFM_SCORE]],1)>="2",MID(Table_Market[[#This Row],[RFM_SCORE]],2,1)>="2",RIGHT(Table_Market[[#This Row],[RFM_SCORE]],1)>="2"),"Fidèles rentables","Occasionnels")))) -> Fidèles rentables | U338: 378 | V338: 97 | W338: 259 | X338: 197 | Y338: 194 | Z338: 34 | AA338: 2 | AB338: 7 | AC338: 3 | AD338: 6 | AE338: 4 | AF338: 0 | AG338: 0 | AH338: 0 | AI338: 0 | AJ338: 0 | AK338: 0 | AL338: 3 | AM338: 11 | AN338: 0
A339: 8492 | B339: 1978 | C339: =YEAR(TODAY())-CLEAN!$B339 -> 47 | D339: 45-59 ans | E339: BAC+3 | F339: Conjoint | G339: 75437 | H339: 0 | I339: 0 | J339: =CLEAN!$H339+CLEAN!$I339 -> 0 | K339: 41587 | L339: =YEAR(TODAY())-YEAR(CLEAN!$K339) -> 12 | M339: 25 | N339: =SUM(CLEAN!$AB339:$AE339) -> 28 | O339: =CLEAN!$U339+CLEAN!$V339+CLEAN!$W339+CLEAN!$X339+CLEAN!$Y339+CLEAN!$Z339 -> 1493 | P339: =IF(CLEAN!$M339<=32,3,IF(CLEAN!$M339<=65,2,1)) -> 3 | Q339: =IF(Table_Market[[#This Row],[F_TOTAL_achat]]<=14,1,IF(Table_Market[[#This Row],[F_TOTAL_achat]]<=21,2,3)) -> 3 | R339: =IF(Table_Market[[#This Row],[M_TOTAL_dépensé]]<=115,1,IF(Table_Market[[#This Row],[M_TOTAL_dépensé]]<=833,2,3)) -> 3 | S339: =Table_Market[[#This Row],[R_SCORE]]&Table_Market[[#This Row],[F_SCORE]]&Table_Market[[#This Row],[M_SCORE]] -> 333 | T339: =IF(Table_Market[[#This Row],[RFM_SCORE]]="333","Clients élites",IF(LEFT(Table_Market[[#This Row],[RFM_SCORE]],1)="3","Récents prometteurs",IF(LEFT(Table_Market[[#This Row],[RFM_SCORE]],1)="1","Inactifs",IF(AND(LEFT(Table_Market[[#This Row],[RFM_SCORE]],1)>="2",MID(Table_Market[[#This Row],[RFM_SCORE]],2,1)>="2",RIGHT(Table_Market[[#This Row],[RFM_SCORE]],1)>="2"),"Fidèles rentables","Occasionnels")))) -> Clients élites | U339: 795 | V339: 0 | W339: 545 | X339: 95 | Y339: 58 | Z339: 0 | AA339: 1 | AB339: 8 | AC339: 4 | AD339: 10 | AE339: 6 | AF339: 0 | AG339: 0 | AH339: 0 | AI339: 1 | AJ339: 0 | AK339: 0 | AL339: 3 | AM339: 11 | AN339: 0
A340: 8746 | B340: 1989 | C340: =YEAR(TODAY())-CLEAN!$B340 -> 36 | D340: 30-44 ans | E340: BAC+3 | F340: Marié | G340: 75433 | H340: 1 | I340: 0 | J340: =CLEAN!$H340+CLEAN!$I340 -> 1 | K340: 41734 | L340: =YEAR(TODAY())-YEAR(CLEAN!$K340) -> 11 | M340: 28 | N340: =SUM(CLEAN!$AB340:$AE340) -> 23 | O340: =CLEAN!$U340+CLEAN!$V340+CLEAN!$W340+CLEAN!$X340+CLEAN!$Y340+CLEAN!$Z340 -> 1188 | P340: =IF(CLEAN!$M340<=32,3,IF(CLEAN!$M340<=65,2,1)) -> 3 | Q340: =IF(Table_Market[[#This Row],[F_TOTAL_achat]]<=14,1,IF(Table_Market[[#This Row],[F_TOTAL_achat]]<=21,2,3)) -> 3 | R340: =IF(Table_Market[[#This Row],[M_TOTAL_dépensé]]<=115,1,IF(Table_Market[[#This Row],[M_TOTAL_dépensé]]<=833,2,3)) -> 3 | S340: =Table_Market[[#This Row],[R_SCORE]]&Table_Market[[#This Row],[F_SCORE]]&Table_Market[[#This Row],[M_SCORE]] -> 333 | T340: =IF(Table_Market[[#This Row],[RFM_SCORE]]="333","Clients élites",IF(LEFT(Table_Market[[#This Row],[RFM_SCORE]],1)="3","Récents prometteurs",IF(LEFT(Table_Market[[#This Row],[RFM_SCORE]],1)="1","Inactifs",IF(AND(LEFT(Table_Market[[#This Row],[RFM_SCORE]],1)>="2",MID(Table_Market[[#This Row],[RFM_SCORE]],2,1)>="2",RIGHT(Table_Market[[#This Row],[RFM_SCORE]],1)>="2"),"Fidèles rentables","Occasionnels")))) -> Clients élites | U340: 800 | V340: 0 | W340: 297 | X340: 0 | Y340: 34 | Z340: 57 | AA340: 2 | AB340: 2 | AC340: 5 | AD340: 10 | AE340: 6 | AF340: 0 | AG340: 1 | AH340: 0 | AI340: 1 | AJ340: 0 | AK340: 0 | AL340: 3 | AM340: 11 | AN340: 0
A341: 6072 | B341: 1970 | C341: =YEAR(TODAY())-CLEAN!$B341 -> 55 | D341: 45-59 ans | E341: BAC+5 | F341: Célibataire | G341: 75345 | H341: 0 | I341: 0 | J341: =CLEAN!$H341+CLEAN!$I341 -> 0 | K341: 41307 | L341: =YEAR(TODAY())-YEAR(CLEAN!$K341) -> 12 | M341: 16 | N341: =SUM(CLEAN!$AB341:$AE341) -> 22 | O341: =CLEAN!$U341+CLEAN!$V341+CLEAN!$W341+CLEAN!$X341+CLEAN!$Y341+CLEAN!$Z341 -> 2087 | P341: =IF(CLEAN!$M341<=32,3,IF(CLEAN!$M341<=65,2,1)) -> 3 | Q341: =IF(Table_Market[[#This Row],[F_TOTAL_achat]]<=14,1,IF(Table_Market[[#This Row],[F_TOTAL_achat]]<=21,2,3)) -> 3 | R341: =IF(Table_Market[[#This Row],[M_TOTAL_dépensé]]<=115,1,IF(Table_Market[[#This Row],[M_TOTAL_dépensé]]<=833,2,3)) -> 3 | S341: =Table_Market[[#This Row],[R_SCORE]]&Table_Market[[#This Row],[F_SCORE]]&Table_Market[[#This Row],[M_SCORE]] -> 333 | T341: =IF(Table_Market[[#This Row],[RFM_SCORE]]="333","Clients élites",IF(LEFT(Table_Market[[#This Row],[RFM_SCORE]],1)="3","Récents prometteurs",IF(LEFT(Table_Market[[#This Row],[RFM_SCORE]],1)="1","Inactifs",IF(AND(LEFT(Table_Market[[#This Row],[RFM_SCORE]],1)>="2",MID(Table_Market[[#This Row],[RFM_SCORE]],2,1)>="2",RIGHT(Table_Market[[#This Row],[RFM_SCORE]],1)>="2"),"Fidèles rentables","Occasionnels")))) -> Clients élites | U341: 918 | V341: 57 | W341: 842 | X341: 99 | Y341: 38 | Z341: 133 | AA341: 1 | AB341: 5 | AC341: 8 | AD341: 6 | AE341: 3 | AF341: 0 | AG341: 0 | AH341: 0 | AI341: 1 | AJ341: 0 | AK341: 0 | AL341: 3 | AM341: 11 | AN341: 1
A342: 2499 | B342: 1958 | C342: =YEAR(TODAY())-CLEAN!$B342 -> 67 | D342: 60 ans et + | E342: BAC+5 | F342: Célibataire | G342: 75342 | H342: 0 | I342: 1 | J342: =CLEAN!$H342+CLEAN!$I342 -> 1 | K342: 41400 | L342: =YEAR(TODAY())-YEAR(CLEAN!$K342) -> 12 | M342: 38 | N342: =SUM(CLEAN!$AB342:$AE342) -> 21 | O342: =CLEAN!$U342+CLEAN!$V342+CLEAN!$W342+CLEAN!$X342+CLEAN!$Y342+CLEAN!$Z342 -> 563 | P342: =IF(CLEAN!$M342<=32,3,IF(CLEAN!$M342<=65,2,1)) -> 2 | Q342: =IF(Table_Market[[#This Row],[F_TOTAL_achat]]<=14,1,IF(Table_Market[[#This Row],[F_TOTAL_achat]]<=21,2,3)) -> 2 | R342: =IF(Table_Market[[#This Row],[M_TOTAL_dépensé]]<=115,1,IF(Table_Market[[#This Row],[M_TOTAL_dépensé]]<=833,2,3)) -> 2 | S342: =Table_Market[[#This Row],[R_SCORE]]&Table_Market[[#This Row],[F_SCORE]]&Table_Market[[#This Row],[M_SCORE]] -> 222 | T342: =IF(Table_Market[[#This Row],[RFM_SCORE]]="333","Clients élites",IF(LEFT(Table_Market[[#This Row],[RFM_SCORE]],1)="3","Récents prometteurs",IF(LEFT(Table_Market[[#This Row],[RFM_SCORE]],1)="1","Inactifs",IF(AND(LEFT(Table_Market[[#This Row],[RFM_SCORE]],1)>="2",MID(Table_Market[[#This Row],[RFM_SCORE]],2,1)>="2",RIGHT(Table_Market[[#This Row],[RFM_SCORE]],1)>="2"),"Fidèles rentables","Occasionnels")))) -> Fidèles rentables | U342: 204 | V342: 97 | W342: 97 | X342: 21 | Y342: 118 | Z342: 26 | AA342: 1 | AB342: 5 | AC342: 2 | AD342: 10 | AE342: 4 | AF342: 0 | AG342: 0 | AH342: 0 | AI342: 0 | AJ342: 0 | AK342: 0 | AL342: 3 | AM342: 11 | AN342: 0
A343: 4786 | B343: 1977 | C343: =YEAR(TODAY())-CLEAN!$B343 -> 48 | D343: 45-59 ans | E343: BAC+3 | F343: Marié | G343: 75330 | H343: 1 | I343: 1 | J343: =CLEAN!$H343+CLEAN!$I343 -> 2 | K343: 41186 | L343: =YEAR(TODAY())-YEAR(CLEAN!$K343) -> 13 | M343: 94 | N343: =SUM(CLEAN!$AB343:$AE343) -> 31 | O343: =CLEAN!$U343+CLEAN!$V343+CLEAN!$W343+CLEAN!$X343+CLEAN!$Y343+CLEAN!$Z343 -> 1109 | P343: =IF(CLEAN!$M343<=32,3,IF(CLEAN!$M343<=65,2,1)) -> 1 | Q343: =IF(Table_Market[[#This Row],[F_TOTAL_achat]]<=14,1,IF(Table_Market[[#This Row],[F_TOTAL_achat]]<=21,2,3)) -> 3 | R343: =IF(Table_Market[[#This Row],[M_TOTAL_dépensé]]<=115,1,IF(Table_Market[[#This Row],[M_TOTAL_dépensé]]<=833,2,3)) -> 3 | S343: =Table_Market[[#This Row],[R_SCORE]]&Table_Market[[#This Row],[F_SCORE]]&Table_Market[[#This Row],[M_SCORE]] -> 133 | T343: =IF(Table_Market[[#This Row],[RFM_SCORE]]="333","Clients élites",IF(LEFT(Table_Market[[#This Row],[RFM_SCORE]],1)="3","Récents prometteurs",IF(LEFT(Table_Market[[#This Row],[RFM_SCORE]],1)="1","Inactifs",IF(AND(LEFT(Table_Market[[#This Row],[RFM_SCORE]],1)>="2",MID(Table_Market[[#This Row],[RFM_SCORE]],2,1)>="2",RIGHT(Table_Market[[#This Row],[RFM_SCORE]],1)>="2"),"Fidèles rentables","Occasionnels")))) -> Inactifs | U343: 555 | V343: 82 | W343: 257 | X343: 93 | Y343: 61 | Z343: 61 | AA343: 4 | AB343: 10 | AC343: 3 | AD343: 12 | AE343: 6 | AF343: 0 | AG343: 0 | AH343: 0 | AI343: 0 | AJ343: 0 | AK343: 0 | AL343: 3 | AM343: 11 | AN343: 0
... A532: 7233 | B532: 1972 | C532: =YEAR(TODAY())-CLEAN!$B532 -> 53 | D532: 45-59 ans | E532: BAC+3 | F532: Marié | G532: 69209 | H532: 0 | I532: 0 | J532: =CLEAN!$H532+CLEAN!$I532 -> 0 | K532: 41169 | L532: =YEAR(TODAY())-YEAR(CLEAN!$K532) -> 13 | M532: 4 | N532: =SUM(CLEAN!$AB532:$AE532) -> 18 | O532: =CLEAN!$U532+CLEAN!$V532+CLEAN!$W532+CLEAN!$X532+CLEAN!$Y532+CLEAN!$Z532 -> 1782 | P532: =IF(CLEAN!$M532<=32,3,IF(CLEAN!$M532<=65,2,1)) -> 3 | Q532: =IF(Table_Market[[#This Row],[F_TOTAL_achat]]<=14,1,IF(Table_Market[[#This Row],[F_TOTAL_achat]]<=21,2,3)) -> 2 | R532: =IF(Table_Market[[#This Row],[M_TOTAL_dépensé]]<=115,1,IF(Table_Market[[#This Row],[M_TOTAL_dépensé]]<=833,2,3)) -> 3 | S532: =Table_Market[[#This Row],[R_SCORE]]&Table_Market[[#This Row],[F_SCORE]]&Table_Market[[#This Row],[M_SCORE]] -> 323 | T532: =IF(Table_Market[[#This Row],[RFM_SCORE]]="333","Clients élites",IF(LEFT(Table_Market[[#This Row],[RFM_SCORE]],1)="3","Récents prometteurs",IF(LEFT(Table_Market[[#This Row],[RFM_SCORE]],1)="1","Inactifs",IF(AND(LEFT(Table_Market[[#This Row],[RFM_SCORE]],1)>="2",MID(Table_Market[[#This Row],[RFM_SCORE]],2,1)>="2",RIGHT(Table_Market[[#This Row],[RFM_SCORE]],1)>="2"),"Fidèles rentables","Occasionnels")))) -> Récents prometteurs | U532: 496 | V532: 32 | W532: 849 | X532: 229 | Y532: 48 | Z532: 128 | AA532: 2 | AB532: 5 | AC532: 3 | AD532: 6 | AE532: 4 | AF532: 0 | AG532: 0 | AH532: 0 | AI532: 1 | AJ532: 0 | AK532: 0 | AL532: 3 | AM532: 11 | AN532: 0
A533: 7300 | B533: 1952 | C533: =YEAR(TODAY())-CLEAN!$B533 -> 73 | D533: 60 ans et + | E533: BAC+3 | F533: Divorcé | G533: 69142 | H533: 0 | I533: 1 | J533: =CLEAN!$H533+CLEAN!$I533 -> 1 | K533: 41819 | M533: 50 | N533: =SUM(CLEAN!$AB533:$AE533) -> 21 | O533: =CLEAN!$U533+CLEAN!$V533+CLEAN!$W533+CLEAN!$X533+CLEAN!$Y533+CLEAN!$Z533 -> 535 | P533: =IF(CLEAN!$M533<=32,3,IF(CLEAN!$M533<=65,2,1)) -> 2 | Q533: =IF(Table_Market[[#This Row],[F_TOTAL_achat]]<=14,1,IF(Table_Market[[#This Row],[F_TOTAL_achat]]<=21,2,3)) -> 2 | R533: =IF(Table_Market[[#This Row],[M_TOTAL_dépensé]]<=115,1,IF(Table_Market[[#This Row],[M_TOTAL_dépensé]]<=833,2,3)) -> 2 | S533: =Table_Market[[#This Row],[R_SCORE]]&Table_Market[[#This Row],[F_SCORE]]&Table_Market[[#This Row],[M_SCORE]] -> 222 | T533: =IF(Table_Market[[#This Row],[RFM_SCORE]]="333","Clients élites",IF(LEFT(Table_Market[[#This Row],[RFM_SCORE]],1)="3","Récents prometteurs",IF(LEFT(Table_Market[[#This Row],[RFM_SCORE]],1)="1","Inactifs",IF(AND(LEFT(Table_Market[[#This Row],[RFM_SCORE]],1)>="2",MID(Table_Market[[#This Row],[RFM_SCORE]],2,1)>="2",RIGHT(Table_Market[[#This Row],[RFM_SCORE]],1)>="2"),"Fidèles rentables","Occasionnels")))) -> Fidèles rentables | U533: 448 | V533: 4 | W533: 34 | X533: 6 | Y533: 4 | Z533: 39 | AA533: 3 | AB533: 8 | AC533: 1 | AD533: 7 | AE533: 5 | AF533: 0 | AG533: 1 | AH533: 0 | AI533: 0 | AJ533: 0 | AK533: 0 | AL533: 3 | AM533: 11 | AN533: 0
A534: 5232 | B534: 1965 | C534: =YEAR(TODAY())-CLEAN!$B534 -> 60 | D534: 60 ans et + | E534: BAC+3 | F534: Marié | G534: 69139 | H534: 0 | I534: 1 | J534: =CLEAN!$H534+CLEAN!$I534 -> 1 | K534: 41666 | L534: =YEAR(TODAY())-YEAR(CLEAN!$K534) -> 11 | M534: 23 | N534: =SUM(CLEAN!$AB534:$AE534) -> 14 | O534: =CLEAN!$U534+CLEAN!$V534+CLEAN!$W534+CLEAN!$X534+CLEAN!$Y534+CLEAN!$Z534 -> 227 | P534: =IF(CLEAN!$M534<=32,3,IF(CLEAN!$M534<=65,2,1)) -> 3 | Q534: =IF(Table_Market[[#This Row],[F_TOTAL_achat]]<=14,1,IF(Table_Market[[#This Row],[F_TOTAL_achat]]<=21,2,3)) -> 1 | R534: =IF(Table_Market[[#This Row],[M_TOTAL_dépensé]]<=115,1,IF(Table_Market[[#This Row],[M_TOTAL_dépensé]]<=833,2,3)) -> 2 | S534: =Table_Market[[#This Row],[R_SCORE]]&Table_Market[[#This Row],[F_SCORE]]&Table_Market[[#This Row],[M_SCORE]] -> 312 | T534: =IF(Table_Market[[#This Row],[RFM_SCORE]]="333","Clients élites",IF(LEFT(Table_Market[[#This Row],[RFM_SCORE]],1)="3","Récents prometteurs",IF(LEFT(Table_Market[[#This Row],[RFM_SCORE]],1)="1","Inactifs",IF(AND(LEFT(Table_Market[[#This Row],[RFM_SCORE]],1)>="2",MID(Table_Market[[#This Row],[RFM_SCORE]],2,1)>="2",RIGHT(Table_Market[[#This Row],[RFM_SCORE]],1)>="2"),"Fidèles rentables","Occasionnels")))) -> Récents prometteurs | U534: 86 | V534: 12 | W534: 75 | X534: 33 | Y534: 15 | Z534: 6 | AA534: 1 | AB534: 4 | AC534: 1 | AD534: 5 | AE534: 4 | AF534: 0 | AG534: 0 | AH534: 0 | AI534: 0 | AJ534: 0 | AK534: 0 | AL534: 3 | AM534: 11 | AN534: 0
A535: 3011 | B535: 1965 | C535: =YEAR(TODAY())-CLEAN!$B535 -> 60 | D535: 60 ans et + | E535: BAC+3 | F535: Marié | G535: 69139 | H535: 0 | I535: 1 | J535: =CLEAN!$H535+CLEAN!$I535 -> 1 | K535: 41666 | L535: =YEAR(TODAY())-YEAR(CLEAN!$K535) -> 11 | M535: 23 | N535: =SUM(CLEAN!$AB535:$AE535) -> 14 | O535: =CLEAN!$U535+CLEAN!$V535+CLEAN!$W535+CLEAN!$X535+CLEAN!$Y535+CLEAN!$Z535 -> 227 | P535: =IF(CLEAN!$M535<=32,3,IF(CLEAN!$M535<=65,2,1)) -> 3 | Q535: =IF(Table_Market[[#This Row],[F_TOTAL_achat]]<=14,1,IF(Table_Market[[#This Row],[F_TOTAL_achat]]<=21,2,3)) -> 1 | R535: =IF(Table_Market[[#This Row],[M_TOTAL_dépensé]]<=115,1,IF(Table_Market[[#This Row],[M_TOTAL_dépensé]]<=833,2,3)) -> 2 | S535: =Table_Market[[#This Row],[R_SCORE]]&Table_Market[[#This Row],[F_SCORE]]&Table_Market[[#This Row],[M_SCORE]] -> 312 | T535: =IF(Table_Market[[#This Row],[RFM_SCORE]]="333","Clients élites",IF(LEFT(Table_Market[[#This Row],[RFM_SCORE]],1)="3","Récents prometteurs",IF(LEFT(Table_Market[[#This Row],[RFM_SCORE]],1)="1","Inactifs",IF(AND(LEFT(Table_Market[[#This Row],[RFM_SCORE]],1)>="2",MID(Table_Market[[#This Row],[RFM_SCORE]],2,1)>="2",RIGHT(Table_Market[[#This Row],[RFM_SCORE]],1)>="2"),"Fidèles rentables","Occasionnels")))) -> Récents prometteurs | U535: 86 | V535: 12 | W535: 75 | X535: 33 | Y535: 15 | Z535: 6 | AA535: 1 | AB535: 4 | AC535: 1 | AD535: 5 | AE535: 4 | AF535: 0 | AG535: 0 | AH535: 0 | AI535: 0 | AJ535: 0 | AK535: 0 | AL535: 3 | AM535: 11 | AN535: 0
A536: 2407 | B536: 1982 | C536: =YEAR(TODAY())-CLEAN!$B536 -> 43 | D536: 30-44 ans | E536: BAC+3 | F536: Marié | G536: 69109 | H536: 0 | I536: 0 | J536: =CLEAN!$H536+CLEAN!$I536 -> 0 | K536: 41222 | L536: =YEAR(TODAY())-YEAR(CLEAN!$K536) -> 13 | M536: 10 | N536: =SUM(CLEAN!$AB536:$AE536) -> 23 | O536: =CLEAN!$U536+CLEAN!$V536+CLEAN!$W536+CLEAN!$X536+CLEAN!$Y536+CLEAN!$Z536 -> 1555 | P536: =IF(CLEAN!$M536<=32,3,IF(CLEAN!$M536<=65,2,1)) -> 3 | Q536: =IF(Table_Market[[#This Row],[F_TOTAL_achat]]<=14,1,IF(Table_Market[[#This Row],[F_TOTAL_achat]]<=21,2,3)) -> 3 | R536: =IF(Table_Market[[#This Row],[M_TOTAL_dépensé]]<=115,1,IF(Table_Market[[#This Row],[M_TOTAL_dépensé]]<=833,2,3)) -> 3 | S536: =Table_Market[[#This Row],[R_SCORE]]&Table_Market[[#This Row],[F_SCORE]]&Table_Market[[#This Row],[M_SCORE]] -> 333 | T536: =IF(Table_Market[[#This Row],[RFM_SCORE]]="333","Clients élites",IF(LEFT(Table_Market[[#This Row],[RFM_SCORE]],1)="3","Récents prometteurs",IF(LEFT(Table_Market[[#This Row],[RFM_SCORE]],1)="1","Inactifs",IF(AND(LEFT(Table_Market[[#This Row],[RFM_SCORE]],1)>="2",MID(Table_Market[[#This Row],[RFM_SCORE]],2,1)>="2",RIGHT(Table_Market[[#This Row],[RFM_SCORE]],1)>="2"),"Fidèles rentables","Occasionnels")))) -> Clients élites | U536: 823 | V536: 25 | W536: 459 | X536: 124 | Y536: 29 | Z536: 95 | AA536: 1 | AB536: 6 | AC536: 6 | AD536: 7 | AE536: 4 | AF536: 0 | AG536: 0 | AH536: 1 | AI536: 0 | AJ536: 0 | AK536: 0 | AL536: 3 | AM536: 11 | AN536: 1
A537: 9064 | B537: 1982 | C537: =YEAR(TODAY())-CLEAN!$B537 -> 43 | D537: 30-44 ans | E537: BAC+3 | F537: Marié | G537: 69109 | H537: 0 | I537: 0 | J537: =CLEAN!$H537+CLEAN!$I537 -> 0 | K537: 41222 | L537: =YEAR(TODAY())-YEAR(CLEAN!$K537) -> 13 | M537: 10 | N537: =SUM(CLEAN!$AB537:$AE537) -> 23 | O537: =CLEAN!$U537+CLEAN!$V537+CLEAN!$W537+CLEAN!$X537+CLEAN!$Y537+CLEAN!$Z537 -> 1555 | P537: =IF(CLEAN!$M537<=32,3,IF(CLEAN!$M537<=65,2,1)) -> 3 | Q537: =IF(Table_Market[[#This Row],[F_TOTAL_achat]]<=14,1,IF(Table_Market[[#This Row],[F_TOTAL_achat]]<=21,2,3)) -> 3 | R537: =IF(Table_Market[[#This Row],[M_TOTAL_dépensé]]<=115,1,IF(Table_Market[[#This Row],[M_TOTAL_dépensé]]<=833,2,3)) -> 3 | S537: =Table_Market[[#This Row],[R_SCORE]]&Table_Market[[#This Row],[F_SCORE]]&Table_Market[[#This Row],[M_SCORE]] -> 333 | T537: =IF(Table_Market[[#This Row],[RFM_SCORE]]="333","Clients élites",IF(LEFT(Table_Market[[#This Row],[RFM_SCORE]],1)="3","Récents prometteurs",IF(LEFT(Table_Market[[#This Row],[RFM_SCORE]],1)="1","Inactifs",IF(AND(LEFT(Table_Market[[#This Row],[RFM_SCORE]],1)>="2",MID(Table_Market[[#This Row],[RFM_SCORE]],2,1)>="2",RIGHT(Table_Market[[#This Row],[RFM_SCORE]],1)>="2"),"Fidèles rentables","Occasionnels")))) -> Clients élites | U537: 823 | V537: 25 | W537: 459 | X537: 124 | Y537: 29 | Z537: 95 | AA537: 1 | AB537: 6 | AC537: 6 | AD537: 7 | AE537: 4 | AF537: 0 | AG537: 0 | AH537: 1 | AI537: 0 | AJ537: 0 | AK537: 0 | AL537: 3 | AM537: 11 | AN537: 1
A538: 4475 | B538: 1949 | C538: =YEAR(TODAY())-CLEAN!$B538 -> 76 | D538: 60 ans et + | E538: Doctorat | F538: Marié | G538: 69098 | H538: 0 | I538: 0 | J538: =CLEAN!$H538+CLEAN!$I538 -> 0 | K538: 41321 | L538: =YEAR(TODAY())-YEAR(CLEAN!$K538) -> 12 | M538: 82 | N538: =SUM(CLEAN!$AB538:$AE538) -> 29 | O538: =CLEAN!$U538+CLEAN!$V538+CLEAN!$W538+CLEAN!$X538+CLEAN!$Y538+CLEAN!$Z538 -> 2440 | P538: =IF(CLEAN!$M538<=32,3,IF(CLEAN!$M538<=65,2,1)) -> 1 | Q538: =IF(Table_Market[[#This Row],[F_TOTAL_achat]]<=14,1,IF(Table_Market[[#This Row],[F_TOTAL_achat]]<=21,2,3)) -> 3 | R538: =IF(Table_Market[[#This Row],[M_TOTAL_dépensé]]<=115,1,IF(Table_Market[[#This Row],[M_TOTAL_dépensé]]<=833,2,3)) -> 3 | S538: =Table_Market[[#This Row],[R_SCORE]]&Table_Market[[#This Row],[F_SCORE]]&Table_Market[[#This Row],[M_SCORE]] -> 133 | T538: =IF(Table_Market[[#This Row],[RFM_SCORE]]="333","Clients élites",IF(LEFT(Table_Market[[#This Row],[RFM_SCORE]],1)="3","Récents prometteurs",IF(LEFT(Table_Market[[#This Row],[RFM_SCORE]],1)="1","Inactifs",IF(AND(LEFT(Table_Market[[#This Row],[RFM_SCORE]],1)>="2",MID(Table_Market[[#This Row],[RFM_SCORE]],2,1)>="2",RIGHT(Table_Market[[#This Row],[RFM_SCORE]],1)>="2"),"Fidèles rentables","Occasionnels")))) -> Inactifs | U538: 1315 | V538: 22 | W538: 780 | X538: 145 | Y538: 0 | Z538: 178 | AA538: 1 | AB538: 7 | AC538: 8 | AD538: 9 | AE538: 5 | AF538: 0 | AG538: 0 | AH538: 0 | AI538: 0 | AJ538: 0 | AK538: 0 | AL538: 3 | AM538: 11 | AN538: 0
A539: 4477 | B539: 1958 | C539: =YEAR(TODAY())-CLEAN!$B539 -> 67 | D539: 60 ans et + | E539: BAC+3 | F539: Conjoint | G539: 69096 | H539: 0 | I539: 1 | J539: =CLEAN!$H539+CLEAN!$I539 -> 1 | K539: 41544 | L539: =YEAR(TODAY())-YEAR(CLEAN!$K539) -> 12 | M539: 4 | N539: =SUM(CLEAN!$AB539:$AE539) -> 21 | O539: =CLEAN!$U539+CLEAN!$V539+CLEAN!$W539+CLEAN!$X539+CLEAN!$Y539+CLEAN!$Z539 -> 653 | P539: =IF(CLEAN!$M539<=32,3,IF(CLEAN!$M539<=65,2,1)) -> 3 | Q539: =IF(Table_Market[[#This Row],[F_TOTAL_achat]]<=14,1,IF(Table_Market[[#This Row],[F_TOTAL_achat]]<=21,2,3)) -> 2 | R539: =IF(Table_Market[[#This Row],[M_TOTAL_dépensé]]<=115,1,IF(Table_Market[[#This Row],[M_TOTAL_dépensé]]<=833,2,3)) -> 2 | S539: =Table_Market[[#This Row],[R_SCORE]]&Table_Market[[#This Row],[F_SCORE]]&Table_Market[[#This Row],[M_SCORE]] -> 322 | T539: =IF(Table_Market[[#This Row],[RFM_SCORE]]="333","Clients élites",IF(LEFT(Table_Market[[#This Row],[RFM_SCORE]],1)="3","Récents prometteurs",IF(LEFT(Table_Market[[#This Row],[RFM_SCORE]],1)="1","Inactifs",IF(AND(LEFT(Table_Market[[#This Row],[RFM_SCORE]],1)>="2",MID(Table_Market[[#This Row],[RFM_SCORE]],2,1)>="2",RIGHT(Table_Market[[#This Row],[RFM_SCORE]],1)>="2"),"Fidèles rentables","Occasionnels")))) -> Récents prometteurs | U539: 247 | V539: 49 | W539: 159 | X539: 7 | Y539: 82 | Z539: 109 | AA539: 1 | AB539: 5 | AC539: 2 | AD539: 10 | AE539: 4 | AF539: 0 | AG539: 0 | AH539: 0 | AI539: 0 | AJ539: 0 | AK539: 0 | AL539: 3 | AM539: 11 | AN539: 0
A540: 10727 | B540: 1970 | C540: =YEAR(TODAY())-CLEAN!$B540 -> 55 | D540: 45-59 ans | E540: Doctorat | F540: Marié | G540: 69084 | H540: 1 | I540: 0 | J540: =CLEAN!$H540+CLEAN!$I540 -> 1 | K540: 41597 | L540: =YEAR(TODAY())-YEAR(CLEAN!$K540) -> 12 | M540: 43 | N540: =SUM(CLEAN!$AB540:$AE540) -> 31 | O540: =CLEAN!$U540+CLEAN!$V540+CLEAN!$W540+CLEAN!$X540+CLEAN!$Y540+CLEAN!$Z540 -> 1586 | P540: =IF(CLEAN!$M540<=32,3,IF(CLEAN!$M540<=65,2,1)) -> 2 | Q540: =IF(Table_Market[[#This Row],[F_TOTAL_achat]]<=14,1,IF(Table_Market[[#This Row],[F_TOTAL_achat]]<=21,2,3)) -> 3 | R540: =IF(Table_Market[[#This Row],[M_TOTAL_dépensé]]<=115,1,IF(Table_Market[[#This Row],[M_TOTAL_dépensé]]<=833,2,3)) -> 3 | S540: =Table_Market[[#This Row],[R_SCORE]]&Table_Market[[#This Row],[F_SCORE]]&Table_Market[[#This Row],[M_SCORE]] -> 233 | T540: =IF(Table_Market[[#This Row],[RFM_SCORE]]="333","Clients élites",IF(LEFT(Table_Market[[#This Row],[RFM_SCORE]],1)="3","Récents prometteurs",IF(LEFT(Table_Market[[#This Row],[RFM_SCORE]],1)="1","Inactifs",IF(AND(LEFT(Table_Market[[#This Row],[RFM_SCORE]],1)>="2",MID(Table_Market[[#This Row],[RFM_SCORE]],2,1)>="2",RIGHT(Table_Market[[#This Row],[RFM_SCORE]],1)>="2"),"Fidèles rentables","Occasionnels")))) -> Fidèles rentables | U540: 1181 | V540: 107 | W540: 199 | X540: 39 | Y540: 30 | Z540: 30 | AA540: 2 | AB540: 7 | AC540: 3 | AD540: 13 | AE540: 8 | AF540: 0 | AG540: 0 | AH540: 0 | AI540: 0 | AJ540: 0 | AK540: 0 | AL540: 3 | AM540: 11 | AN540: 0
A541: 5299 | B541: 1970 | C541: =YEAR(TODAY())-CLEAN!$B541 -> 55 | D541: 45-59 ans | E541: Doctorat | F541: Marié | G541: 69084 | H541: 1 | I541: 0 | J541: =CLEAN!$H541+CLEAN!$I541 -> 1 | K541: 41597 | L541: =YEAR(TODAY())-YEAR(CLEAN!$K541) -> 12 | M541: 43 | N541: =SUM(CLEAN!$AB541:$AE541) -> 31 | O541: =CLEAN!$U541+CLEAN!$V541+CLEAN!$W541+CLEAN!$X541+CLEAN!$Y541+CLEAN!$Z541 -> 1586 | P541: =IF(CLEAN!$M541<=32,3,IF(CLEAN!$M541<=65,2,1)) -> 2 | Q541: =IF(Table_Market[[#This Row],[F_TOTAL_achat]]<=14,1,IF(Table_Market[[#This Row],[F_TOTAL_achat]]<=21,2,3)) -> 3 | R541: =IF(Table_Market[[#This Row],[M_TOTAL_dépensé]]<=115,1,IF(Table_Market[[#This Row],[M_TOTAL_dépensé]]<=833,2,3)) -> 3 | S541: =Table_Market[[#This Row],[R_SCORE]]&Table_Market[[#This Row],[F_SCORE]]&Table_Market[[#This Row],[M_SCORE]] -> 233 | T541: =IF(Table_Market[[#This Row],[RFM_SCORE]]="333","Clients élites",IF(LEFT(Table_Market[[#This Row],[RFM_SCORE]],1)="3","Récents prometteurs",IF(LEFT(Table_Market[[#This Row],[RFM_SCORE]],1)="1","Inactifs",IF(AND(LEFT(Table_Market[[#This Row],[RFM_SCORE]],1)>="2",MID(Table_Market[[#This Row],[RFM_SCORE]],2,1)>="2",RIGHT(Table_Market[[#This Row],[RFM_SCORE]],1)>="2"),"Fidèles rentables","Occasionnels")))) -> Fidèles rentables | U541: 1181 | V541: 107 | W541: 199 | X541: 39 | Y541: 30 | Z541: 30 | AA541: 2 | AB541: 7 | AC541: 3 | AD541: 13 | AE541: 8 | AF541: 0 | AG541: 0 | AH541: 0 | AI541: 0 | AJ541: 0 | AK541: 0 | AL541: 3 | AM541: 11 | AN541: 0
A542: 1459 | B542: 1966 | C542: =YEAR(TODAY())-CLEAN!$B542 -> 59 | D542: 45-59 ans | E542: Doctorat | F542: Marié | G542: 69063 | H542: 0 | I542: 1 | J542: =CLEAN!$H542+CLEAN!$I542 -> 1 | K542: 41220 | L542: =YEAR(TODAY())-YEAR(CLEAN!$K542) -> 13 | M542: 16 | N542: =SUM(CLEAN!$AB542:$AE542) -> 16 | O542: =CLEAN!$U542+CLEAN!$V542+CLEAN!$W542+CLEAN!$X542+CLEAN!$Y542+CLEAN!$Z542 -> 928 | P542: =IF(CLEAN!$M542<=32,3,IF(CLEAN!$M542<=65,2,1)) -> 3 | Q542: =IF(Table_Market[[#This Row],[F_TOTAL_achat]]<=14,1,IF(Table_Market[[#This Row],[F_TOTAL_achat]]<=21,2,3)) -> 2 | R542: =IF(Table_Market[[#This Row],[M_TOTAL_dépensé]]<=115,1,IF(Table_Market[[#This Row],[M_TOTAL_dépensé]]<=833,2,3)) -> 3 | S542: =Table_Market[[#This Row],[R_SCORE]]&Table_Market[[#This Row],[F_SCORE]]&Table_Market[[#This Row],[M_SCORE]] -> 323 | T542: =IF(Table_Market[[#This Row],[RFM_SCORE]]="333","Clients élites",IF(LEFT(Table_Market[[#This Row],[RFM_SCORE]],1)="3","Récents prometteurs",IF(LEFT(Table_Market[[#This Row],[RFM_SCORE]],1)="1","Inactifs",IF(AND(LEFT(Table_Market[[#This Row],[RFM_SCORE]],1)>="2",MID(Table_Market[[#This Row],[RFM_SCORE]],2,1)>="2",RIGHT(Table_Market[[#This Row],[RFM_SCORE]],1)>="2"),"Fidèles rentables","Occasionnels")))) -> Récents prometteurs | U542: 666 | V542: 35 | W542: 124 | X542: 69 | Y542: 8 | Z542: 26 | AA542: 1 | AB542: 5 | AC542: 3 | AD542: 5 | AE542: 3 | AF542: 0 | AG542: 0 | AH542: 0 | AI542: 0 | AJ542: 0 | AK542: 0 | AL542: 3 | AM542: 11 | AN542: 0
A543: 3389 | B543: 1970 | C543: =YEAR(TODAY())-CLEAN!$B543 -> 55 | D543: 45-59 ans | E543: BAC+3 | F543: Marié | G543: 69016 | H543: 0 | I543: 1 | J543: =CLEAN!$H543+CLEAN!$I543 -> 1 | K543: 41235 | L543: =YEAR(TODAY())-YEAR(CLEAN!$K543) -> 13 | M543: 61 | N543: =SUM(CLEAN!$AB543:$AE543) -> 35 | O543: =CLEAN!$U543+CLEAN!$V543+CLEAN!$W543+CLEAN!$X543+CLEAN!$Y543+CLEAN!$Z543 -> 1533 | P543: =IF(CLEAN!$M543<=32,3,IF(CLEAN!$M543<=65,2,1)) -> 2 | Q543: =IF(Table_Market[[#This Row],[F_TOTAL_achat]]<=14,1,IF(Table_Market[[#This Row],[F_TOTAL_achat]]<=21,2,3)) -> 3 | R543: =IF(Table_Market[[#This Row],[M_TOTAL_dépensé]]<=115,1,IF(Table_Market[[#This Row],[M_TOTAL_dépensé]]<=833,2,3)) -> 3 | S543: =Table_Market[[#This Row],[R_SCORE]]&Table_Market[[#This Row],[F_SCORE]]&Table_Market[[#This Row],[M_SCORE]] -> 233 | T543: =IF(Table_Market[[#This Row],[RFM_SCORE]]="333","Clients élites",IF(LEFT(Table_Market[[#This Row],[RFM_SCORE]],1)="3","Récents prometteurs",IF(LEFT(Table_Market[[#This Row],[RFM_SCORE]],1)="1","Inactifs",IF(AND(LEFT(Table_Market[[#This Row],[RFM_SCORE]],1)>="2",MID(Table_Market[[#This Row],[RFM_SCORE]],2,1)>="2",RIGHT(Table_Market[[#This Row],[RFM_SCORE]],1)>="2"),"Fidèles rentables","Occasionnels")))) -> Fidèles rentables | U543: 726 | V543: 53 | W543: 363 | X543: 123 | Y543: 107 | Z543: 161 | AA543: 4 | AB543: 8 | AC543: 9 | AD543: 13 | AE543: 5 | AF543: 0 | AG543: 0 | AH543: 0 | AI543: 0 | AJ543: 0 | AK543: 0 | AL543: 3 | AM543: 11 | AN543: 0
A544: 6870 | B544: 1959 | C544: =YEAR(TODAY())-CLEAN!$B544 -> 66 | D544: 60 ans et + | E544: Doctorat | F544: Divorcé | G544: 68805 | H544: 0 | I544: 1 | J544: =CLEAN!$H544+CLEAN!$I544 -> 1 | K544: 41534 | L544: =YEAR(TODAY())-YEAR(CLEAN!$K544) -> 12 | M544: 73 | N544: =SUM(CLEAN!$AB544:$AE544) -> 13 | O544: =CLEAN!$U544+CLEAN!$V544+CLEAN!$W544+CLEAN!$X544+CLEAN!$Y544+CLEAN!$Z544 -> 283 | P544: =IF(CLEAN!$M544<=32,3,IF(CLEAN!$M544<=65,2,1)) -> 1 | Q544: =IF(Table_Market[[#This Row],[F_TOTAL_achat]]<=14,1,IF(Table_Market[[#This Row],[F_TOTAL_achat]]<=21,2,3)) -> 1 | R544: =IF(Table_Market[[#This Row],[M_TOTAL_dépensé]]<=115,1,IF(Table_Market[[#This Row],[M_TOTAL_dépensé]]<=833,2,3)) -> 2 | S544: =Table_Market[[#This Row],[R_SCORE]]&Table_Market[[#This Row],[F_SCORE]]&Table_Market[[#This Row],[M_SCORE]] -> 112 | T544: =IF(Table_Market[[#This Row],[RFM_SCORE]]="333","Clients élites",IF(LEFT(Table_Market[[#This Row],[RFM_SCORE]],1)="3","Récents prometteurs",IF(LEFT(Table_Market[[#This Row],[RFM_SCORE]],1)="1","Inactifs",IF(AND(LEFT(Table_Market[[#This Row],[RFM_SCORE]],1)>="2",MID(Table_Market[[#This Row],[RFM_SCORE]],2,1)>="2",RIGHT(Table_Market[[#This Row],[RFM_SCORE]],1)>="2"),"Fidèles rentables","Occasionnels")))) -> Inactifs | U544: 182 | V544: 2 | W544: 49 | X544: 17 | Y544: 13 | Z544: 20 | AA544: 1 | AB544: 3 | AC544: 1 | AD544: 7 | AE544: 2 | AF544: 0 | AG544: 0 | AH544: 0 | AI544: 0 | AJ544: 0 | AK544: 0 | AL544: 3 | AM544: 11 | AN544: 0
A545: 4910 | B545: 1967 | C545: =YEAR(TODAY())-CLEAN!$B545 -> 58 | D545: 45-59 ans | E545: BAC+3 | F545: Divorcé | G545: 68743 | H545: 0 | I545: 0 | J545: =CLEAN!$H545+CLEAN!$I545 -> 0 | K545: 41151 | L545: =YEAR(TODAY())-YEAR(CLEAN!$K545) -> 13 | M545: 81 | N545: =SUM(CLEAN!$AB545:$AE545) -> 36 | O545: =CLEAN!$U545+CLEAN!$V545+CLEAN!$W545+CLEAN!$X545+CLEAN!$Y545+CLEAN!$Z545 -> 2074 | P545: =IF(CLEAN!$M545<=32,3,IF(CLEAN!$M545<=65,2,1)) -> 1 | Q545: =IF(Table_Market[[#This Row],[F_TOTAL_achat]]<=14,1,IF(Table_Market[[#This Row],[F_TOTAL_achat]]<=21,2,3)) -> 3 | R545: =IF(Table_Market[[#This Row],[M_TOTAL_dépensé]]<=115,1,IF(Table_Market[[#This Row],[M_TOTAL_dépensé]]<=833,2,3)) -> 3 | S545: =Table_Market[[#This Row],[R_SCORE]]&Table_Market[[#This Row],[F_SCORE]]&Table_Market[[#This Row],[M_SCORE]] -> 133 | T545: =IF(Table_Market[[#This Row],[RFM_SCORE]]="333","Clients élites",IF(LEFT(Table_Market[[#This Row],[RFM_SCORE]],1)="3","Récents prometteurs",IF(LEFT(Table_Market[[#This Row],[RFM_SCORE]],1)="1","Inactifs",IF(AND(LEFT(Table_Market[[#This Row],[RFM_SCORE]],1)>="2",MID(Table_Market[[#This Row],[RFM_SCORE]],2,1)>="2",RIGHT(Table_Market[[#This Row],[RFM_SCORE]],1)>="2"),"Fidèles rentables","Occasionnels")))) -> Inactifs | U545: 1132 | V545: 134 | W545: 384 | X545: 175 | Y545: 134 | Z545: 115 | AA545: 1 | AB545: 11 | AC545: 5 | AD545: 13 | AE545: 7 | AF545: 0 | AG545: 0 | AH545: 0 | AI545: 0 | AJ545: 0 | AK545: 0 | AL545: 3 | AM545: 11 | AN545: 0
... A707: 7476 | B707: 1964 | C707: =YEAR(TODAY())-CLEAN!$B707 -> 61 | D707: 60 ans et + | E707: BAC+5 | F707: Célibataire | G707: 63972 | H707: 0 | I707: 1 | J707: =CLEAN!$H707+CLEAN!$I707 -> 1 | K707: 41245 | L707: =YEAR(TODAY())-YEAR(CLEAN!$K707) -> 13 | M707: 93 | N707: =SUM(CLEAN!$AB707:$AE707) -> 23 | O707: =CLEAN!$U707+CLEAN!$V707+CLEAN!$W707+CLEAN!$X707+CLEAN!$Y707+CLEAN!$Z707 -> 1269 | P707: =IF(CLEAN!$M707<=32,3,IF(CLEAN!$M707<=65,2,1)) -> 1 | Q707: =IF(Table_Market[[#This Row],[F_TOTAL_achat]]<=14,1,IF(Table_Market[[#This Row],[F_TOTAL_achat]]<=21,2,3)) -> 3 | R707: =IF(Table_Market[[#This Row],[M_TOTAL_dépensé]]<=115,1,IF(Table_Market[[#This Row],[M_TOTAL_dépensé]]<=833,2,3)) -> 3 | S707: =Table_Market[[#This Row],[R_SCORE]]&Table_Market[[#This Row],[F_SCORE]]&Table_Market[[#This Row],[M_SCORE]] -> 133 | T707: =IF(Table_Market[[#This Row],[RFM_SCORE]]="333","Clients élites",IF(LEFT(Table_Market[[#This Row],[RFM_SCORE]],1)="3","Récents prometteurs",IF(LEFT(Table_Market[[#This Row],[RFM_SCORE]],1)="1","Inactifs",IF(AND(LEFT(Table_Market[[#This Row],[RFM_SCORE]],1)>="2",MID(Table_Market[[#This Row],[RFM_SCORE]],2,1)>="2",RIGHT(Table_Market[[#This Row],[RFM_SCORE]],1)>="2"),"Fidèles rentables","Occasionnels")))) -> Inactifs | U707: 928 | V707: 63 | W707: 254 | X707: 0 | Y707: 12 | Z707: 12 | AA707: 4 | AB707: 5 | AC707: 4 | AD707: 10 | AE707: 4 | AF707: 0 | AG707: 1 | AH707: 0 | AI707: 0 | AJ707: 0 | AK707: 0 | AL707: 3 | AM707: 11 | AN707: 0
A708: 9166 | B708: 1968 | C708: =YEAR(TODAY())-CLEAN!$B708 -> 57 | D708: 45-59 ans | E708: BAC+3 | F708: Marié | G708: 63967 | H708: 0 | I708: 1 | J708: =CLEAN!$H708+CLEAN!$I708 -> 1 | K708: 41495 | M708: 57 | N708: =SUM(CLEAN!$AB708:$AE708) -> 22 | O708: =CLEAN!$U708+CLEAN!$V708+CLEAN!$W708+CLEAN!$X708+CLEAN!$Y708+CLEAN!$Z708 -> 882 | P708: =IF(CLEAN!$M708<=32,3,IF(CLEAN!$M708<=65,2,1)) -> 2 | Q708: =IF(Table_Market[[#This Row],[F_TOTAL_achat]]<=14,1,IF(Table_Market[[#This Row],[F_TOTAL_achat]]<=21,2,3)) -> 3 | R708: =IF(Table_Market[[#This Row],[M_TOTAL_dépensé]]<=115,1,IF(Table_Market[[#This Row],[M_TOTAL_dépensé]]<=833,2,3)) -> 3 | S708: =Table_Market[[#This Row],[R_SCORE]]&Table_Market[[#This Row],[F_SCORE]]&Table_Market[[#This Row],[M_SCORE]] -> 233 | T708: =IF(Table_Market[[#This Row],[RFM_SCORE]]="333","Clients élites",IF(LEFT(Table_Market[[#This Row],[RFM_SCORE]],1)="3","Récents prometteurs",IF(LEFT(Table_Market[[#This Row],[RFM_SCORE]],1)="1","Inactifs",IF(AND(LEFT(Table_Market[[#This Row],[RFM_SCORE]],1)>="2",MID(Table_Market[[#This Row],[RFM_SCORE]],2,1)>="2",RIGHT(Table_Market[[#This Row],[RFM_SCORE]],1)>="2"),"Fidèles rentables","Occasionnels")))) -> Fidèles rentables | U708: 387 | V708: 84 | W708: 141 | X708: 73 | Y708: 35 | Z708: 162 | AA708: 3 | AB708: 4 | AC708: 4 | AD708: 12 | AE708: 2 | AF708: 0 | AG708: 0 | AH708: 0 | AI708: 0 | AJ708: 0 | AK708: 0 | AL708: 3 | AM708: 11 | AN708: 0
A709: 8091 | B709: 1956 | C709: =YEAR(TODAY())-CLEAN!$B709 -> 69 | D709: 60 ans et + | E709: BAC+3 | F709: Marié | G709: 63943 | H709: 0 | I709: 1 | J709: =CLEAN!$H709+CLEAN!$I709 -> 1 | K709: 41154 | L709: =YEAR(TODAY())-YEAR(CLEAN!$K709) -> 13 | M709: 50 | N709: =SUM(CLEAN!$AB709:$AE709) -> 21 | O709: =CLEAN!$U709+CLEAN!$V709+CLEAN!$W709+CLEAN!$X709+CLEAN!$Y709+CLEAN!$Z709 -> 1106 | P709: =IF(CLEAN!$M709<=32,3,IF(CLEAN!$M709<=65,2,1)) -> 2 | Q709: =IF(Table_Market[[#This Row],[F_TOTAL_achat]]<=14,1,IF(Table_Market[[#This Row],[F_TOTAL_achat]]<=21,2,3)) -> 2 | R709: =IF(Table_Market[[#This Row],[M_TOTAL_dépensé]]<=115,1,IF(Table_Market[[#This Row],[M_TOTAL_dépensé]]<=833,2,3)) -> 3 | S709: =Table_Market[[#This Row],[R_SCORE]]&Table_Market[[#This Row],[F_SCORE]]&Table_Market[[#This Row],[M_SCORE]] -> 223 | T709: =IF(Table_Market[[#This Row],[RFM_SCORE]]="333","Clients élites",IF(LEFT(Table_Market[[#This Row],[RFM_SCORE]],1)="3","Récents prometteurs",IF(LEFT(Table_Market[[#This Row],[RFM_SCORE]],1)="1","Inactifs",IF(AND(LEFT(Table_Market[[#This Row],[RFM_SCORE]],1)>="2",MID(Table_Market[[#This Row],[RFM_SCORE]],2,1)>="2",RIGHT(Table_Market[[#This Row],[RFM_SCORE]],1)>="2"),"Fidèles rentables","Occasionnels")))) -> Fidèles rentables | U709: 423 | V709: 184 | W709: 368 | X709: 13 | Y709: 97 | Z709: 21 | AA709: 1 | AB709: 6 | AC709: 4 | AD709: 6 | AE709: 5 | AF709: 0 | AG709: 0 | AH709: 0 | AI709: 0 | AJ709: 0 | AK709: 0 | AL709: 3 | AM709: 11 | AN709: 0
A710: 4405 | B710: 1956 | C710: =YEAR(TODAY())-CLEAN!$B710 -> 69 | D710: 60 ans et + | E710: BAC+5 | F710: Marié | G710: 63915 | H710: 0 | I710: 2 | J710: =CLEAN!$H710+CLEAN!$I710 -> 2 | K710: 41485 | L710: =YEAR(TODAY())-YEAR(CLEAN!$K710) -> 12 | M710: 2 | N710: =SUM(CLEAN!$AB710:$AE710) -> 26 | O710: =CLEAN!$U710+CLEAN!$V710+CLEAN!$W710+CLEAN!$X710+CLEAN!$Y710+CLEAN!$Z710 -> 789 | P710: =IF(CLEAN!$M710<=32,3,IF(CLEAN!$M710<=65,2,1)) -> 3 | Q710: =IF(Table_Market[[#This Row],[F_TOTAL_achat]]<=14,1,IF(Table_Market[[#This Row],[F_TOTAL_achat]]<=21,2,3)) -> 3 | R710: =IF(Table_Market[[#This Row],[M_TOTAL_dépensé]]<=115,1,IF(Table_Market[[#This Row],[M_TOTAL_dépensé]]<=833,2,3)) -> 2 | S710: =Table_Market[[#This Row],[R_SCORE]]&Table_Market[[#This Row],[F_SCORE]]&Table_Market[[#This Row],[M_SCORE]] -> 332 | T710: =IF(Table_Market[[#This Row],[RFM_SCORE]]="333","Clients élites",IF(LEFT(Table_Market[[#This Row],[RFM_SCORE]],1)="3","Récents prometteurs",IF(LEFT(Table_Market[[#This Row],[RFM_SCORE]],1)="1","Inactifs",IF(AND(LEFT(Table_Market[[#This Row],[RFM_SCORE]],1)>="2",MID(Table_Market[[#This Row],[RFM_SCORE]],2,1)>="2",RIGHT(Table_Market[[#This Row],[RFM_SCORE]],1)>="2"),"Fidèles rentables","Occasionnels")))) -> Récents prometteurs | U710: 622 | V710: 7 | W710: 115 | X710: 30 | Y710: 0 | Z710: 15 | AA710: 2 | AB710: 6 | AC710: 3 | AD710: 12 | AE710: 5 | AF710: 0 | AG710: 0 | AH710: 0 | AI710: 0 | AJ710: 0 | AK710: 0 | AL710: 3 | AM710: 11 | AN710: 0
A711: 7079 | B711: 1962 | C711: =YEAR(TODAY())-CLEAN!$B711 -> 63 | D711: 60 ans et + | E711: BAC+3 | F711: Divorcé | G711: 63887 | H711: 0 | I711: 1 | J711: =CLEAN!$H711+CLEAN!$I711 -> 1 | K711: 41160 | L711: =YEAR(TODAY())-YEAR(CLEAN!$K711) -> 13 | M711: 38 | N711: =SUM(CLEAN!$AB711:$AE711) -> 33 | O711: =CLEAN!$U711+CLEAN!$V711+CLEAN!$W711+CLEAN!$X711+CLEAN!$Y711+CLEAN!$Z711 -> 1245 | P711: =IF(CLEAN!$M711<=32,3,IF(CLEAN!$M711<=65,2,1)) -> 2 | Q711: =IF(Table_Market[[#This Row],[F_TOTAL_achat]]<=14,1,IF(Table_Market[[#This Row],[F_TOTAL_achat]]<=21,2,3)) -> 3 | R711: =IF(Table_Market[[#This Row],[M_TOTAL_dépensé]]<=115,1,IF(Table_Market[[#This Row],[M_TOTAL_dépensé]]<=833,2,3)) -> 3 | S711: =Table_Market[[#This Row],[R_SCORE]]&Table_Market[[#This Row],[F_SCORE]]&Table_Market[[#This Row],[M_SCORE]] -> 233 | T711: =IF(Table_Market[[#This Row],[RFM_SCORE]]="333","Clients élites",IF(LEFT(Table_Market[[#This Row],[RFM_SCORE]],1)="3","Récents prometteurs",IF(LEFT(Table_Market[[#This Row],[RFM_SCORE]],1)="1","Inactifs",IF(AND(LEFT(Table_Market[[#This Row],[RFM_SCORE]],1)>="2",MID(Table_Market[[#This Row],[RFM_SCORE]],2,1)>="2",RIGHT(Table_Market[[#This Row],[RFM_SCORE]],1)>="2"),"Fidèles rentables","Occasionnels")))) -> Fidèles rentables | U711: 897 | V711: 23 | W711: 207 | X711: 15 | Y711: 11 | Z711: 92 | AA711: 5 | AB711: 9 | AC711: 6 | AD711: 12 | AE711: 6 | AF711: 0 | AG711: 0 | AH711: 0 | AI711: 0 | AJ711: 0 | AK711: 0 | AL711: 3 | AM711: 11 | AN711: 0
A712: 3870 | B712: 1978 | C712: =YEAR(TODAY())-CLEAN!$B712 -> 47 | D712: 45-59 ans | E712: BAC+5 | F712: Conjoint | G712: 63855 | H712: 0 | I712: 0 | J712: =CLEAN!$H712+CLEAN!$I712 -> 0 | K712: 41314 | L712: =YEAR(TODAY())-YEAR(CLEAN!$K712) -> 12 | M712: 28 | N712: =SUM(CLEAN!$AB712:$AE712) -> 27 | O712: =CLEAN!$U712+CLEAN!$V712+CLEAN!$W712+CLEAN!$X712+CLEAN!$Y712+CLEAN!$Z712 -> 1006 | P712: =IF(CLEAN!$M712<=32,3,IF(CLEAN!$M712<=65,2,1)) -> 3 | Q712: =IF(Table_Market[[#This Row],[F_TOTAL_achat]]<=14,1,IF(Table_Market[[#This Row],[F_TOTAL_achat]]<=21,2,3)) -> 3 | R712: =IF(Table_Market[[#This Row],[M_TOTAL_dépensé]]<=115,1,IF(Table_Market[[#This Row],[M_TOTAL_dépensé]]<=833,2,3)) -> 3 | S712: =Table_Market[[#This Row],[R_SCORE]]&Table_Market[[#This Row],[F_SCORE]]&Table_Market[[#This Row],[M_SCORE]] -> 333 | T712: =IF(Table_Market[[#This Row],[RFM_SCORE]]="333","Clients élites",IF(LEFT(Table_Market[[#This Row],[RFM_SCORE]],1)="3","Récents prometteurs",IF(LEFT(Table_Market[[#This Row],[RFM_SCORE]],1)="1","Inactifs",IF(AND(LEFT(Table_Market[[#This Row],[RFM_SCORE]],1)>="2",MID(Table_Market[[#This Row],[RFM_SCORE]],2,1)>="2",RIGHT(Table_Market[[#This Row],[RFM_SCORE]],1)>="2"),"Fidèles rentables","Occasionnels")))) -> Clients élites | U712: 359 | V712: 35 | W712: 314 | X712: 93 | Y712: 116 | Z712: 89 | AA712: 1 | AB712: 7 | AC712: 3 | AD712: 13 | AE712: 4 | AF712: 0 | AG712: 0 | AH712: 0 | AI712: 0 | AJ712: 0 | AK712: 0 | AL712: 3 | AM712: 11 | AN712: 0
A713: 4391 | B713: 1968 | C713: =YEAR(TODAY())-CLEAN!$B713 -> 57 | D713: 45-59 ans | E713: BAC+5 | F713: Divorcé | G713: 63841 | H713: 0 | I713: 1 | J713: =CLEAN!$H713+CLEAN!$I713 -> 1 | K713: 41385 | L713: =YEAR(TODAY())-YEAR(CLEAN!$K713) -> 12 | M713: 64 | N713: =SUM(CLEAN!$AB713:$AE713) -> 27 | O713: =CLEAN!$U713+CLEAN!$V713+CLEAN!$W713+CLEAN!$X713+CLEAN!$Y713+CLEAN!$Z713 -> 908 | P713: =IF(CLEAN!$M713<=32,3,IF(CLEAN!$M713<=65,2,1)) -> 2 | Q713: =IF(Table_Market[[#This Row],[F_TOTAL_achat]]<=14,1,IF(Table_Market[[#This Row],[F_TOTAL_achat]]<=21,2,3)) -> 3 | R713: =IF(Table_Market[[#This Row],[M_TOTAL_dépensé]]<=115,1,IF(Table_Market[[#This Row],[M_TOTAL_dépensé]]<=833,2,3)) -> 3 | S713: =Table_Market[[#This Row],[R_SCORE]]&Table_Market[[#This Row],[F_SCORE]]&Table_Market[[#This Row],[M_SCORE]] -> 233 | T713: =IF(Table_Market[[#This Row],[RFM_SCORE]]="333","Clients élites",IF(LEFT(Table_Market[[#This Row],[RFM_SCORE]],1)="3","Récents prometteurs",IF(LEFT(Table_Market[[#This Row],[RFM_SCORE]],1)="1","Inactifs",IF(AND(LEFT(Table_Market[[#This Row],[RFM_SCORE]],1)>="2",MID(Table_Market[[#This Row],[RFM_SCORE]],2,1)>="2",RIGHT(Table_Market[[#This Row],[RFM_SCORE]],1)>="2"),"Fidèles rentables","Occasionnels")))) -> Fidèles rentables | U713: 635 | V713: 15 | W713: 100 | X713: 20 | Y713: 7 | Z713: 131 | AA713: 1 | AB713: 9 | AC713: 3 | AD713: 9 | AE713: 6 | AF713: 0 | AG713: 0 | AH713: 0 | AI713: 0 | AJ713: 0 | AK713: 0 | AL713: 3 | AM713: 11 | AN713: 0
A714: 6283 | B714: 1968 | C714: =YEAR(TODAY())-CLEAN!$B714 -> 57 | D714: 45-59 ans | E714: BAC+5 | F714: Divorcé | G714: 63841 | H714: 0 | I714: 1 | J714: =CLEAN!$H714+CLEAN!$I714 -> 1 | K714: 41385 | L714: =YEAR(TODAY())-YEAR(CLEAN!$K714) -> 12 | M714: 64 | N714: =SUM(CLEAN!$AB714:$AE714) -> 27 | O714: =CLEAN!$U714+CLEAN!$V714+CLEAN!$W714+CLEAN!$X714+CLEAN!$Y714+CLEAN!$Z714 -> 908 | P714: =IF(CLEAN!$M714<=32,3,IF(CLEAN!$M714<=65,2,1)) -> 2 | Q714: =IF(Table_Market[[#This Row],[F_TOTAL_achat]]<=14,1,IF(Table_Market[[#This Row],[F_TOTAL_achat]]<=21,2,3)) -> 3 | R714: =IF(Table_Market[[#This Row],[M_TOTAL_dépensé]]<=115,1,IF(Table_Market[[#This Row],[M_TOTAL_dépensé]]<=833,2,3)) -> 3 | S714: =Table_Market[[#This Row],[R_SCORE]]&Table_Market[[#This Row],[F_SCORE]]&Table_Market[[#This Row],[M_SCORE]] -> 233 | T714: =IF(Table_Market[[#This Row],[RFM_SCORE]]="333","Clients élites",IF(LEFT(Table_Market[[#This Row],[RFM_SCORE]],1)="3","Récents prometteurs",IF(LEFT(Table_Market[[#This Row],[RFM_SCORE]],1)="1","Inactifs",IF(AND(LEFT(Table_Market[[#This Row],[RFM_SCORE]],1)>="2",MID(Table_Market[[#This Row],[RFM_SCORE]],2,1)>="2",RIGHT(Table_Market[[#This Row],[RFM_SCORE]],1)>="2"),"Fidèles rentables","Occasionnels")))) -> Fidèles rentables | U714: 635 | V714: 15 | W714: 100 | X714: 20 | Y714: 7 | Z714: 131 | AA714: 1 | AB714: 9 | AC714: 3 | AD714: 9 | AE714: 6 | AF714: 0 | AG714: 0 | AH714: 0 | AI714: 0 | AJ714: 0 | AK714: 0 | AL714: 3 | AM714: 11 | AN714: 0
A715: 3421 | B715: 1968 | C715: =YEAR(TODAY())-CLEAN!$B715 -> 57 | D715: 45-59 ans | E715: BAC+5 | F715: Divorcé | G715: 63841 | H715: 0 | I715: 1 | J715: =CLEAN!$H715+CLEAN!$I715 -> 1 | K715: 41385 | L715: =YEAR(TODAY())-YEAR(CLEAN!$K715) -> 12 | M715: 64 | N715: =SUM(CLEAN!$AB715:$AE715) -> 27 | O715: =CLEAN!$U715+CLEAN!$V715+CLEAN!$W715+CLEAN!$X715+CLEAN!$Y715+CLEAN!$Z715 -> 908 | P715: =IF(CLEAN!$M715<=32,3,IF(CLEAN!$M715<=65,2,1)) -> 2 | Q715: =IF(Table_Market[[#This Row],[F_TOTAL_achat]]<=14,1,IF(Table_Market[[#This Row],[F_TOTAL_achat]]<=21,2,3)) -> 3 | R715: =IF(Table_Market[[#This Row],[M_TOTAL_dépensé]]<=115,1,IF(Table_Market[[#This Row],[M_TOTAL_dépensé]]<=833,2,3)) -> 3 | S715: =Table_Market[[#This Row],[R_SCORE]]&Table_Market[[#This Row],[F_SCORE]]&Table_Market[[#This Row],[M_SCORE]] -> 233 | T715: =IF(Table_Market[[#This Row],[RFM_SCORE]]="333","Clients élites",IF(LEFT(Table_Market[[#This Row],[RFM_SCORE]],1)="3","Récents prometteurs",IF(LEFT(Table_Market[[#This Row],[RFM_SCORE]],1)="1","Inactifs",IF(AND(LEFT(Table_Market[[#This Row],[RFM_SCORE]],1)>="2",MID(Table_Market[[#This Row],[RFM_SCORE]],2,1)>="2",RIGHT(Table_Market[[#This Row],[RFM_SCORE]],1)>="2"),"Fidèles rentables","Occasionnels")))) -> Fidèles rentables | U715: 635 | V715: 15 | W715: 100 | X715: 20 | Y715: 7 | Z715: 131 | AA715: 1 | AB715: 9 | AC715: 3 | AD715: 9 | AE715: 6 | AF715: 0 | AG715: 0 | AH715: 0 | AI715: 0 | AJ715: 0 | AK715: 0 | AL715: 3 | AM715: 11 | AN715: 0
A716: 1245 | B716: 1966 | C716: =YEAR(TODAY())-CLEAN!$B716 -> 59 | D716: 45-59 ans | E716: BAC+3 | F716: Célibataire | G716: 63810 | H716: 0 | I716: 1 | J716: =CLEAN!$H716+CLEAN!$I716 -> 1 | K716: 41224 | L716: =YEAR(TODAY())-YEAR(CLEAN!$K716) -> 13 | M716: 45 | N716: =SUM(CLEAN!$AB716:$AE716) -> 27 | O716: =CLEAN!$U716+CLEAN!$V716+CLEAN!$W716+CLEAN!$X716+CLEAN!$Y716+CLEAN!$Z716 -> 1371 | P716: =IF(CLEAN!$M716<=32,3,IF(CLEAN!$M716<=65,2,1)) -> 2 | Q716: =IF(Table_Market[[#This Row],[F_TOTAL_achat]]<=14,1,IF(Table_Market[[#This Row],[F_TOTAL_achat]]<=21,2,3)) -> 3 | R716: =IF(Table_Market[[#This Row],[M_TOTAL_dépensé]]<=115,1,IF(Table_Market[[#This Row],[M_TOTAL_dépensé]]<=833,2,3)) -> 3 | S716: =Table_Market[[#This Row],[R_SCORE]]&Table_Market[[#This Row],[F_SCORE]]&Table_Market[[#This Row],[M_SCORE]] -> 233 | T716: =IF(Table_Market[[#This Row],[RFM_SCORE]]="333","Clients élites",IF(LEFT(Table_Market[[#This Row],[RFM_SCORE]],1)="3","Récents prometteurs",IF(LEFT(Table_Market[[#This Row],[RFM_SCORE]],1)="1","Inactifs",IF(AND(LEFT(Table_Market[[#This Row],[RFM_SCORE]],1)>="2",MID(Table_Market[[#This Row],[RFM_SCORE]],2,1)>="2",RIGHT(Table_Market[[#This Row],[RFM_SCORE]],1)>="2"),"Fidèles rentables","Occasionnels")))) -> Fidèles rentables | U716: 977 | V716: 12 | W716: 253 | X716: 16 | Y716: 12 | Z716: 101 | AA716: 4 | AB716: 4 | AC716: 3 | AD716: 12 | AE716: 8 | AF716: 0 | AG716: 1 | AH716: 0 | AI716: 0 | AJ716: 0 | AK716: 0 | AL716: 3 | AM716: 11 | AN716: 0
A717: 2561 | B717: 1966 | C717: =YEAR(TODAY())-CLEAN!$B717 -> 59 | D717: 45-59 ans | E717: BAC+3 | F717: Célibataire | G717: 63810 | H717: 0 | I717: 1 | J717: =CLEAN!$H717+CLEAN!$I717 -> 1 | K717: 41224 | L717: =YEAR(TODAY())-YEAR(CLEAN!$K717) -> 13 | M717: 45 | N717: =SUM(CLEAN!$AB717:$AE717) -> 27 | O717: =CLEAN!$U717+CLEAN!$V717+CLEAN!$W717+CLEAN!$X717+CLEAN!$Y717+CLEAN!$Z717 -> 1371 | P717: =IF(CLEAN!$M717<=32,3,IF(CLEAN!$M717<=65,2,1)) -> 2 | Q717: =IF(Table_Market[[#This Row],[F_TOTAL_achat]]<=14,1,IF(Table_Market[[#This Row],[F_TOTAL_achat]]<=21,2,3)) -> 3 | R717: =IF(Table_Market[[#This Row],[M_TOTAL_dépensé]]<=115,1,IF(Table_Market[[#This Row],[M_TOTAL_dépensé]]<=833,2,3)) -> 3 | S717: =Table_Market[[#This Row],[R_SCORE]]&Table_Market[[#This Row],[F_SCORE]]&Table_Market[[#This Row],[M_SCORE]] -> 233 | T717: =IF(Table_Market[[#This Row],[RFM_SCORE]]="333","Clients élites",IF(LEFT(Table_Market[[#This Row],[RFM_SCORE]],1)="3","Récents prometteurs",IF(LEFT(Table_Market[[#This Row],[RFM_SCORE]],1)="1","Inactifs",IF(AND(LEFT(Table_Market[[#This Row],[RFM_SCORE]],1)>="2",MID(Table_Market[[#This Row],[RFM_SCORE]],2,1)>="2",RIGHT(Table_Market[[#This Row],[RFM_SCORE]],1)>="2"),"Fidèles rentables","Occasionnels")))) -> Fidèles rentables | U717: 977 | V717: 12 | W717: 253 | X717: 16 | Y717: 12 | Z717: 101 | AA717: 4 | AB717: 4 | AC717: 3 | AD717: 12 | AE717: 8 | AF717: 0 | AG717: 1 | AH717: 0 | AI717: 0 | AJ717: 0 | AK717: 0 | AL717: 3 | AM717: 11 | AN717: 0
A718: 4478 | B718: 1979 | C718: =YEAR(TODAY())-CLEAN!$B718 -> 46 | D718: 45-59 ans | E718: BAC+3 | F718: Marié | G718: 63777 | H718: 1 | I718: 1 | J718: =CLEAN!$H718+CLEAN!$I718 -> 2 | K718: 41357 | L718: =YEAR(TODAY())-YEAR(CLEAN!$K718) -> 12 | M718: 87 | N718: =SUM(CLEAN!$AB718:$AE718) -> 26 | O718: =CLEAN!$U718+CLEAN!$V718+CLEAN!$W718+CLEAN!$X718+CLEAN!$Y718+CLEAN!$Z718 -> 653 | P718: =IF(CLEAN!$M718<=32,3,IF(CLEAN!$M718<=65,2,1)) -> 1 | Q718: =IF(Table_Market[[#This Row],[F_TOTAL_achat]]<=14,1,IF(Table_Market[[#This Row],[F_TOTAL_achat]]<=21,2,3)) -> 3 | R718: =IF(Table_Market[[#This Row],[M_TOTAL_dépensé]]<=115,1,IF(Table_Market[[#This Row],[M_TOTAL_dépensé]]<=833,2,3)) -> 2 | S718: =Table_Market[[#This Row],[R_SCORE]]&Table_Market[[#This Row],[F_SCORE]]&Table_Market[[#This Row],[M_SCORE]] -> 132 | T718: =IF(Table_Market[[#This Row],[RFM_SCORE]]="333","Clients élites",IF(LEFT(Table_Market[[#This Row],[RFM_SCORE]],1)="3","Récents prometteurs",IF(LEFT(Table_Market[[#This Row],[RFM_SCORE]],1)="1","Inactifs",IF(AND(LEFT(Table_Market[[#This Row],[RFM_SCORE]],1)>="2",MID(Table_Market[[#This Row],[RFM_SCORE]],2,1)>="2",RIGHT(Table_Market[[#This Row],[RFM_SCORE]],1)>="2"),"Fidèles rentables","Occasionnels")))) -> Inactifs | U718: 457 | V718: 5 | W718: 106 | X718: 15 | Y718: 17 | Z718: 53 | AA718: 8 | AB718: 11 | AC718: 1 | AD718: 6 | AE718: 8 | AF718: 0 | AG718: 0 | AH718: 0 | AI718: 0 | AJ718: 0 | AK718: 0 | AL718: 3 | AM718: 11 | AN718: 0
A719: 8727 | B719: 1978 | C719: =YEAR(TODAY())-CLEAN!$B719 -> 47 | D719: 45-59 ans | E719: BAC+3 | F719: Divorcé | G719: 63693 | H719: 0 | I719: 1 | J719: =CLEAN!$H719+CLEAN!$I719 -> 1 | K719: 41561 | L719: =YEAR(TODAY())-YEAR(CLEAN!$K719) -> 12 | M719: 63 | N719: =SUM(CLEAN!$AB719:$AE719) -> 32 | O719: =CLEAN!$U719+CLEAN!$V719+CLEAN!$W719+CLEAN!$X719+CLEAN!$Y719+CLEAN!$Z719 -> 1150 | P719: =IF(CLEAN!$M719<=32,3,IF(CLEAN!$M719<=65,2,1)) -> 2 | Q719: =IF(Table_Market[[#This Row],[F_TOTAL_achat]]<=14,1,IF(Table_Market[[#This Row],[F_TOTAL_achat]]<=21,2,3)) -> 3 | R719: =IF(Table_Market[[#This Row],[M_TOTAL_dépensé]]<=115,1,IF(Table_Market[[#This Row],[M_TOTAL_dépensé]]<=833,2,3)) -> 3 | S719: =Table_Market[[#This Row],[R_SCORE]]&Table_Market[[#This Row],[F_SCORE]]&Table_Market[[#This Row],[M_SCORE]] -> 233 | T719: =IF(Table_Market[[#This Row],[RFM_SCORE]]="333","Clients élites",IF(LEFT(Table_Market[[#This Row],[RFM_SCORE]],1)="3","Récents prometteurs",IF(LEFT(Table_Market[[#This Row],[RFM_SCORE]],1)="1","Inactifs",IF(AND(LEFT(Table_Market[[#This Row],[RFM_SCORE]],1)>="2",MID(Table_Market[[#This Row],[RFM_SCORE]],2,1)>="2",RIGHT(Table_Market[[#This Row],[RFM_SCORE]],1)>="2"),"Fidèles rentables","Occasionnels")))) -> Fidèles rentables | U719: 587 | V719: 43 | W719: 337 | X719: 42 | Y719: 87 | Z719: 54 | AA719: 3 | AB719: 11 | AC719: 6 | AD719: 9 | AE719: 6 | AF719: 0 | AG719: 0 | AH719: 0 | AI719: 0 | AJ719: 0 | AK719: 0 | AL719: 3 | AM719: 11 | AN719: 0
A720: 3056 | B720: 1978 | C720: =YEAR(TODAY())-CLEAN!$B720 -> 47 | D720: 45-59 ans | E720: BAC+3 | F720: Divorcé | G720: 63693 | H720: 0 | I720: 1 | J720: =CLEAN!$H720+CLEAN!$I720 -> 1 | K720: 41561 | L720: =YEAR(TODAY())-YEAR(CLEAN!$K720) -> 12 | M720: 63 | N720: =SUM(CLEAN!$AB720:$AE720) -> 32 | O720: =CLEAN!$U720+CLEAN!$V720+CLEAN!$W720+CLEAN!$X720+CLEAN!$Y720+CLEAN!$Z720 -> 1150 | P720: =IF(CLEAN!$M720<=32,3,IF(CLEAN!$M720<=65,2,1)) -> 2 | Q720: =IF(Table_Market[[#This Row],[F_TOTAL_achat]]<=14,1,IF(Table_Market[[#This Row],[F_TOTAL_achat]]<=21,2,3)) -> 3 | R720: =IF(Table_Market[[#This Row],[M_TOTAL_dépensé]]<=115,1,IF(Table_Market[[#This Row],[M_TOTAL_dépensé]]<=833,2,3)) -> 3 | S720: =Table_Market[[#This Row],[R_SCORE]]&Table_Market[[#This Row],[F_SCORE]]&Table_Market[[#This Row],[M_SCORE]] -> 233 | T720: =IF(Table_Market[[#This Row],[RFM_SCORE]]="333","Clients élites",IF(LEFT(Table_Market[[#This Row],[RFM_SCORE]],1)="3","Récents prometteurs",IF(LEFT(Table_Market[[#This Row],[RFM_SCORE]],1)="1","Inactifs",IF(AND(LEFT(Table_Market[[#This Row],[RFM_SCORE]],1)>="2",MID(Table_Market[[#This Row],[RFM_SCORE]],2,1)>="2",RIGHT(Table_Market[[#This Row],[RFM_SCORE]],1)>="2"),"Fidèles rentables","Occasionnels")))) -> Fidèles rentables | U720: 587 | V720: 43 | W720: 337 | X720: 42 | Y720: 87 | Z720: 54 | AA720: 3 | AB720: 11 | AC720: 6 | AD720: 9 | AE720: 6 | AF720: 0 | AG720: 0 | AH720: 0 | AI720: 0 | AJ720: 0 | AK720: 0 | AL720: 3 | AM720: 11 | AN720: 0
A721: 3599 | B721: 1970 | C721: =YEAR(TODAY())-CLEAN!$B721 -> 55 | D721: 45-59 ans | E721: BAC+3 | F721: Marié | G721: 63684 | H721: 0 | I721: 1 | J721: =CLEAN!$H721+CLEAN!$I721 -> 1 | K721: 41239 | M721: 61 | N721: =SUM(CLEAN!$AB721:$AE721) -> 25 | O721: =CLEAN!$U721+CLEAN!$V721+CLEAN!$W721+CLEAN!$X721+CLEAN!$Y721+CLEAN!$Z721 -> 1464 | P721: =IF(CLEAN!$M721<=32,3,IF(CLEAN!$M721<=65,2,1)) -> 2 | Q721: =IF(Table_Market[[#This Row],[F_TOTAL_achat]]<=14,1,IF(Table_Market[[#This Row],[F_TOTAL_achat]]<=21,2,3)) -> 3 | R721: =IF(Table_Market[[#This Row],[M_TOTAL_dépensé]]<=115,1,IF(Table_Market[[#This Row],[M_TOTAL_dépensé]]<=833,2,3)) -> 3 | S721: =Table_Market[[#This Row],[R_SCORE]]&Table_Market[[#This Row],[F_SCORE]]&Table_Market[[#This Row],[M_SCORE]] -> 233 | T721: =IF(Table_Market[[#This Row],[RFM_SCORE]]="333","Clients élites",IF(LEFT(Table_Market[[#This Row],[RFM_SCORE]],1)="3","Récents prometteurs",IF(LEFT(Table_Market[[#This Row],[RFM_SCORE]],1)="1","Inactifs",IF(AND(LEFT(Table_Market[[#This Row],[RFM_SCORE]],1)>="2",MID(Table_Market[[#This Row],[RFM_SCORE]],2,1)>="2",RIGHT(Table_Market[[#This Row],[RFM_SCORE]],1)>="2"),"Fidèles rentables","Occasionnels")))) -> Fidèles rentables | U721: 575 | V721: 80 | W721: 428 | X721: 208 | Y721: 93 | Z721: 80 | AA721: 3 | AB721: 8 | AC721: 4 | AD721: 8 | AE721: 5 | AF721: 0 | AG721: 0 | AH721: 0 | AI721: 0 | AJ721: 0 | AK721: 0 | AL721: 3 | AM721: 11 | AN721: 0
A722: 4073 | B722: 1954 | C722: =YEAR(TODAY())-CLEAN!$B722 -> 71 | D722: 60 ans et + | E722: BAC+5 | F722: Marié | G722: 63564 | H722: 0 | I722: 0 | J722: =CLEAN!$H722+CLEAN!$I722 -> 0 | K722: 41668 | L722: =YEAR(TODAY())-YEAR(CLEAN!$K722) -> 11 | M722: 0 | N722: =SUM(CLEAN!$AB722:$AE722) -> 33 | O722: =CLEAN!$U722+CLEAN!$V722+CLEAN!$W722+CLEAN!$X722+CLEAN!$Y722+CLEAN!$Z722 -> 1215 | P722: =IF(CLEAN!$M722<=32,3,IF(CLEAN!$M722<=65,2,1)) -> 3 | Q722: =IF(Table_Market[[#This Row],[F_TOTAL_achat]]<=14,1,IF(Table_Market[[#This Row],[F_TOTAL_achat]]<=21,2,3)) -> 3 | R722: =IF(Table_Market[[#This Row],[M_TOTAL_dépensé]]<=115,1,IF(Table_Market[[#This Row],[M_TOTAL_dépensé]]<=833,2,3)) -> 3 | S722: =Table_Market[[#This Row],[R_SCORE]]&Table_Market[[#This Row],[F_SCORE]]&Table_Market[[#This Row],[M_SCORE]] -> 333 | T722: =IF(Table_Market[[#This Row],[RFM_SCORE]]="333","Clients élites",IF(LEFT(Table_Market[[#This Row],[RFM_SCORE]],1)="3","Récents prometteurs",IF(LEFT(Table_Market[[#This Row],[RFM_SCORE]],1)="1","Inactifs",IF(AND(LEFT(Table_Market[[#This Row],[RFM_SCORE]],1)>="2",MID(Table_Market[[#This Row],[RFM_SCORE]],2,1)>="2",RIGHT(Table_Market[[#This Row],[RFM_SCORE]],1)>="2"),"Fidèles rentables","Occasionnels")))) -> Clients élites | U722: 769 | V722: 80 | W722: 252 | X722: 15 | Y722: 34 | Z722: 65 | AA722: 1 | AB722: 10 | AC722: 10 | AD722: 7 | AE722: 6 | AF722: 1 | AG722: 0 | AH722: 0 | AI722: 0 | AJ722: 0 | AK722: 0 | AL722: 3 | AM722: 11 | AN722: 1
A723: 7873 | B723: 1973 | C723: =YEAR(TODAY())-CLEAN!$B723 -> 52 | D723: 45-59 ans | E723: Doctorat | F723: Conjoint | G723: 63516 | H723: 1 | I723: 1 | J723: =CLEAN!$H723+CLEAN!$I723 -> 2 | K723: 41461 | L723: =YEAR(TODAY())-YEAR(CLEAN!$K723) -> 12 | M723: 30 | N723: =SUM(CLEAN!$AB723:$AE723) -> 17 | O723: =CLEAN!$U723+CLEAN!$V723+CLEAN!$W723+CLEAN!$X723+CLEAN!$Y723+CLEAN!$Z723 -> 300 | P723: =IF(CLEAN!$M723<=32,3,IF(CLEAN!$M723<=65,2,1)) -> 3 | Q723: =IF(Table_Market[[#This Row],[F_TOTAL_achat]]<=14,1,IF(Table_Market[[#This Row],[F_TOTAL_achat]]<=21,2,3)) -> 2 | R723: =IF(Table_Market[[#This Row],[M_TOTAL_dépensé]]<=115,1,IF(Table_Market[[#This Row],[M_TOTAL_dépensé]]<=833,2,3)) -> 2 | S723: =Table_Market[[#This Row],[R_SCORE]]&Table_Market[[#This Row],[F_SCORE]]&Table_Market[[#This Row],[M_SCORE]] -> 322 | T723: =IF(Table_Market[[#This Row],[RFM_SCORE]]="333","Clients élites",IF(LEFT(Table_Market[[#This Row],[RFM_SCORE]],1)="3","Récents prometteurs",IF(LEFT(Table_Market[[#This Row],[RFM_SCORE]],1)="1","Inactifs",IF(AND(LEFT(Table_Market[[#This Row],[RFM_SCORE]],1)>="2",MID(Table_Market[[#This Row],[RFM_SCORE]],2,1)>="2",RIGHT(Table_Market[[#This Row],[RFM_SCORE]],1)>="2"),"Fidèles rentables","Occasionnels")))) -> Récents prometteurs | U723: 141 | V723: 11 | W723: 114 | X723: 15 | Y723: 14 | Z723: 5 | AA723: 4 | AB723: 4 | AC723: 1 | AD723: 7 | AE723: 5 | AF723: 0 | AG723: 0 | AH723: 0 | AI723: 0 | AJ723: 0 | AK723: 0 | AL723: 3 | AM723: 11 | AN723: 0
...

Sheet PIVOT
A1: KPI'S
B3: Nombre de client | D3: CA TOTAL | F3: Panier moyen | H3: Nbr de visite web moyenne (mois dernier) | J3: Moyenne de Réponse dernière campagne
B4: 2211 | D4: 1340954 | F4: 606.49209 | H4: 5.3251922 | J4: 0.1501583
A6: Segmentation client (profil démographique)
A8: Nombre de ID | B8: Étiquettes de colonnes
A9: Étiquettes de lignes | B9: BAC ou études secondaires | C9: BAC+3 | D9: BAC+5 | E9: Doctorat
A10: 45-59 ans | B10: 0.023302938 | C10: 0.52077001 | D10: 0.25025329 | E10: 0.20567376
A11: 30-44 ans | B11: 0.055702918 | C11: 0.53050398 | D11: 0.25994695 | E11: 0.15384615
A12: 60 ans et + | B12: 0.010650888 | C12: 0.47455621 | D12: 0.2556213 | E12: 0.2591716
A13: 18-29 ans | B13: 0.5 | C13: 0 | D13: 0.5 | E13: 0
A14: Total général | B14: 0.024423338 | C14: 0.5042967 | D14: 0.25418363 | E14: 0.21709634
A31: Insight 1 : Chez les 18-29 ans, 50% des consommateurs sont de niveaux BAC ou études secondaires tandis que les 50% restants sont actuellement en BAC+5.
A32: Pour les 30-44, 45-59 et 60 et +, le niveaux d'études des clients qui prime est le BAC+3 avec une moyenne de 55%. Les BAC+5 representent quant à eux un peu moins d'un tiers du total,, contre peu de doctarant,
A35: Dépenses par catégorie de produits
I37: Répartition du chiffre d’affaires total par tranche d’âge (%)
A38: Étiquettes de lignes | B38: VINS | C38: SUCRERIES | D38: VIANDES | E38: POISSONS | F38: OR | G38: FRUITS | I38: Tranche d'âge | J38: Total CA | K38: % du Total CA | M38: =SUM(Tableau8[Total CA]) -> 1340954
A39: 18-29 ans | B39: 4.4471193e-06 | C39: 0.00041829103 | D39: 4.3376538e-05 | E39: 0.00021719195 | F39: 0.00059937169 | G39: 0.00030988534 | I39: 18–29 ans | J39: =SUMIF(Table_Market[Tranche_âge],"18-29 ans",Table_Market[M_TOTAL_dépensé]) -> 138 | K39: =J39/M38 -> 0.00010291181
A40: 30-44 ans | B40: 0.14245902 | C40: 0.17680325 | D40: 0.19124445 | E40: 0.1826343 | F40: 0.16382482 | G40: 0.18508763 | I40: 30–44 ans | J40: =SUMIF(Table_Market[Tranche_âge],"30-44 ans",Table_Market[M_TOTAL_dépensé]) -> 218952 | K40: =J40/M38 -> 0.16328077
A41: 45-59 ans | B41: 0.38880571 | C41: 0.40962404 | D41: 0.39074399 | E41: 0.39323809 | F41: 0.40790344 | G41: 0.40254106 | I41: 45–59 ans | J41: =SUMIF(Table_Market[Tranche_âge],"45-59 ans",Table_Market[M_TOTAL_dépensé]) -> 526343 | K41: =J41/M38 -> 0.39251384
A42: 60 ans et + | B42: 0.46873082 | C42: 0.41315442 | D42: 0.41796819 | E42: 0.42391042 | F42: 0.42767237 | G42: 0.41206143 | I42: 60 ans et + | J42: =SUMIF(Table_Market[Tranche_âge],"60 ans et +",Table_Market[M_TOTAL_dépensé]) -> 595521 | K42: =J42/M38 -> 0.44410248
A43: Total général | B43: 1 | C43: 1 | D43: 1 | E43: 1 | F43: 1 | G43: 1
A65: Insight 3 : Les 60 ans et + concentrent la majorité du chiffre d’affaires, dominé par le vin (47 %) et les produits de luxe (43 %).
A66: Les 45–59 ans présentent un profil similaire, tandis que les 30–44 ans dépensent davantage dans les produits du quotidien.
A67: Les 18–29 ans, quasi absents, représentent un segment à conquérir
A69: Analyse RFM — Structure et rentabilité des segments clients - Fidélité & valeur client (RFM simplifié)
A73: Étiquettes de lignes | B73: Nombre de clients | C73: % du CA / nombre clients | I73: TYPE | J73: 1ère BORNE | K73: 2ème BORNE
A74: Inactifs | B74: 733 | C74: 0.33658649 | I74: Récence | J74: =_xlfn.PERCENTILE.INC(CLEAN!$M$2:$M$2212,1/3) -> 32 | K74: =_xlfn.PERCENTILE.INC(CLEAN!$M$2:$M$2212,2/3) -> 65
A75: Récents prometteurs | B75: 602 | C75: 0.18609363 | I75: Total_Achat | J75: =_xlfn.PERCENTILE.INC(CLEAN!$N$2:$N$2212,1/3) -> 14 | K75: =_xlfn.PERCENTILE.INC(CLEAN!$N$2:$N$2212,2/3) -> 21
A76: Fidèles rentables | B76: 430 | C76: 0.30622005 | I76: Total_DÉPENSÉ | J76: =_xlfn.PERCENTILE.INC(CLEAN!$O$2:$O$2212,1/3) -> 114.66667 | K76: =_xlfn.PERCENTILE.INC(CLEAN!$O$2:$O$2212,2/3) -> 833
A77: Occasionnels | B77: 292 | C77: 0.01956965
A78: Clients élites | B78: 154 | C78: 0.15153018
A79: Total général | B79: 2211 | C79: 1
A95: Insight 3 : 70 % du CA est généré par moins d’un tiers des clients — priorité à la fidélisation et à la réactivation sélective.
A96: Les Fidèles Premium – clients réguliers et à forte valeur, véritable moteur du chiffre d’affaires (31 %).
A97: • Les À réactiver – une large base dormante (34 % du CA, 733 clients) qui représente un levier de croissance sous-exploité.
A98: En parallèle, le segment VIP 333 (seulement 154 clients) affiche un pouvoir d’achat exceptionnel : chaque VIP dépense en moyenne 2,5 fois plus qu’un client standard.
A99: Ces résultats invitent à concentrer les efforts marketing sur la fidélisation des Premiums et la réactivation ciblée des dormants à fort potentiel.
A101: Étiquettes de lignes | B101: Nombre de clients
A102: Inactifs | B102: 0.3315242
A103: Récents prometteurs | B103: 0.27227499
A104: Fidèles rentables | B104: 0.19448213
A105: Occasionnels | B105: 0.13206694
A106: Clients élites | B106: 0.069651741
A107: Total général | B107: 1
A122: Insight 3 bis : Les segments “À réactiver” (33 %) et “Nouveaux prometteurs” (27 %) représentent la majorité des clients.
A123: Les “Fidèles Premium” et “VIP 333”, bien que minoritaires (26 %), concentrent la clientèle la plus engagée.
A124: Objectif : transformer les nouveaux clients en fidèles, tout en réactivant les inactifs.
A126: La base client montre un profil en évolution :
A127: un grand nombre de clients à réengager (33 %) coexiste avec une proportion prometteuse de nouveaux entrants (27 %).
A128: Les segments à forte valeur — “Fidèles Premium” et “VIP 333” — ne représentent qu’un quart de la clientèle, mais constituent le moteur futur du chiffre d’affaires.
A129: L’enjeu marketing est double : réactiver les anciens et fidéliser les récents.
A132: Campagne marketing
A135: Étiquettes de lignes | B135: % de répondants | D135: Campagnes | E135: Réponses positives
A136: Cmp1 | B136: 0.14242424 | D136: Cmp1 | E136: =COUNTIF(Table_Market[Campagne1Acceptée],1) -> 141
A137: Cmp2 | B137: 0.03030303 | D137: Cmp2 | E137: =COUNTIF(Table_Market[Campagne2Acceptée],1) -> 30
A138: Cmp3 | B138: 0.16464646 | D138: Cmp3 | E138: =COUNTIF(Table_Market[Campagne3Acceptée],1) -> 163
A139: Cmp4 | B139: 0.16565657 | D139: Cmp4 | E139: =COUNTIF(Table_Market[Campagne4Acceptée],1) -> 164
A140: Cmp5 | B140: 0.16161616 | D140: Cmp5 | E140: =COUNTIF(Table_Market[Campagne5Acceptée],1) -> 160
A141: Réponse à la dernière cmp | B141: 0.33535354 | D141: Réponse à la dernière cmp | E141: =COUNTIF(Table_Market[Réponse dernière campagne],1) -> 332
A142: Total général | B142: 1
A156: Insight 4 : La dernière campagne (“Response”) affiche le meilleur taux de conversion (34 %), signe d’une amélioration continue des performances marketing.

Sheet DASHBOARD

Sheet AUDIT
A1: TERCILES 1,2,3
A2: Modèle RFM
A4: J’ai conçu un modèle RFM simple dans Excel pour segmenter la base client selon la récence, la fréquence et le montant d’achat.
A5: Cela m’a permis d’identifier les segments les plus rentables et de formuler des recommandations marketing concrètes.
A6: Ce projet illustre ma capacité à relier la donnée à la stratégie business.
A8: Calcul des seuils R, F, M via PERCENTILE.INC pour définir 3 segments clients (1 = faible, 3 = élevé)
A16: RFM_Score | B16: Interprétation marketing
A17: 333 | B17: Client idéal : récent, fidèle, dépensier 🏆 | C17: Position | D17: Signifie | E17: Exemple (333)
A18: 331 / 323 | B18: Client fidèle et régulier, dépense correcte 👍 | C18: 1er chiffre | D18: R = Récence | E18: 3 → client récent
A19: 311 / 312 | B19: Client fidèle mais ancien, à surveiller 👀 | C19: 2e chiffre | D19: F = Fréquence | E19: 3 → achète souvent
A20: 133 / 123 | B20: Nouveau client prometteur 🌱 | C20: 3e chiffre | D20: M = Montant | E20: 3 → dépense beaucoup
A21: 111 | B21: Client inactif ou à réactiver 💤

Sheet RÉSUMÉ
